Workbook
Name K_LevyCap: Assumptions!$C$7
Name K_ResTrail: Assumptions!$C$8
Name K_ComTrail: Assumptions!$C$9
Name K_TrendRate: Assumptions!$C$10
Name K_ResNewShare: Assumptions!$C$11
Name K_ComNewShare: Assumptions!$C$12
Name K_PP: Assumptions!$C$13
Name K_ResNewPct: Assumptions!$C$14
Name K_ResRenoPct: Assumptions!$C$15
Name K_ComNewPct: Assumptions!$C$16
Name K_ComRenoPct: Assumptions!$C$17
Name K_TownNG: Assumptions!$C$18
Name K_Perm27: Assumptions!$C$19
Name K_Perm27Lo: Assumptions!$C$20
Name K_Perm27Hi: Assumptions!$C$21
Name K_Perm28: Assumptions!$C$22
Name K_Perm28Lo: Assumptions!$C$23
Name K_Perm28Hi: Assumptions!$C$24
Name K_NG2026: Assumptions!$C$25
Name Levy2025: Assumptions!$C$26
Name K_HomesPace: Assumptions!$C$29
Name K_ResValUnit: Assumptions!$C$30
Name K_ResApp: Assumptions!$C$31
Name K_ComValSqft: Assumptions!$C$32
Name K_ComApp: Assumptions!$C$33
Name K_ResTax: Assumptions!$C$34
Name K_ComTax: Assumptions!$C$35
Name K_ResValShare: Assumptions!$C$36
Name K_LevyGrowth: Assumptions!$C$37
Name K_BlendApp: Assumptions!$C$38
Name K_PermitRate26: Assumptions!$C$41
Name K_PermitRate27: Assumptions!$C$42
Name K_Permits2025: Assumptions!$C$43
Name K_Inv2019: Assumptions!$C$44
Name K_Inv2025: Assumptions!$C$45
Name K_InvEst2025: Assumptions!$C$46
Name K_InvFlat: Assumptions!$C$47
Name K_Meals2019: Assumptions!$C$48
Name K_Meals2025: Assumptions!$C$49
Name K_MealsGrowth: Assumptions!$C$50
Name K_MealsPerSqft: Assumptions!$C$51
Name R_LRresid2025: Assumptions!$C$52
Name R_LRbase: Assumptions!$C$53
Name R_SA2026: Assumptions!$C$54
Name R_SA2027: Assumptions!$C$55
Name R_SAbase: Assumptions!$C$56
Name R_BudgetRatio: Assumptions!$C$59
Name R_OtherSurplus: Assumptions!$C$60
Name R_ApprShare: Assumptions!$C$61
Name K_ChcaStart: Assumptions!$C$64
Name K_ChcaSpan: Assumptions!$C$65
Name K_ChcaDollarYr: Assumptions!$C$66
Name K_ChcaUnits: Assumptions!$C$67
Name K_ChcaSPU: Assumptions!$C$68
Name K_ChcaEmp: Assumptions!$C$69
Name K_pD: Assumptions!$C$72
Name K_psD: Assumptions!$C$73
Name K_TownFTE: Assumptions!$C$74
Name K_BasePay: Assumptions!$C$75
Name K_BenLoad: Assumptions!$C$76

Sheet Start here
A1: Brookline's finances to 2040: the forecast as a spreadsheet
A3: What this is
A5: This workbook is the Forecast Explorer (brooklinefuture.org/forecast/explorer) in spreadsheet form. It runs the same forecast, from the same numbers, with every step a formula you can follow.
A6: How to use it
A7: 1. Go to Settings and change any yellow cell. Each setting is a control on the Explorer, with the same choices.
A8: 2. Read the result on Forecast: revenue, spending and the room (revenue minus spending) for every year to FY2040. A negative room means spending runs ahead of revenue that year.
A9: 3. To start over, copy the Base case column on Settings back into Your value.
A10: The sheets
A11: Settings: the 23 settings, their base case values and allowed ranges, and, below them, how the model reads each one.
A12: Forecast: the results at the top, then every working step the model takes, row by row, in the order the Explorer's engine takes them.
A13: Revenue build: property tax year by year. Last year's levy limit, plus 2.5%, plus new growth in five kinds, plus the May 2026 override; then the homes and commercial space that new growth stands for, and the permit fees and meals tax that come with it.
A14: Worked example: one year, FY2033, followed step by step from the levy to the room, every number a live cell.
... A27: Voter-approved debt exclusions run through the General Fund but pay for nothing except their own building debt, so the forecast sets them aside on both the revenue and the spending side; they would add the same amount to each.

Sheet Settings
A1: Settings
A2: Change the yellow cells; the Forecast sheet updates. Each setting matches a control on the Forecast Explorer, with the same choices. To return to the base case, copy the Base case column back into Your value.
A4: Setting | B4: Your value | C4: Base case | D4: Allowed | E4: Works out to | F4: What it means
A6: The big six
A7: Pay raises compared with the base case | B7: 0 | C7: 0 | D7: -1.5 to +2.0 points | E7: =PayTown | F7: Moves every employee group's yearly raise by the same amount. The base case starts from the Town's 3.0% bargaining target, with schools and Public Safety above it (next group).
A8: Pension savings after full funding | B8: Moved to retiree health (OPEB), the Town's plan; once it's paid off, held for a decision | C8: Moved to retiree health (OPEB), the Town's plan; once it's paid off, held for a decision | D8: Choose from the list | F8: The pension system reaches full funding in FY2030. The Town plans to use the money it stops paying toward pensions to pay down its retiree health (OPEB) liability instead. Once that is paid off, the base case keeps the money in the budget for a decision then; the second choice counts it as room.
A9: School staff as enrollment falls | B9: Fall half as fast as enrollment, as in FY2019 to FY2025 | C9: Fall half as fast as enrollment, as in FY2019 to FY2025 | D9: Choose from the list | F9: From FY2019 to FY2025 enrollment fell 10.6% and school staff 5.0%, about half as fast. The base case continues that pattern; students from new homes are staffed in full. The School Department's own plan holds staff at the FY2027 level.
A10: Health premium growth, FY2030 on | B10: 0.08 | C10: 0.08 | D10: 5% to 12% | F10: Yearly rise in health insurance premiums. The 25-year average is 6.5%; recent years ran 10 to 12%.
A11: Property tax new growth, tenths of a point above the recent trend | B11: 0 | C11: 0 | D11: -6 to 13 | E11: =GrowthRate | F11: Tax base added each year by construction, renovation and business equipment, as a share of last year's levy. 0 is the recent trend; each step is a tenth of a percentage point.
A12: New homes built | B12: As expected | C12: As expected | D12: Choose from the list | F12: Scales only the new-homes part of new growth (about a sixth of it), including any added growth above; renovation, commercial space and business equipment continue at their pace. The enrollment forecast is left as it is.
A14: The next five
A15: School pay above the Town target | B15: 0.007 | C15: 0.007 | D15: 0 to 2.5 points | E15: =PayTown+SchDrift | F15: The base case puts school pay 0.7 point above the Town target (3.7%). The schools' own forecast implies about 2 points.
A16: Public Safety pay above the Town target | B16: 0.005 | C16: 0.005 | D16: 0 to 2.5 points | E16: =PayTown+PSPrem | F16: The base case puts Public Safety pay 0.5 point above the target (3.5%). Police and fire cost per position grew about 3.3% a year from FY2011 to FY2025; the agreed fire steps and police refills are counted on top.
A17: Local receipts growth | B17: 0.017648984 | C17: 0.017648984 | D17: 1% to 6% | F17: Fees, excise and other local revenue, apart from meals tax and building permits. Base: the FY2019 to FY2025 rate.
A18: Inflation | B18: 0.025 | C18: 0.025 | D18: 1.5% to 5% | F18: Price growth for everything that is not pay: supplies, utilities, contracts.
A19: State aid growth | B19: 0.025 | C19: 0.025 | D19: 0% to 6% | F19: Chapter 70 school aid and unrestricted local aid, from the adopted FY2027 figure. Base: 2.5%, the Town plan's rate.
A21: Everything else
A22: Where added growth comes from | B22: Today's mix | C22: Today's mix | D22: Choose from the list | F22: Only matters when new growth is set above the recent trend. New homes add students and services; commercial space pays a higher tax rate and costs less to serve.
A23: Students from added homes | B23: Each brings new staff at today's ratio | C23: Each brings new staff at today's ratio | D23: Choose from the list | F23: Students from added homes can fill seats left open as enrollment falls: all of them with staff held at the FY2027 level, half of them with staff falling half as fast. Has no effect when staff follow enrollment fully.
A24: School enrollment forecast | B24: NESDEC (declines) | C24: NESDEC (declines) | D24: Choose from the list | F24: Which enrollment path the schools serve.
A25: Families moving in, change in each class a year | B25: 0 | C25: 0 | D25: -1 to +2 points | F25: How much each class grows or shrinks each year from families moving in and out, beyond what NESDEC assumes, for children of every age from birth on, so kindergartners per birth move with it. Since COVID classes have grown about 0.35 point a year faster than NESDEC assumes. Changes the NESDEC path only.
A26: Health premium growth, FY2028 and FY2029 | B26: 0.12 | C26: 0.12 | D26: 6% to 14% | F26: The Town's own forecast for the next two years.
A27: School non-personnel costs above inflation | B27: 0 | C27: 0 | D27: 0 to 3 points | F27: Special education placements and transportation have at times grown faster than prices in general.
A28: Capital funding | B28: The 6.6% policy, from FY2028 | C28: The 6.6% policy, from FY2028 | D28: Choose from the list | F28: The Select Board's policy puts 6.6% of the prior year's net revenue into capital from FY2028; holding capital at the Town's six-year table's dollars comes to about 6% of this forecast's net revenue.
A29: Town cost of serving a new home (FY2025 $) | B29: 660 | C29: 660 | D29: $200 to $1,200 | F29: Town department cost per added home a year, before schools. The forecast leaves out fire's share, about a fifth, since fire is counted in steps under Police and fire staffing, and police's share too when police grow with homes.
A30: Police and fire staffing | B30: FY2027 budget, plus a fire company at about 31,200 homes | C30: FY2027 budget, plus a fire company at about 31,200 homes | D30: Choose from the list | F30: The FY2027 budget funds 128 sworn police and 160 firefighters. A fire company (20 firefighters) is added when the town reaches about 31,200 homes. Police growing with homes keeps 4.42 officers per 1,000 homes; restoring earlier staffing adds 16 positions from FY2028.
A31: Chestnut Hill redevelopment | B31: Approved program, Town Meeting May 2026 | C31: Approved program, Town Meeting May 2026 | D31: Choose from the list | F31: 266 homes and a 200-room hotel, arriving FY2032 to FY2034. The estimates differ only in revenue.
A32: Pension full funding slips | B32: On schedule, FY2030 | C32: On schedule, FY2030 | D32: Choose from the list | F32: If investment returns fall short, full pension contributions continue for longer.
A33: New growth in FY2027 and FY2028 | B33: The recent trend (the base case) | C33: The recent trend (the base case) | D33: Choose from the list | F33: Building permits show new growth about two years ahead. The 2024 and 2025 permits point to real estate new growth well below the trend in FY2027 and FY2028; business equipment stays at its trend. The shortfall then carries through every later levy. The Explorer does not have this setting.
A34: A further override (first-year dollars) | B34: 0 | C34: 0 | D34: $0 to $30,000,000 | F34: An operating override added to the levy, growing 2.5% a year after. The forecast itself never assumes one.
A35: First year of that override | B35: 2031 | C35: 2031 | D35: 2029 to 2035 | F35: Only matters when the override above is more than zero.
A37: How the model reads these settings (worked out, do not edit)
A38: Each line turns a choice above into the value the Forecast sheet uses.
A39: Pay growth, Town staff | B39: =K_BasePay+In_pay
A40: Public Safety above the target | B40: =In_ps_premium
A41: Schools above the target | B41: =In_school_drift
A42: Health premiums, FY2030 on | B42: =In_premium_long
A43: Health premiums, FY2028 and FY2029 | B43: =In_premium_near
A44: Inflation | B44: =In_cpi
A45: School non-personnel above inflation | B45: =In_np_extra
A46: Town cost of a new home | B46: =In_cost_home
A47: State aid growth | B47: =In_sa
A48: Local receipts growth | B48: =In_lr
A49: Pension savings move to OPEB (1 yes, 0 no) | B49: =IF(INDEX(Data!$D$42:$D$44,MATCH(In_opeb,Data!$C$42:$C$44,0))="keep",0,1)
A50: Money freed by the OPEB payoff held for a decision (1 yes, 0 no) | B50: =IF(INDEX(Data!$D$42:$D$44,MATCH(In_opeb,Data!$C$42:$C$44,0))="redirect",1,0)
A51: School staffing rule | B51: =INDEX(Data!$D$45:$D$48,MATCH(In_staffing,Data!$C$45:$C$48,0))
A52: Growth mix | B52: =INDEX(Data!$D$49:$D$52,MATCH(In_mix,Data!$C$49:$C$52,0))
A53: Students fill open seats (1 yes, 0 no) | B53: =IF(INDEX(Data!$D$56:$D$57,MATCH(In_fill,Data!$C$56:$C$57,0))="fill",1,0)
A54: Share of expected new homes built | B54: =IF(INDEX(Data!$D$53:$D$55,MATCH(In_homes,Data!$C$53:$C$55,0))="half",0.5,IF(INDEX(Data!$D$53:$D$55,MATCH(In_homes,Data!$C$53:$C$55,0))="none",0,1))
A55: Enrollment path | B55: =INDEX(Data!$D$58:$D$60,MATCH(In_enroll,Data!$C$58:$C$60,0))
A56: Families moving in, change in each class a year | B56: =In_migration
A57: Capital at the full policy (1 yes, 0 no) | B57: =IF(INDEX(Data!$D$61:$D$62,MATCH(In_capital,Data!$C$61:$C$62,0))="full",1,0)
A58: Chestnut Hill estimate | B58: =INDEX(Data!$D$63:$D$66,MATCH(In_chca,Data!$C$63:$C$66,0))
A59: New growth in FY2027 and FY2028 | B59: =INDEX(Data!$D$71:$D$74,MATCH(In_ng2728,Data!$C$71:$C$74,0))
A60: Chestnut Hill counted on top of trend (1 yes, 0 no) | B60: =IF(ChcaEstimate="in_trend",0,1)
A61: Years pension full funding slips | B61: =INDEX(Data!$D$75:$D$78,MATCH(In_slip,Data!$C$75:$C$78,0))
A62: Fire company added at the threshold (1 yes, 0 no) | B62: =IF(INDEX(Data!$D$67:$D$70,MATCH(In_ps_staff,Data!$C$67:$C$70,0))="none",0,1)
A63: Police and fire restored to earlier staffing (1 yes, 0 no) | B63: =IF(INDEX(Data!$D$67:$D$70,MATCH(In_ps_staff,Data!$C$67:$C$70,0))="restore",1,0)
A64: Police grow with homes at the peer ratio (1 yes, 0 no) | B64: =IF(INDEX(Data!$D$67:$D$70,MATCH(In_ps_staff,Data!$C$67:$C$70,0))="police",1,0)
A65: New growth step, tenths of a point | B65: =In_growth
A66: New growth rate, share of last year's levy | B66: =K_TrendRate+GrowthStep*0.001
A67: Further override, first-year dollars | B67: =In_ov_amt
A68: Further override, first year | B68: =In_ov_year

Sheet Forecast
A1: Forecast, FY2027 to FY2040
A2: Revenue and spending of the General Fund, with voter-approved debt exclusions set aside on both sides. Everything here is a live formula driven by the Settings sheet, the Revenue build sheet and the Assumptions sheet. FY2026 appears only because the free cash cycle and new growth start from it.
C4: 2026 | D4: 2027 | E4: 2028 | F4: 2029 | G4: 2030 | H4: 2031 | I4: 2032 | J4: 2033 | K4: 2034 | L4: 2035 | M4: 2036 | N4: 2037 | O4: 2038 | P4: 2039 | Q4: 2040
A6: Revenue
A7: Property tax (debt exclusions set aside) | D7: =D47-D48 | E7: =E47-E48 | F7: =F47-F48 | G7: =G47-G48 | H7: =H47-H48 | I7: =I47-I48 | J7: =J47-J48 | K7: =K47-K48 | ... Q7: =Q47-Q48
A8: State aid | D8: =D72 | E8: =E72 | F8: =F72 | G8: =G72 | H8: =H72 | I8: =I72 | J8: =J72 | K8: =K72 | ... Q8: =Q72
A9: Local receipts, as budgeted | D9: =D76 | E9: =E76 | F9: =F76 | G9: =G76 | H9: =H76 | I9: =I76 | J9: =J76 | K9: =K76 | ... Q9: =Q76
A10: Free cash | D10: =D77 | E10: =E77 | F10: =F77 | G10: =G77 | H10: =H77 | I10: =I77 | J10: =J77 | K10: =K77 | ... Q10: =Q77
A11: Other available funds | D11: =D49 | E11: =E49 | F11: =F49 | G11: =G49 | H11: =H49 | I11: =I49 | J11: =J49 | K11: =K49 | ... Q11: =Q49
A12: A further override | D12: =D74 | E12: =E74 | F12: =F74 | G12: =G74 | H12: =H74 | I12: =I74 | J12: =J74 | K12: =K74 | ... Q12: =Q74
A13: Total revenue | D13: =D78-D48 | E13: =E78-E48 | F13: =F78-F48 | G13: =G78-G48 | H13: =H78-H48 | I13: =I78-I48 | J13: =J78-J48 | K13: =K78-K48 | ... Q13: =Q78-Q48
A15: Spending
A16: Town departments, today's services | D16: =A_TD*(K_pD*D66+(1-K_pD)*D58)+D37 | E16: =A_TD*(K_pD*E66+(1-K_pD)*E58)+E37 | F16: =A_TD*(K_pD*F66+(1-K_pD)*F58)+F37 | G16: =A_TD*(K_pD*G66+(1-K_pD)*G58)+G37 | H16: =A_TD*(K_pD*H66+(1-K_pD)*H58)+H37 | I16: =A_TD*(K_pD*I66+(1-K_pD)*I58)+I37 | J16: =A_TD*(K_pD*J66+(1-K_pD)*J58)+J37 | K16: =A_TD*(K_pD*K66+(1-K_pD)*K58)+K37 | ... Q16: =A_TD*(K_pD*Q66+(1-K_pD)*Q58)+Q37
A17: Town services for added homes and businesses | D17: =(D34*CostHome*(1-K_PSShare*(FireStep*(1-K_PSSharePol)+PoliceStep*K_PSSharePol))+D67*K_CostPerEmp)*PayToFY27*D55+D36+D39 | E17: =(E34*CostHome*(1-K_PSShare*(FireStep*(1-K_PSSharePol)+PoliceStep*K_PSSharePol))+E67*K_CostPerEmp)*PayToFY27*E55+K_Permit*MAX(E45/E46-1,0)*E55+E36+E39 | F17: =(F34*CostHome*(1-K_PSShare*(FireStep*(1-K_PSSharePol)+PoliceStep*K_PSSharePol))+F67*K_CostPerEmp)*PayToFY27*F55+K_Permit*MAX(F45/F46-1,0)*F55+F36+F39 | G17: =(G34*CostHome*(1-K_PSShare*(FireStep*(1-K_PSSharePol)+PoliceStep*K_PSSharePol))+G67*K_CostPerEmp)*PayToFY27*G55+K_Permit*MAX(G45/G46-1,0)*G55+G36+G39 | H17: =(H34*CostHome*(1-K_PSShare*(FireStep*(1-K_PSSharePol)+PoliceStep*K_PSSharePol))+H67*K_CostPerEmp)*PayToFY27*H55+K_Permit*MAX(H45/H46-1,0)*H55+H36+H39 | I17: =(I34*CostHome*(1-K_PSShare*(FireStep*(1-K_PSSharePol)+PoliceStep*K_PSSharePol))+I67*K_CostPerEmp)*PayToFY27*I55+K_Permit*MAX(I45/I46-1,0)*I55+I36+I39 | J17: =(J34*CostHome*(1-K_PSShare*(FireStep*(1-K_PSSharePol)+PoliceStep*K_PSSharePol))+J67*K_CostPerEmp)*PayToFY27*J55+K_Permit*MAX(J45/J46-1,0)*J55+J36+J39 | K17: =(K34*CostHome*(1-K_PSShare*(FireStep*(1-K_PSSharePol)+PoliceStep*K_PSSharePol))+K67*K_CostPerEmp)*PayToFY27*K55+K_Permit*MAX(K45/K46-1,0)*K55+K36+K39 | L17: =(L34*CostHome*(1-K_PSShare*(FireStep*(1-K_PSSharePol)+PoliceStep*K_PSSharePol))+L67*K_CostPerEmp)*PayToFY27*L55+K_Permit*MAX(L45/L46-1,0)*L55+L36+L39 | ... Q17: =(Q34*CostHome*(1-K_PSShare*(FireStep*(1-K_PSSharePol)+PoliceStep*K_PSSharePol))+Q67*K_CostPerEmp)*PayToFY27*Q55+K_Permit*MAX(Q45/Q46-1,0)*Q55+Q36+Q39
A18: Schools | D18: =A_Sch*(K_SPS*D57*D33/Staff27+(1-K_SPS)*D59*((1-K_V)+K_V*D32/Enroll27))+D63*(K_FillSeat-A_Sch*(1-K_SPS)*K_V/Enroll27)*D57/$D$57 | E18: =A_Sch*(K_SPS*E57*E33/Staff27+(1-K_SPS)*E59*((1-K_V)+K_V*E32/Enroll27))+E63*(K_FillSeat-A_Sch*(1-K_SPS)*K_V/Enroll27)*E57/$D$57 | F18: =A_Sch*(K_SPS*F57*F33/Staff27+(1-K_SPS)*F59*((1-K_V)+K_V*F32/Enroll27))+F63*(K_FillSeat-A_Sch*(1-K_SPS)*K_V/Enroll27)*F57/$D$57 | G18: =A_Sch*(K_SPS*G57*G33/Staff27+(1-K_SPS)*G59*((1-K_V)+K_V*G32/Enroll27))+G63*(K_FillSeat-A_Sch*(1-K_SPS)*K_V/Enroll27)*G57/$D$57 | H18: =A_Sch*(K_SPS*H57*H33/Staff27+(1-K_SPS)*H59*((1-K_V)+K_V*H32/Enroll27))+H63*(K_FillSeat-A_Sch*(1-K_SPS)*K_V/Enroll27)*H57/$D$57 | I18: =A_Sch*(K_SPS*I57*I33/Staff27+(1-K_SPS)*I59*((1-K_V)+K_V*I32/Enroll27))+I63*(K_FillSeat-A_Sch*(1-K_SPS)*K_V/Enroll27)*I57/$D$57 | J18: =A_Sch*(K_SPS*J57*J33/Staff27+(1-K_SPS)*J59*((1-K_V)+K_V*J32/Enroll27))+J63*(K_FillSeat-A_Sch*(1-K_SPS)*K_V/Enroll27)*J57/$D$57 | K18: =A_Sch*(K_SPS*K57*K33/Staff27+(1-K_SPS)*K59*((1-K_V)+K_V*K32/Enroll27))+K63*(K_FillSeat-A_Sch*(1-K_SPS)*K_V/Enroll27)*K57/$D$57 | ... Q18: =A_Sch*(K_SPS*Q57*Q33/Staff27+(1-K_SPS)*Q59*((1-K_V)+K_V*Q32/Enroll27))+Q63*(K_FillSeat-A_Sch*(1-K_SPS)*K_V/Enroll27)*Q57/$D$57
A19: Health insurance | D19: =A_GH*D71*D60 | E19: =A_GH*E71*E60 | F19: =A_GH*F71*F60 | G19: =A_GH*G71*G60 | H19: =A_GH*H71*H60 | I19: =A_GH*I71*I60 | J19: =A_GH*J71*J60 | K19: =A_GH*K71*K60 | ... Q19: =A_GH*Q71*Q60
A20: Benefits for staff added by growth | D20: =(D17-D36-D39)*K_BenLoad | E20: =(E17-E36-E39)*K_BenLoad | F20: =(F17-F36-F39)*K_BenLoad | G20: =(G17-G36-G39)*K_BenLoad | H20: =(H17-H36-H39)*K_BenLoad | I20: =(I17-I36-I39)*K_BenLoad | J20: =(J17-J36-J39)*K_BenLoad | K20: =(K17-K36-K39)*K_BenLoad | ... Q20: =(Q17-Q36-Q39)*K_BenLoad
A21: Pensions | D21: =A_Pen | E21: =E69 | F21: =F69 | G21: =IF(AND(PensionSlip>0,G$4>=2030,G$4<=2030+PensionSlip),PenNC30+PenSlipPay,G69) | H21: =IF(AND(PensionSlip>0,H$4>=2030,H$4<=2030+PensionSlip),H69+PenSlipPay,H69) | I21: =IF(AND(PensionSlip>0,I$4>=2030,I$4<=2030+PensionSlip),I69+PenSlipPay,I69) | J21: =IF(AND(PensionSlip>0,J$4>=2030,J$4<=2030+PensionSlip),J69+PenSlipPay,J69) | K21: =IF(AND(PensionSlip>0,K$4>=2030,K$4<=2030+PensionSlip),K69+PenSlipPay,K69) | L21: =IF(AND(PensionSlip>0,L$4>=2030,L$4<=2030+PensionSlip),L69+PenSlipPay,L69) | M21: =IF(AND(PensionSlip>0,M$4>=2030,M$4<=2030+PensionSlip),M69+PenSlipPay,M69) | N21: =IF(AND(PensionSlip>0,N$4>=2030,N$4<=2030+PensionSlip),N69+PenSlipPay,N69) | O21: =IF(AND(PensionSlip>0,O$4>=2030,O$4<=2030+PensionSlip),O69+PenSlipPay,O69) | ... Q21: =IF(AND(PensionSlip>0,Q$4>=2030,Q$4<=2030+PensionSlip),Q69+PenSlipPay,Q69)
A22: Retiree health (OPEB) | D22: =A_OPEB | E22: =IF(AND(OpebHold=1,Redirect=1),E85,E86) | F22: =IF(AND(OpebHold=1,Redirect=1),F85,F86) | G22: =IF(AND(OpebHold=1,Redirect=1),G85,G86) | H22: =IF(AND(OpebHold=1,Redirect=1),H85,H86) | I22: =IF(AND(OpebHold=1,Redirect=1),I85,I86) | J22: =IF(AND(OpebHold=1,Redirect=1),J85,J86) | K22: =IF(AND(OpebHold=1,Redirect=1),K85,K86) | L22: =IF(AND(OpebHold=1,Redirect=1),L85,L86) | ... Q22: =IF(AND(OpebHold=1,Redirect=1),Q85,Q86)
A23: Other benefits | D23: =A_OB | E23: =Data!E28 | F23: =Data!F28 | G23: =Data!G28 | H23: =Data!H28 | I23: =Data!$H$28*I68/$H$68 | J23: =Data!$H$28*J68/$H$68 | K23: =Data!$H$28*K68/$H$68 | L23: =Data!$H$28*L68/$H$68 | M23: =Data!$H$28*M68/$H$68 | N23: =Data!$H$28*N68/$H$68 | O23: =Data!$H$28*O68/$H$68 | P23: =Data!$H$28*P68/$H$68 | Q23: =Data!$H$28*Q68/$H$68
A24: Debt within the levy | D24: =A_Debt | E24: =Data!E29 | F24: =Data!F29 | G24: =Data!G29 | H24: =Data!H29 | I24: =Data!I29 | J24: =Data!$I$29*(1+K_DebtGrowth)^(J$4-2032) | K24: =Data!$I$29*(1+K_DebtGrowth)^(K$4-2032) | L24: =Data!$I$29*(1+K_DebtGrowth)^(L$4-2032) | M24: =Data!$I$29*(1+K_DebtGrowth)^(M$4-2032) | N24: =Data!$I$29*(1+K_DebtGrowth)^(N$4-2032) | O24: =Data!$I$29*(1+K_DebtGrowth)^(O$4-2032) | P24: =Data!$I$29*(1+K_DebtGrowth)^(P$4-2032) | Q24: =Data!$I$29*(1+K_DebtGrowth)^(Q$4-2032)
A25: Capital, reserves and other | D25: =A_Other | E25: =Data!E30+IF(CapFull=1,MAX(K_CIP*D79-E24-Data!E31,0),0)+K_Reserve*D79-Data!E32+E77-(Data!E34+K_FCDeposit*Data!E33+K_FCReserve*D79) | F25: =Data!F30+IF(CapFull=1,MAX(K_CIP*E79-F24-Data!F31,0),0)+K_Reserve*E79-Data!F32+F77-(Data!F34+K_FCDeposit*Data!F33+K_FCReserve*E79) | G25: =Data!G30+IF(CapFull=1,MAX(K_CIP*F79-G24-Data!G31,0),0)+K_Reserve*F79-Data!G32+G77-(Data!G34+K_FCDeposit*Data!G33+K_FCReserve*F79) | H25: =Data!H30+IF(CapFull=1,MAX(K_CIP*G79-H24-Data!H31,0),0)+K_Reserve*G79-Data!H32+H77-(Data!H34+K_FCDeposit*Data!H33+K_FCReserve*G79) | I25: =Data!I30+IF(CapFull=1,MAX(K_CIP*H79-I24-Data!I31,0),0)+K_Reserve*H79-Data!H32+K_GenFY31*(H79/$G$79-1)+K_NonAppFY31*((1+K_NonAppG)^(I$4-2031)-1)+I77-(Data!I34+K_FCDeposit*K_GenFY31*H79/$G$79+K_FCReserve*H79) | J25: =Data!J30+IF(CapFull=1,MAX(K_CIP*I79-J24-Data!J31,0),0)+K_Reserve*I79-Data!H32+K_GenFY31*(I79/$G$79-1)+K_NonAppFY31*((1+K_NonAppG)^(J$4-2031)-1)+J77-(Data!J34+K_FCDeposit*K_GenFY31*I79/$G$79+K_FCReserve*I79) | K25: =Data!K30+IF(CapFull=1,MAX(K_CIP*J79-K24-Data!K31,0),0)+K_Reserve*J79-Data!H32+K_GenFY31*(J79/$G$79-1)+K_NonAppFY31*((1+K_NonAppG)^(K$4-2031)-1)+K77-(Data!K34+K_FCDeposit*K_GenFY31*J79/$G$79+K_FCReserve*J79) | L25: =Data!L30+IF(CapFull=1,MAX(K_CIP*K79-L24-Data!L31,0),0)+K_Reserve*K79-Data!H32+K_GenFY31*(K79/$G$79-1)+K_NonAppFY31*((1+K_NonAppG)^(L$4-2031)-1)+L77-(Data!L34+K_FCDeposit*K_GenFY31*K79/$G$79+K_FCReserve*K79) | M25: =Data!M30+IF(CapFull=1,MAX(K_CIP*L79-M24-Data!M31,0),0)+K_Reserve*L79-Data!H32+K_GenFY31*(L79/$G$79-1)+K_NonAppFY31*((1+K_NonAppG)^(M$4-2031)-1)+M77-(Data!M34+K_FCDeposit*K_GenFY31*L79/$G$79+K_FCReserve*L79) | N25: =Data!N30+IF(CapFull=1,MAX(K_CIP*M79-N24-Data!N31,0),0)+K_Reserve*M79-Data!H32+K_GenFY31*(M79/$G$79-1)+K_NonAppFY31*((1+K_NonAppG)^(N$4-2031)-1)+N77-(Data!N34+K_FCDeposit*K_GenFY31*M79/$G$79+K_FCReserve*M79) | O25: =Data!O30+IF(CapFull=1,MAX(K_CIP*N79-O24-Data!O31,0),0)+K_Reserve*N79-Data!H32+K_GenFY31*(N79/$G$79-1)+K_NonAppFY31*((1+K_NonAppG)^(O$4-2031)-1)+O77-(Data!O34+K_FCDeposit*K_GenFY31*N79/$G$79+K_FCReserve*N79) | P25: =Data!P30+IF(CapFull=1,MAX(K_CIP*O79-P24-Data!P31,0),0)+K_Reserve*O79-Data!H32+K_GenFY31*(O79/$G$79-1)+K_NonAppFY31*((1+K_NonAppG)^(P$4-2031)-1)+P77-(Data!P34+K_FCDeposit*K_GenFY31*O79/$G$79+K_FCReserve*O79) | Q25: =Data!Q30+IF(CapFull=1,MAX(K_CIP*P79-Q24-Data!Q31,0),0)+K_Reserve*P79-Data!H32+K_GenFY31*(P79/$G$79-1)+K_NonAppFY31*((1+K_NonAppG)^(Q$4-2031)-1)+Q77-(Data!Q34+K_FCDeposit*K_GenFY31*P79/$G$79+K_FCReserve*P79)
A26: Total spending | D26: =D16+D17+D18+D19+D20+D21+D22+D23+D24+D25 | E26: =E16+E17+E18+E19+E20+E21+E22+E23+E24+E25 | F26: =F16+F17+F18+F19+F20+F21+F22+F23+F24+F25 | G26: =G16+G17+G18+G19+G20+G21+G22+G23+G24+G25 | H26: =H16+H17+H18+H19+H20+H21+H22+H23+H24+H25 | I26: =I16+I17+I18+I19+I20+I21+I22+I23+I24+I25 | J26: =J16+J17+J18+J19+J20+J21+J22+J23+J24+J25 | K26: =K16+K17+K18+K19+K20+K21+K22+K23+K24+K25 | ... Q26: =Q16+Q17+Q18+Q19+Q20+Q21+Q22+Q23+Q24+Q25
A29: Room: revenue minus spending | D29: =D13-D26 | E29: =E13-E26 | F29: =F13-F26 | G29: =G13-G26 | H29: =H13-H26 | I29: =I13-I26 | J29: =J13-J26 | K29: =K13-K26 | ... Q29: =Q13-Q26
A31: Context
A32: School enrollment served | C32: =C61+C62 | D32: =D61+D62 | E32: =E61+E62 | F32: =F61+F62 | G32: =G61+G62 | H32: =H61+H62 | I32: =I61+I62 | J32: =J61+J62 | ... Q32: =Q61+Q62
A33: School staff | C33: =Staff27*(1-K_V)+K_V*C65 | D33: =Staff27*(1-K_V)+K_V*D65 | E33: =Staff27*(1-K_V)+K_V*E65 | F33: =Staff27*(1-K_V)+K_V*F65 | G33: =Staff27*(1-K_V)+K_V*G65 | H33: =Staff27*(1-K_V)+K_V*H65 | I33: =Staff27*(1-K_V)+K_V*I65 | J33: =Staff27*(1-K_V)+K_V*J65 | ... Q33: =Staff27*(1-K_V)+K_V*Q65
A34: Added homes since FY2027, including Chestnut Hill | D34: =D51+K_ChcaUnits*D54 | E34: =E51+K_ChcaUnits*E54 | F34: =F51+K_ChcaUnits*F54 | G34: =G51+K_ChcaUnits*G54 | H34: =H51+K_ChcaUnits*H54 | I34: =I51+K_ChcaUnits*I54 | J34: =J51+K_ChcaUnits*J54 | K34: =K51+K_ChcaUnits*K54 | ... Q34: =Q51+K_ChcaUnits*Q54
A35: Homes in town, including Chestnut Hill | C35: =K_Homes25+SUM($C42:C42)+K_ChcaUnits*C54 | D35: =K_Homes25+SUM($C42:D42)+K_ChcaUnits*D54 | E35: =K_Homes25+SUM($C42:E42)+K_ChcaUnits*E54 | F35: =K_Homes25+SUM($C42:F42)+K_ChcaUnits*F54 | G35: =K_Homes25+SUM($C42:G42)+K_ChcaUnits*G54 | H35: =K_Homes25+SUM($C42:H42)+K_ChcaUnits*H54 | I35: =K_Homes25+SUM($C42:I42)+K_ChcaUnits*I54 | J35: =K_Homes25+SUM($C42:J42)+K_ChcaUnits*J54 | ... Q35: =K_Homes25+SUM($C42:Q42)+K_ChcaUnits*Q54
A36: Fire company (included in Town services for growth) | D36: =0 | E36: =IF(AND(FireStep=1,E35>=K_FireHomes),K_FireCost*PSPayToFY27*E56,0) | F36: =IF(AND(FireStep=1,F35>=K_FireHomes),K_FireCost*PSPayToFY27*F56,0) | G36: =IF(AND(FireStep=1,G35>=K_FireHomes),K_FireCost*PSPayToFY27*G56,0) | H36: =IF(AND(FireStep=1,H35>=K_FireHomes),K_FireCost*PSPayToFY27*H56,0) | I36: =IF(AND(FireStep=1,I35>=K_FireHomes),K_FireCost*PSPayToFY27*I56,0) | J36: =IF(AND(FireStep=1,J35>=K_FireHomes),K_FireCost*PSPayToFY27*J56,0) | K36: =IF(AND(FireStep=1,K35>=K_FireHomes),K_FireCost*PSPayToFY27*K56,0) | L36: =IF(AND(FireStep=1,L35>=K_FireHomes),K_FireCost*PSPayToFY27*L56,0) | ... Q36: =IF(AND(FireStep=1,Q35>=K_FireHomes),K_FireCost*PSPayToFY27*Q56,0)
A37: Police and fire: restored staffing if chosen, and commitments already agreed (in today's services) | D37: =0 | E37: =PSRestore*K_PSRestoreN*K_PSPos*PSPayToFY27*E56+K_FireSteps*E56/$E$56+(1-PSRestore)*K_PolRefill28*K_PSPos*PSPayToFY27*E56 | F37: =PSRestore*K_PSRestoreN*K_PSPos*PSPayToFY27*F56+K_FireSteps*F56/$E$56+(1-PSRestore)*K_PolRefill29*K_PSPos*PSPayToFY27*F56 | G37: =PSRestore*K_PSRestoreN*K_PSPos*PSPayToFY27*G56+K_FireSteps*G56/$E$56+(1-PSRestore)*K_PolRefill29*K_PSPos*PSPayToFY27*G56 | H37: =PSRestore*K_PSRestoreN*K_PSPos*PSPayToFY27*H56+K_FireSteps*H56/$E$56+(1-PSRestore)*K_PolRefill29*K_PSPos*PSPayToFY27*H56 | I37: =PSRestore*K_PSRestoreN*K_PSPos*PSPayToFY27*I56+K_FireSteps*I56/$E$56+(1-PSRestore)*K_PolRefill29*K_PSPos*PSPayToFY27*I56 | J37: =PSRestore*K_PSRestoreN*K_PSPos*PSPayToFY27*J56+K_FireSteps*J56/$E$56+(1-PSRestore)*K_PolRefill29*K_PSPos*PSPayToFY27*J56 | K37: =PSRestore*K_PSRestoreN*K_PSPos*PSPayToFY27*K56+K_FireSteps*K56/$E$56+(1-PSRestore)*K_PolRefill29*K_PSPos*PSPayToFY27*K56 | L37: =PSRestore*K_PSRestoreN*K_PSPos*PSPayToFY27*L56+K_FireSteps*L56/$E$56+(1-PSRestore)*K_PolRefill29*K_PSPos*PSPayToFY27*L56 | M37: =PSRestore*K_PSRestoreN*K_PSPos*PSPayToFY27*M56+K_FireSteps*M56/$E$56+(1-PSRestore)*K_PolRefill29*K_PSPos*PSPayToFY27*M56 | ... Q37: =PSRestore*K_PSRestoreN*K_PSPos*PSPayToFY27*Q56+K_FireSteps*Q56/$E$56+(1-PSRestore)*K_PolRefill29*K_PSPos*PSPayToFY27*Q56
A38: Police officers added to hold the peer ratio | D38: =0 | E38: =IF(PoliceStep=1,MAX(INT(E35*K_PolRatio/1000+1E-9)-K_PolBudget-K_PolRefill28,0),0) | F38: =IF(PoliceStep=1,MAX(INT(F35*K_PolRatio/1000+1E-9)-K_PolBudget-K_PolRefill29,0),0) | G38: =IF(PoliceStep=1,MAX(INT(G35*K_PolRatio/1000+1E-9)-K_PolBudget-K_PolRefill29,0),0) | H38: =IF(PoliceStep=1,MAX(INT(H35*K_PolRatio/1000+1E-9)-K_PolBudget-K_PolRefill29,0),0) | I38: =IF(PoliceStep=1,MAX(INT(I35*K_PolRatio/1000+1E-9)-K_PolBudget-K_PolRefill29,0),0) | J38: =IF(PoliceStep=1,MAX(INT(J35*K_PolRatio/1000+1E-9)-K_PolBudget-K_PolRefill29,0),0) | K38: =IF(PoliceStep=1,MAX(INT(K35*K_PolRatio/1000+1E-9)-K_PolBudget-K_PolRefill29,0),0) | L38: =IF(PoliceStep=1,MAX(INT(L35*K_PolRatio/1000+1E-9)-K_PolBudget-K_PolRefill29,0),0) | M38: =IF(PoliceStep=1,MAX(INT(M35*K_PolRatio/1000+1E-9)-K_PolBudget-K_PolRefill29,0),0) | ... Q38: =IF(PoliceStep=1,MAX(INT(Q35*K_PolRatio/1000+1E-9)-K_PolBudget-K_PolRefill29,0),0)
A39: Police added (included in Town services for growth) | D39: =D38*K_PSPos*PSPayToFY27*D56 | E39: =E38*K_PSPos*PSPayToFY27*E56 | F39: =F38*K_PSPos*PSPayToFY27*F56 | G39: =G38*K_PSPos*PSPayToFY27*G56 | H39: =H38*K_PSPos*PSPayToFY27*H56 | I39: =I38*K_PSPos*PSPayToFY27*I56 | J39: =J38*K_PSPos*PSPayToFY27*J56 | K39: =K38*K_PSPos*PSPayToFY27*K56 | ... Q39: =Q38*K_PSPos*PSPayToFY27*Q56
A41: How the model works it out
A42: Homes added that year (Revenue build) | C42: =ROUND('Revenue build'!C45,0) | D42: =ROUND('Revenue build'!D45,0) | E42: =ROUND('Revenue build'!E45,0) | F42: =ROUND('Revenue build'!F45,0) | G42: =ROUND('Revenue build'!G45,0) | H42: =ROUND('Revenue build'!H45,0) | I42: =ROUND('Revenue build'!I45,0) | J42: =ROUND('Revenue build'!J45,0) | ... Q42: =ROUND('Revenue build'!Q45,0)
A43: Homes added that year at the recent trend (Revenue build) | C43: =ROUND('Revenue build'!C66,0) | D43: =ROUND('Revenue build'!D66,0) | E43: =ROUND('Revenue build'!E66,0) | F43: =ROUND('Revenue build'!F66,0) | G43: =ROUND('Revenue build'!G66,0) | H43: =ROUND('Revenue build'!H66,0) | I43: =ROUND('Revenue build'!I66,0) | J43: =ROUND('Revenue build'!J66,0) | ... Q43: =ROUND('Revenue build'!Q66,0)
A44: Commercial square feet added that year (Revenue build) | C44: =ROUND('Revenue build'!C46,0) | D44: =ROUND('Revenue build'!D46,0) | E44: =ROUND('Revenue build'!E46,0) | F44: =ROUND('Revenue build'!F46,0) | G44: =ROUND('Revenue build'!G46,0) | H44: =ROUND('Revenue build'!H46,0) | I44: =ROUND('Revenue build'!I46,0) | J44: =ROUND('Revenue build'!J46,0) | ... Q44: =ROUND('Revenue build'!Q46,0)
A45: Real-estate new growth (Revenue build) | C45: ='Revenue build'!C47 | D45: ='Revenue build'!D47 | E45: ='Revenue build'!E47 | F45: ='Revenue build'!F47 | G45: ='Revenue build'!G47 | H45: ='Revenue build'!H47 | I45: ='Revenue build'!I47 | J45: ='Revenue build'!J47 | ... Q45: ='Revenue build'!Q47
A46: Real-estate new growth at the recent trend (Revenue build) | C46: ='Revenue build'!C67 | D46: ='Revenue build'!D67 | E46: ='Revenue build'!E67 | F46: ='Revenue build'!F67 | G46: ='Revenue build'!G67 | H46: ='Revenue build'!H67 | I46: ='Revenue build'!I67 | J46: ='Revenue build'!J67 | ... Q46: ='Revenue build'!Q67
A47: Property tax, all (Revenue build) | C47: ='Revenue build'!C38 | D47: ='Revenue build'!D38 | E47: ='Revenue build'!E38 | F47: ='Revenue build'!F38 | G47: ='Revenue build'!G38 | H47: ='Revenue build'!H38 | I47: ='Revenue build'!I38 | J47: ='Revenue build'!J38 | ... Q47: ='Revenue build'!Q38
A48: Debt exclusion tax (Revenue build) | C48: ='Revenue build'!C37 | D48: ='Revenue build'!D37 | E48: ='Revenue build'!E37 | F48: ='Revenue build'!F37 | G48: ='Revenue build'!G37 | H48: ='Revenue build'!H37 | I48: ='Revenue build'!I37 | J48: ='Revenue build'!J37 | ... Q48: ='Revenue build'!Q37
A49: Other available funds (Revenue build) | C49: ='Revenue build'!C59 | D49: ='Revenue build'!D59 | E49: ='Revenue build'!E59 | F49: ='Revenue build'!F59 | G49: ='Revenue build'!G59 | H49: ='Revenue build'!H59 | I49: ='Revenue build'!I59 | J49: ='Revenue build'!J59 | ... Q49: ='Revenue build'!Q59
A50: Local receipts tied to growth (Revenue build) | C50: ='Revenue build'!C56 | D50: ='Revenue build'!D56 | E50: ='Revenue build'!E56 | F50: ='Revenue build'!F56 | G50: ='Revenue build'!G56 | H50: ='Revenue build'!H56 | I50: ='Revenue build'!I56 | J50: ='Revenue build'!J56 | ... Q50: ='Revenue build'!Q56
A51: Homes added since FY2027 | C51: =MAX(SUM($C42:C42)-SUM($C$42:$D$42),0) | D51: =MAX(SUM($C42:D42)-SUM($C$42:$D$42),0) | E51: =MAX(SUM($C42:E42)-SUM($C$42:$D$42),0) | F51: =MAX(SUM($C42:F42)-SUM($C$42:$D$42),0) | G51: =MAX(SUM($C42:G42)-SUM($C$42:$D$42),0) | H51: =MAX(SUM($C42:H42)-SUM($C$42:$D$42),0) | I51: =MAX(SUM($C42:I42)-SUM($C$42:$D$42),0) | J51: =MAX(SUM($C42:J42)-SUM($C$42:$D$42),0) | ... Q51: =MAX(SUM($C42:Q42)-SUM($C$42:$D$42),0)
A52: Homes added since FY2027, recent trend | C52: =MAX(SUM($C43:C43)-SUM($C$43:$D$43),0) | D52: =MAX(SUM($C43:D43)-SUM($C$43:$D$43),0) | E52: =MAX(SUM($C43:E43)-SUM($C$43:$D$43),0) | F52: =MAX(SUM($C43:F43)-SUM($C$43:$D$43),0) | G52: =MAX(SUM($C43:G43)-SUM($C$43:$D$43),0) | H52: =MAX(SUM($C43:H43)-SUM($C$43:$D$43),0) | I52: =MAX(SUM($C43:I43)-SUM($C$43:$D$43),0) | J52: =MAX(SUM($C43:J43)-SUM($C$43:$D$43),0) | ... Q52: =MAX(SUM($C43:Q43)-SUM($C$43:$D$43),0)
A53: Commercial square feet added since FY2027 | C53: =MAX(SUM($C44:C44)-SUM($C$44:$D$44),0) | D53: =MAX(SUM($C44:D44)-SUM($C$44:$D$44),0) | E53: =MAX(SUM($C44:E44)-SUM($C$44:$D$44),0) | F53: =MAX(SUM($C44:F44)-SUM($C$44:$D$44),0) | G53: =MAX(SUM($C44:G44)-SUM($C$44:$D$44),0) | H53: =MAX(SUM($C44:H44)-SUM($C$44:$D$44),0) | I53: =MAX(SUM($C44:I44)-SUM($C$44:$D$44),0) | J53: =MAX(SUM($C44:J44)-SUM($C$44:$D$44),0) | ... Q53: =MAX(SUM($C44:Q44)-SUM($C$44:$D$44),0)
A54: Chestnut Hill: share built and counted | C54: =ChcaOn*'Revenue build'!C29 | D54: =ChcaOn*'Revenue build'!D29 | E54: =ChcaOn*'Revenue build'!E29 | F54: =ChcaOn*'Revenue build'!F29 | G54: =ChcaOn*'Revenue build'!G29 | H54: =ChcaOn*'Revenue build'!H29 | I54: =ChcaOn*'Revenue build'!I29 | J54: =ChcaOn*'Revenue build'!J29 | ... Q54: =ChcaOn*'Revenue build'!Q29
A55: Pay index, Town staff (FY2027 = 1) | C55: =1 | D55: =IF(D$4>=2028,C55*(1+PayTown),1) | E55: =IF(E$4>=2028,D55*(1+PayTown),1) | F55: =IF(F$4>=2028,E55*(1+PayTown),1) | G55: =IF(G$4>=2028,F55*(1+PayTown),1) | H55: =IF(H$4>=2028,G55*(1+PayTown),1) | I55: =IF(I$4>=2028,H55*(1+PayTown),1) | J55: =IF(J$4>=2028,I55*(1+PayTown),1) | K55: =IF(K$4>=2028,J55*(1+PayTown),1) | ... Q55: =IF(Q$4>=2028,P55*(1+PayTown),1)
A56: Pay index, Public Safety | C56: =1 | D56: =IF(D$4>=2028,C56*(1+(PayTown+PSPrem)),1) | E56: =IF(E$4>=2028,D56*(1+(PayTown+PSPrem)),1) | F56: =IF(F$4>=2028,E56*(1+(PayTown+PSPrem)),1) | G56: =IF(G$4>=2028,F56*(1+(PayTown+PSPrem)),1) | H56: =IF(H$4>=2028,G56*(1+(PayTown+PSPrem)),1) | I56: =IF(I$4>=2028,H56*(1+(PayTown+PSPrem)),1) | J56: =IF(J$4>=2028,I56*(1+(PayTown+PSPrem)),1) | K56: =IF(K$4>=2028,J56*(1+(PayTown+PSPrem)),1) | ... Q56: =IF(Q$4>=2028,P56*(1+(PayTown+PSPrem)),1)
A57: Pay index, schools | C57: =1 | D57: =IF(D$4>=2028,C57*(1+(PayTown+SchDrift)),1) | E57: =IF(E$4>=2028,D57*(1+(PayTown+SchDrift)),1) | F57: =IF(F$4>=2028,E57*(1+(PayTown+SchDrift)),1) | G57: =IF(G$4>=2028,F57*(1+(PayTown+SchDrift)),1) | H57: =IF(H$4>=2028,G57*(1+(PayTown+SchDrift)),1) | I57: =IF(I$4>=2028,H57*(1+(PayTown+SchDrift)),1) | J57: =IF(J$4>=2028,I57*(1+(PayTown+SchDrift)),1) | K57: =IF(K$4>=2028,J57*(1+(PayTown+SchDrift)),1) | ... Q57: =IF(Q$4>=2028,P57*(1+(PayTown+SchDrift)),1)
A58: Price index | C58: =1 | D58: =IF(D$4>=2028,C58*(1+Inflation),1) | E58: =IF(E$4>=2028,D58*(1+Inflation),1) | F58: =IF(F$4>=2028,E58*(1+Inflation),1) | G58: =IF(G$4>=2028,F58*(1+Inflation),1) | H58: =IF(H$4>=2028,G58*(1+Inflation),1) | I58: =IF(I$4>=2028,H58*(1+Inflation),1) | J58: =IF(J$4>=2028,I58*(1+Inflation),1) | K58: =IF(K$4>=2028,J58*(1+Inflation),1) | ... Q58: =IF(Q$4>=2028,P58*(1+Inflation),1)
A59: Price index, school non-personnel | C59: =1 | D59: =IF(D$4>=2028,C59*(1+(Inflation+NPExtra)),1) | E59: =IF(E$4>=2028,D59*(1+(Inflation+NPExtra)),1) | F59: =IF(F$4>=2028,E59*(1+(Inflation+NPExtra)),1) | G59: =IF(G$4>=2028,F59*(1+(Inflation+NPExtra)),1) | H59: =IF(H$4>=2028,G59*(1+(Inflation+NPExtra)),1) | I59: =IF(I$4>=2028,H59*(1+(Inflation+NPExtra)),1) | J59: =IF(J$4>=2028,I59*(1+(Inflation+NPExtra)),1) | K59: =IF(K$4>=2028,J59*(1+(Inflation+NPExtra)),1) | ... Q59: =IF(Q$4>=2028,P59*(1+(Inflation+NPExtra)),1)
A60: Health premium index | C60: =1 | D60: =IF(D$4>=2028,C60*(1+IF(OR(D$4=2028,D$4=2029),PremNear,PremLong)),1) | E60: =IF(E$4>=2028,D60*(1+IF(OR(E$4=2028,E$4=2029),PremNear,PremLong)),1) | F60: =IF(F$4>=2028,E60*(1+IF(OR(F$4=2028,F$4=2029),PremNear,PremLong)),1) | G60: =IF(G$4>=2028,F60*(1+IF(OR(G$4=2028,G$4=2029),PremNear,PremLong)),1) | H60: =IF(H$4>=2028,G60*(1+IF(OR(H$4=2028,H$4=2029),PremNear,PremLong)),1) | I60: =IF(I$4>=2028,H60*(1+IF(OR(I$4=2028,I$4=2029),PremNear,PremLong)),1) | J60: =IF(J$4>=2028,I60*(1+IF(OR(J$4=2028,J$4=2029),PremNear,PremLong)),1) | K60: =IF(K$4>=2028,J60*(1+IF(OR(K$4=2028,K$4=2029),PremNear,PremLong)),1) | ... Q60: =IF(Q$4>=2028,P60*(1+IF(OR(Q$4=2028,Q$4=2029),PremNear,PremLong)),1)
A61: Enrollment on the chosen path | C61: =IF(EnrollMode="cm",Data!C25,IF(AND(EnrollMode="flat",C$4>2027),Data!$D$10,Data!C11*(1+Migration)^0+Data!C12*(1+Migration)^1+Data!C13*(1+Migration)^2+Data!C14*(1+Migration)^3+Data!C15*(1+Migration)^4+Data!C16*(1+Migration)^5+Data!C17*(1+Migration)^6+Data!C18*(1+Migration)^7+Data!C19*(1+Migration)^8+Data!C20*(1+Migration)^9+Data!C21*(1+Migration)^10+Data!C22*(1+Migration)^11+Data!C23*(1+Migration)^12+Data!C24*(1+Migration)^13)) | D61: =IF(EnrollMode="cm",Data!D25,IF(AND(EnrollMode="flat",D$4>2027),Data!$D$10,Data!D11*(1+Migration)^0+Data!D12*(1+Migration)^1+Data!D13*(1+Migration)^2+Data!D14*(1+Migration)^3+Data!D15*(1+Migration)^4+Data!D16*(1+Migration)^5+Data!D17*(1+Migration)^6+Data!D18*(1+Migration)^7+Data!D19*(1+Migration)^8+Data!D20*(1+Migration)^9+Data!D21*(1+Migration)^10+Data!D22*(1+Migration)^11+Data!D23*(1+Migration)^12+Data!D24*(1+Migration)^13)) | E61: =IF(EnrollMode="cm",Data!E25,IF(AND(EnrollMode="flat",E$4>2027),Data!$D$10,Data!E11*(1+Migration)^0+Data!E12*(1+Migration)^1+Data!E13*(1+Migration)^2+Data!E14*(1+Migration)^3+Data!E15*(1+Migration)^4+Data!E16*(1+Migration)^5+Data!E17*(1+Migration)^6+Data!E18*(1+Migration)^7+Data!E19*(1+Migration)^8+Data!E20*(1+Migration)^9+Data!E21*(1+Migration)^10+Data!E22*(1+Migration)^11+Data!E23*(1+Migration)^12+Data!E24*(1+Migration)^13)) | F61: =IF(EnrollMode="cm",Data!F25,IF(AND(EnrollMode="flat",F$4>2027),Data!$D$10,Data!F11*(1+Migration)^0+Data!F12*(1+Migration)^1+Data!F13*(1+Migration)^2+Data!F14*(1+Migration)^3+Data!F15*(1+Migration)^4+Data!F16*(1+Migration)^5+Data!F17*(1+Migration)^6+Data!F18*(1+Migration)^7+Data!F19*(1+Migration)^8+Data!F20*(1+Migration)^9+Data!F21*(1+Migration)^10+Data!F22*(1+Migration)^11+Data!F23*(1+Migration)^12+Data!F24*(1+Migration)^13)) | G61: =IF(EnrollMode="cm",Data!G25,IF(AND(EnrollMode="flat",G$4>2027),Data!$D$10,Data!G11*(1+Migration)^0+Data!G12*(1+Migration)^1+Data!G13*(1+Migration)^2+Data!G14*(1+Migration)^3+Data!G15*(1+Migration)^4+Data!G16*(1+Migration)^5+Data!G17*(1+Migration)^6+Data!G18*(1+Migration)^7+Data!G19*(1+Migration)^8+Data!G20*(1+Migration)^9+Data!G21*(1+Migration)^10+Data!G22*(1+Migration)^11+Data!G23*(1+Migration)^12+Data!G24*(1+Migration)^13)) | H61: =IF(EnrollMode="cm",Data!H25,IF(AND(EnrollMode="flat",H$4>2027),Data!$D$10,Data!H11*(1+Migration)^0+Data!H12*(1+Migration)^1+Data!H13*(1+Migration)^2+Data!H14*(1+Migration)^3+Data!H15*(1+Migration)^4+Data!H16*(1+Migration)^5+Data!H17*(1+Migration)^6+Data!H18*(1+Migration)^7+Data!H19*(1+Migration)^8+Data!H20*(1+Migration)^9+Data!H21*(1+Migration)^10+Data!H22*(1+Migration)^11+Data!H23*(1+Migration)^12+Data!H24*(1+Migration)^13)) | I61: =IF(EnrollMode="cm",Data!I25,IF(AND(EnrollMode="flat",I$4>2027),Data!$D$10,Data!I11*(1+Migration)^0+Data!I12*(1+Migration)^1+Data!I13*(1+Migration)^2+Data!I14*(1+Migration)^3+Data!I15*(1+Migration)^4+Data!I16*(1+Migration)^5+Data!I17*(1+Migration)^6+Data!I18*(1+Migration)^7+Data!I19*(1+Migration)^8+Data!I20*(1+Migration)^9+Data!I21*(1+Migration)^10+Data!I22*(1+Migration)^11+Data!I23*(1+Migration)^12+Data!I24*(1+Migration)^13)) | J61: =IF(EnrollMode="cm",Data!J25,IF(AND(EnrollMode="flat",J$4>2027),Data!$D$10,Data!J11*(1+Migration)^0+Data!J12*(1+Migration)^1+Data!J13*(1+Migration)^2+Data!J14*(1+Migration)^3+Data!J15*(1+Migration)^4+Data!J16*(1+Migration)^5+Data!J17*(1+Migration)^6+Data!J18*(1+Migration)^7+Data!J19*(1+Migration)^8+Data!J20*(1+Migration)^9+Data!J21*(1+Migration)^10+Data!J22*(1+Migration)^11+Data!J23*(1+Migration)^12+Data!J24*(1+Migration)^13)) | ... Q61: =IF(EnrollMode="cm",Data!Q25,IF(AND(EnrollMode="flat",Q$4>2027),Data!$D$10,Data!Q11*(1+Migration)^0+Data!Q12*(1+Migration)^1+Data!Q13*(1+Migration)^2+Data!Q14*(1+Migration)^3+Data!Q15*(1+Migration)^4+Data!Q16*(1+Migration)^5+Data!Q17*(1+Migration)^6+Data!Q18*(1+Migration)^7+Data!Q19*(1+Migration)^8+Data!Q20*(1+Migration)^9+Data!Q21*(1+Migration)^10+Data!Q22*(1+Migration)^11+Data!Q23*(1+Migration)^12+Data!Q24*(1+Migration)^13))
A62: Students from growth above the trend | C62: =MAX(C51-C52,0)*K_SPH+K_ChcaUnits*C54*K_ChcaSPU | D62: =MAX(D51-D52,0)*K_SPH+K_ChcaUnits*D54*K_ChcaSPU | E62: =MAX(E51-E52,0)*K_SPH+K_ChcaUnits*E54*K_ChcaSPU | F62: =MAX(F51-F52,0)*K_SPH+K_ChcaUnits*F54*K_ChcaSPU | G62: =MAX(G51-G52,0)*K_SPH+K_ChcaUnits*G54*K_ChcaSPU | H62: =MAX(H51-H52,0)*K_SPH+K_ChcaUnits*H54*K_ChcaSPU | I62: =MAX(I51-I52,0)*K_SPH+K_ChcaUnits*I54*K_ChcaSPU | J62: =MAX(J51-J52,0)*K_SPH+K_ChcaUnits*J54*K_ChcaSPU | ... Q62: =MAX(Q51-Q52,0)*K_SPH+K_ChcaUnits*Q54*K_ChcaSPU
A63: Students from growth filling open seats, unstaffed | C63: =IF(AND(FillCap=1,RatioMode="keep"),MAX(MIN(C62,Enroll27-C61),0),IF(AND(FillCap=1,RatioMode="half"),MIN(C62,0.5*MAX(Enroll27-C61,0)),0)) | D63: =IF(AND(FillCap=1,RatioMode="keep"),MAX(MIN(D62,Enroll27-D61),0),IF(AND(FillCap=1,RatioMode="half"),MIN(D62,0.5*MAX(Enroll27-D61,0)),0)) | E63: =IF(AND(FillCap=1,RatioMode="keep"),MAX(MIN(E62,Enroll27-E61),0),IF(AND(FillCap=1,RatioMode="half"),MIN(E62,0.5*MAX(Enroll27-E61,0)),0)) | F63: =IF(AND(FillCap=1,RatioMode="keep"),MAX(MIN(F62,Enroll27-F61),0),IF(AND(FillCap=1,RatioMode="half"),MIN(F62,0.5*MAX(Enroll27-F61,0)),0)) | G63: =IF(AND(FillCap=1,RatioMode="keep"),MAX(MIN(G62,Enroll27-G61),0),IF(AND(FillCap=1,RatioMode="half"),MIN(G62,0.5*MAX(Enroll27-G61,0)),0)) | H63: =IF(AND(FillCap=1,RatioMode="keep"),MAX(MIN(H62,Enroll27-H61),0),IF(AND(FillCap=1,RatioMode="half"),MIN(H62,0.5*MAX(Enroll27-H61,0)),0)) | I63: =IF(AND(FillCap=1,RatioMode="keep"),MAX(MIN(I62,Enroll27-I61),0),IF(AND(FillCap=1,RatioMode="half"),MIN(I62,0.5*MAX(Enroll27-I61,0)),0)) | J63: =IF(AND(FillCap=1,RatioMode="keep"),MAX(MIN(J62,Enroll27-J61),0),IF(AND(FillCap=1,RatioMode="half"),MIN(J62,0.5*MAX(Enroll27-J61,0)),0)) | ... Q63: =IF(AND(FillCap=1,RatioMode="keep"),MAX(MIN(Q62,Enroll27-Q61),0),IF(AND(FillCap=1,RatioMode="half"),MIN(Q62,0.5*MAX(Enroll27-Q61,0)),0))
A64: Students per staff member | C64: =IF(RatioMode="partial",Ratio27+(RatioTarget-Ratio27)*MIN(MAX((C$4-2027)/5,0),1),Ratio27) | D64: =IF(RatioMode="partial",Ratio27+(RatioTarget-Ratio27)*MIN(MAX((D$4-2027)/5,0),1),Ratio27) | E64: =IF(RatioMode="partial",Ratio27+(RatioTarget-Ratio27)*MIN(MAX((E$4-2027)/5,0),1),Ratio27) | F64: =IF(RatioMode="partial",Ratio27+(RatioTarget-Ratio27)*MIN(MAX((F$4-2027)/5,0),1),Ratio27) | G64: =IF(RatioMode="partial",Ratio27+(RatioTarget-Ratio27)*MIN(MAX((G$4-2027)/5,0),1),Ratio27) | H64: =IF(RatioMode="partial",Ratio27+(RatioTarget-Ratio27)*MIN(MAX((H$4-2027)/5,0),1),Ratio27) | I64: =IF(RatioMode="partial",Ratio27+(RatioTarget-Ratio27)*MIN(MAX((I$4-2027)/5,0),1),Ratio27) | J64: =IF(RatioMode="partial",Ratio27+(RatioTarget-Ratio27)*MIN(MAX((J$4-2027)/5,0),1),Ratio27) | ... Q64: =IF(RatioMode="partial",Ratio27+(RatioTarget-Ratio27)*MIN(MAX((Q$4-2027)/5,0),1),Ratio27)
A65: Staff implied by the staffing rule | C65: =IF(AND(FillCap=1,RatioMode="keep"),Staff27+MAX(C32-Enroll27,0)/Ratio27,IF(RatioMode="keep",Staff27+C62/Ratio27,IF(AND(FillCap=1,RatioMode="half"),Staff27+(0.5/K_V)*MIN(C61-Enroll27,0)/Ratio27+MAX(C61-Enroll27,0)/Ratio27+MAX(C62-0.5*MAX(Enroll27-C61,0),0)/Ratio27,IF(RatioMode="half",Staff27+C62/Ratio27+(0.5/K_V)*MIN(C61-Enroll27,0)/Ratio27+MAX(C61-Enroll27,0)/Ratio27,C32/C64)))) | D65: =IF(AND(FillCap=1,RatioMode="keep"),Staff27+MAX(D32-Enroll27,0)/Ratio27,IF(RatioMode="keep",Staff27+D62/Ratio27,IF(AND(FillCap=1,RatioMode="half"),Staff27+(0.5/K_V)*MIN(D61-Enroll27,0)/Ratio27+MAX(D61-Enroll27,0)/Ratio27+MAX(D62-0.5*MAX(Enroll27-D61,0),0)/Ratio27,IF(RatioMode="half",Staff27+D62/Ratio27+(0.5/K_V)*MIN(D61-Enroll27,0)/Ratio27+MAX(D61-Enroll27,0)/Ratio27,D32/D64)))) | E65: =IF(AND(FillCap=1,RatioMode="keep"),Staff27+MAX(E32-Enroll27,0)/Ratio27,IF(RatioMode="keep",Staff27+E62/Ratio27,IF(AND(FillCap=1,RatioMode="half"),Staff27+(0.5/K_V)*MIN(E61-Enroll27,0)/Ratio27+MAX(E61-Enroll27,0)/Ratio27+MAX(E62-0.5*MAX(Enroll27-E61,0),0)/Ratio27,IF(RatioMode="half",Staff27+E62/Ratio27+(0.5/K_V)*MIN(E61-Enroll27,0)/Ratio27+MAX(E61-Enroll27,0)/Ratio27,E32/E64)))) | F65: =IF(AND(FillCap=1,RatioMode="keep"),Staff27+MAX(F32-Enroll27,0)/Ratio27,IF(RatioMode="keep",Staff27+F62/Ratio27,IF(AND(FillCap=1,RatioMode="half"),Staff27+(0.5/K_V)*MIN(F61-Enroll27,0)/Ratio27+MAX(F61-Enroll27,0)/Ratio27+MAX(F62-0.5*MAX(Enroll27-F61,0),0)/Ratio27,IF(RatioMode="half",Staff27+F62/Ratio27+(0.5/K_V)*MIN(F61-Enroll27,0)/Ratio27+MAX(F61-Enroll27,0)/Ratio27,F32/F64)))) | G65: =IF(AND(FillCap=1,RatioMode="keep"),Staff27+MAX(G32-Enroll27,0)/Ratio27,IF(RatioMode="keep",Staff27+G62/Ratio27,IF(AND(FillCap=1,RatioMode="half"),Staff27+(0.5/K_V)*MIN(G61-Enroll27,0)/Ratio27+MAX(G61-Enroll27,0)/Ratio27+MAX(G62-0.5*MAX(Enroll27-G61,0),0)/Ratio27,IF(RatioMode="half",Staff27+G62/Ratio27+(0.5/K_V)*MIN(G61-Enroll27,0)/Ratio27+MAX(G61-Enroll27,0)/Ratio27,G32/G64)))) | H65: =IF(AND(FillCap=1,RatioMode="keep"),Staff27+MAX(H32-Enroll27,0)/Ratio27,IF(RatioMode="keep",Staff27+H62/Ratio27,IF(AND(FillCap=1,RatioMode="half"),Staff27+(0.5/K_V)*MIN(H61-Enroll27,0)/Ratio27+MAX(H61-Enroll27,0)/Ratio27+MAX(H62-0.5*MAX(Enroll27-H61,0),0)/Ratio27,IF(RatioMode="half",Staff27+H62/Ratio27+(0.5/K_V)*MIN(H61-Enroll27,0)/Ratio27+MAX(H61-Enroll27,0)/Ratio27,H32/H64)))) | I65: =IF(AND(FillCap=1,RatioMode="keep"),Staff27+MAX(I32-Enroll27,0)/Ratio27,IF(RatioMode="keep",Staff27+I62/Ratio27,IF(AND(FillCap=1,RatioMode="half"),Staff27+(0.5/K_V)*MIN(I61-Enroll27,0)/Ratio27+MAX(I61-Enroll27,0)/Ratio27+MAX(I62-0.5*MAX(Enroll27-I61,0),0)/Ratio27,IF(RatioMode="half",Staff27+I62/Ratio27+(0.5/K_V)*MIN(I61-Enroll27,0)/Ratio27+MAX(I61-Enroll27,0)/Ratio27,I32/I64)))) | J65: =IF(AND(FillCap=1,RatioMode="keep"),Staff27+MAX(J32-Enroll27,0)/Ratio27,IF(RatioMode="keep",Staff27+J62/Ratio27,IF(AND(FillCap=1,RatioMode="half"),Staff27+(0.5/K_V)*MIN(J61-Enroll27,0)/Ratio27+MAX(J61-Enroll27,0)/Ratio27+MAX(J62-0.5*MAX(Enroll27-J61,0),0)/Ratio27,IF(RatioMode="half",Staff27+J62/Ratio27+(0.5/K_V)*MIN(J61-Enroll27,0)/Ratio27+MAX(J61-Enroll27,0)/Ratio27,J32/J64)))) | ... Q65: =IF(AND(FillCap=1,RatioMode="keep"),Staff27+MAX(Q32-Enroll27,0)/Ratio27,IF(RatioMode="keep",Staff27+Q62/Ratio27,IF(AND(FillCap=1,RatioMode="half"),Staff27+(0.5/K_V)*MIN(Q61-Enroll27,0)/Ratio27+MAX(Q61-Enroll27,0)/Ratio27+MAX(Q62-0.5*MAX(Enroll27-Q61,0),0)/Ratio27,IF(RatioMode="half",Staff27+Q62/Ratio27+(0.5/K_V)*MIN(Q61-Enroll27,0)/Ratio27+MAX(Q61-Enroll27,0)/Ratio27,Q32/Q64))))
A66: Town pay index, weighted for Public Safety | D66: =K_psD*D56+(1-K_psD)*D55 | E66: =K_psD*E56+(1-K_psD)*E55 | F66: =K_psD*F56+(1-K_psD)*F55 | G66: =K_psD*G56+(1-K_psD)*G55 | H66: =K_psD*H56+(1-K_psD)*H55 | I66: =K_psD*I56+(1-K_psD)*I55 | J66: =K_psD*J56+(1-K_psD)*J55 | K66: =K_psD*K56+(1-K_psD)*K55 | ... Q66: =K_psD*Q56+(1-K_psD)*Q55
A67: Added commercial employees | D67: =D53/K_SqftPerEmp+K_ChcaEmp*D54 | E67: =E53/K_SqftPerEmp+K_ChcaEmp*E54 | F67: =F53/K_SqftPerEmp+K_ChcaEmp*F54 | G67: =G53/K_SqftPerEmp+K_ChcaEmp*G54 | H67: =H53/K_SqftPerEmp+K_ChcaEmp*H54 | I67: =I53/K_SqftPerEmp+K_ChcaEmp*I54 | J67: =J53/K_SqftPerEmp+K_ChcaEmp*J54 | K67: =K53/K_SqftPerEmp+K_ChcaEmp*K54 | ... Q67: =Q53/K_SqftPerEmp+K_ChcaEmp*Q54
A68: Payroll index, Town and school staff, weighted by FY2027 pay | D68: =(A_TD*K_pD*D66+A_Sch*K_SPS*D57*D33/Staff27)/(A_TD*K_pD+A_Sch*K_SPS) | E68: =(A_TD*K_pD*E66+A_Sch*K_SPS*E57*E33/Staff27)/(A_TD*K_pD+A_Sch*K_SPS) | F68: =(A_TD*K_pD*F66+A_Sch*K_SPS*F57*F33/Staff27)/(A_TD*K_pD+A_Sch*K_SPS) | G68: =(A_TD*K_pD*G66+A_Sch*K_SPS*G57*G33/Staff27)/(A_TD*K_pD+A_Sch*K_SPS) | H68: =(A_TD*K_pD*H66+A_Sch*K_SPS*H57*H33/Staff27)/(A_TD*K_pD+A_Sch*K_SPS) | I68: =(A_TD*K_pD*I66+A_Sch*K_SPS*I57*I33/Staff27)/(A_TD*K_pD+A_Sch*K_SPS) | J68: =(A_TD*K_pD*J66+A_Sch*K_SPS*J57*J33/Staff27)/(A_TD*K_pD+A_Sch*K_SPS) | K68: =(A_TD*K_pD*K66+A_Sch*K_SPS*K57*K33/Staff27)/(A_TD*K_pD+A_Sch*K_SPS) | ... Q68: =(A_TD*K_pD*Q66+A_Sch*K_SPS*Q57*Q33/Staff27)/(A_TD*K_pD+A_Sch*K_SPS)
A69: Pensions on schedule (before any slip) | D69: =A_Pen | E69: =Data!E26 | F69: =Data!F26 | G69: =Data!G26 | H69: =Data!H26 | I69: =Data!$H$26*(1+PayTown+K_PenNCPrem)^(I$4-2031) | J69: =Data!$H$26*(1+PayTown+K_PenNCPrem)^(J$4-2031) | K69: =Data!$H$26*(1+PayTown+K_PenNCPrem)^(K$4-2031) | L69: =Data!$H$26*(1+PayTown+K_PenNCPrem)^(L$4-2031) | M69: =Data!$H$26*(1+PayTown+K_PenNCPrem)^(M$4-2031) | N69: =Data!$H$26*(1+PayTown+K_PenNCPrem)^(N$4-2031) | O69: =Data!$H$26*(1+PayTown+K_PenNCPrem)^(O$4-2031) | P69: =Data!$H$26*(1+PayTown+K_PenNCPrem)^(P$4-2031) | Q69: =Data!$H$26*(1+PayTown+K_PenNCPrem)^(Q$4-2031)
A70: Town and school staff | D70: =K_TownFTE+D33 | E70: =K_TownFTE+E33 | F70: =K_TownFTE+F33 | G70: =K_TownFTE+G33 | H70: =K_TownFTE+H33 | I70: =K_TownFTE+I33 | J70: =K_TownFTE+J33 | K70: =K_TownFTE+K33 | ... Q70: =K_TownFTE+Q33
A71: Health plan subscribers index | D71: =K_ActShare*D70/AllStaff27+(1-K_ActShare)*(1+K_RetGrowth)^(D$4-2027) | E71: =K_ActShare*E70/AllStaff27+(1-K_ActShare)*(1+K_RetGrowth)^(E$4-2027) | F71: =K_ActShare*F70/AllStaff27+(1-K_ActShare)*(1+K_RetGrowth)^(F$4-2027) | G71: =K_ActShare*G70/AllStaff27+(1-K_ActShare)*(1+K_RetGrowth)^(G$4-2027) | H71: =K_ActShare*H70/AllStaff27+(1-K_ActShare)*(1+K_RetGrowth)^(H$4-2027) | I71: =K_ActShare*I70/AllStaff27+(1-K_ActShare)*(1+K_RetGrowth)^(I$4-2027) | J71: =K_ActShare*J70/AllStaff27+(1-K_ActShare)*(1+K_RetGrowth)^(J$4-2027) | K71: =K_ActShare*K70/AllStaff27+(1-K_ActShare)*(1+K_RetGrowth)^(K$4-2027) | ... Q71: =K_ActShare*Q70/AllStaff27+(1-K_ActShare)*(1+K_RetGrowth)^(Q$4-2027)
A72: State aid | C72: =R_SA2026 | D72: =R_SA2027*(1+StateAidGrowth)^(D$4-2027) | E72: =R_SA2027*(1+StateAidGrowth)^(E$4-2027) | F72: =R_SA2027*(1+StateAidGrowth)^(F$4-2027) | G72: =R_SA2027*(1+StateAidGrowth)^(G$4-2027) | H72: =R_SA2027*(1+StateAidGrowth)^(H$4-2027) | I72: =R_SA2027*(1+StateAidGrowth)^(I$4-2027) | J72: =R_SA2027*(1+StateAidGrowth)^(J$4-2027) | K72: =R_SA2027*(1+StateAidGrowth)^(K$4-2027) | ... Q72: =R_SA2027*(1+StateAidGrowth)^(Q$4-2027)
A73: Local receipts, actual | C73: =C50+R_LRresid2025*(1+ReceiptsGrowth)^(C$4-2025) | D73: =D50+R_LRresid2025*(1+ReceiptsGrowth)^(D$4-2025) | E73: =E50+R_LRresid2025*(1+ReceiptsGrowth)^(E$4-2025) | F73: =F50+R_LRresid2025*(1+ReceiptsGrowth)^(F$4-2025) | G73: =G50+R_LRresid2025*(1+ReceiptsGrowth)^(G$4-2025) | H73: =H50+R_LRresid2025*(1+ReceiptsGrowth)^(H$4-2025) | I73: =I50+R_LRresid2025*(1+ReceiptsGrowth)^(I$4-2025) | J73: =J50+R_LRresid2025*(1+ReceiptsGrowth)^(J$4-2025) | ... Q73: =Q50+R_LRresid2025*(1+ReceiptsGrowth)^(Q$4-2025)
A74: Further override | C74: =IF(AND(OvAmt>0,C$4>=OvYear),OvAmt*(1+K_LevyCap)^(C$4-OvYear),0) | D74: =IF(AND(OvAmt>0,D$4>=OvYear),OvAmt*(1+K_LevyCap)^(D$4-OvYear),0) | E74: =IF(AND(OvAmt>0,E$4>=OvYear),OvAmt*(1+K_LevyCap)^(E$4-OvYear),0) | F74: =IF(AND(OvAmt>0,F$4>=OvYear),OvAmt*(1+K_LevyCap)^(F$4-OvYear),0) | G74: =IF(AND(OvAmt>0,G$4>=OvYear),OvAmt*(1+K_LevyCap)^(G$4-OvYear),0) | H74: =IF(AND(OvAmt>0,H$4>=OvYear),OvAmt*(1+K_LevyCap)^(H$4-OvYear),0) | I74: =IF(AND(OvAmt>0,I$4>=OvYear),OvAmt*(1+K_LevyCap)^(I$4-OvYear),0) | J74: =IF(AND(OvAmt>0,J$4>=OvYear),OvAmt*(1+K_LevyCap)^(J$4-OvYear),0) | ... Q74: =IF(AND(OvAmt>0,Q$4>=OvYear),OvAmt*(1+K_LevyCap)^(Q$4-OvYear),0)
A75: Revenue before receipts and free cash | C75: =C47+C72+C49+C74 | D75: =D47+D72+D49+D74 | E75: =E47+E72+E49+E74 | F75: =F47+F72+F49+F74 | G75: =G47+G72+G49+G74 | H75: =H47+H72+H49+H74 | I75: =I47+I72+I49+I74 | J75: =J47+J72+J49+J74 | ... Q75: =Q47+Q72+Q49+Q74
A76: Local receipts, budgeted | C76: =Data!C36 | D76: =Data!D36 | E76: =E73*R_BudgetRatio | F76: =F73*R_BudgetRatio | G76: =G73*R_BudgetRatio | H76: =H73*R_BudgetRatio | I76: =I73*R_BudgetRatio | J76: =J73*R_BudgetRatio | K76: =K73*R_BudgetRatio | L76: =L73*R_BudgetRatio | ... Q76: =Q73*R_BudgetRatio
A77: Free cash | C77: =Data!C38 | D77: =Data!D38 | E77: =R_ApprShare*C80 | F77: =R_ApprShare*D80 | G77: =R_ApprShare*E80 | H77: =R_ApprShare*F80 | I77: =R_ApprShare*G80 | J77: =R_ApprShare*H80 | K77: =R_ApprShare*I80 | L77: =R_ApprShare*J80 | ... Q77: =R_ApprShare*O80
A78: Revenue including debt exclusion tax | C78: =C75+C76+C77 | D78: =D75+D76+D77 | E78: =E75+E76+E77 | F78: =F75+F76+F77 | G78: =G75+G76+G77 | H78: =H75+H76+H77 | I78: =I75+I76+I77 | J78: =J75+J76+J77 | ... Q78: =Q75+Q76+Q77
A79: Net revenue for the capital policy (less debt exclusions, free cash, non-appropriated items and any further override) | C79: =C78-C48-C77-C74-K_NonApp*(1+K_NonAppG)^(C$4-2027) | D79: =D78-D48-D77-D74-K_NonApp*(1+K_NonAppG)^(D$4-2027) | E79: =E78-E48-E77-E74-K_NonApp*(1+K_NonAppG)^(E$4-2027) | F79: =F78-F48-F77-F74-K_NonApp*(1+K_NonAppG)^(F$4-2027) | G79: =G78-G48-G77-G74-K_NonApp*(1+K_NonAppG)^(G$4-2027) | H79: =H78-H48-H77-H74-K_NonApp*(1+K_NonAppG)^(H$4-2027) | I79: =I78-I48-I77-I74-K_NonApp*(1+K_NonAppG)^(I$4-2027) | J79: =J78-J48-J77-J74-K_NonApp*(1+K_NonAppG)^(J$4-2027) | ... Q79: =Q78-Q48-Q77-Q74-K_NonApp*(1+K_NonAppG)^(Q$4-2027)
A80: Year-end surplus (returns as free cash two years later) | C80: =(C73-C76)+R_OtherSurplus*(C75+C73) | D80: =(D73-D76)+R_OtherSurplus*(D75+D73) | E80: =(E73-E76)+R_OtherSurplus*(E75+E73) | F80: =(F73-F76)+R_OtherSurplus*(F75+F73) | G80: =(G73-G76)+R_OtherSurplus*(G75+G73) | H80: =(H73-H76)+R_OtherSurplus*(H75+H73) | I80: =(I73-I76)+R_OtherSurplus*(I75+I73) | J80: =(J73-J76)+R_OtherSurplus*(J75+J73) | ... Q80: =(Q73-Q76)+R_OtherSurplus*(Q75+Q73)
A81: Retiree health: service cost | D81: =K_OpebSC27 | E81: =D81*(1+Data!E35) | F81: =E81*(1+Data!F35) | G81: =F81*(1+Data!G35) | H81: =G81*(1+Data!H35) | I81: =H81*(1+Data!I35) | J81: =I81*(1+Data!J35) | K81: =J81*(1+Data!K35) | L81: =K81*(1+K_OpebTrendLong) | M81: =L81*(1+K_OpebTrendLong) | N81: =M81*(1+K_OpebTrendLong) | O81: =N81*(1+K_OpebTrendLong) | P81: =O81*(1+K_OpebTrendLong) | Q81: =P81*(1+K_OpebTrendLong)
A82: Retiree health: benefits paid (in group health) | D82: =K_OpebB27 | E82: =D82*(1+Data!E35)*(1+K_RetGrowth) | F82: =E82*(1+Data!F35)*(1+K_RetGrowth) | G82: =F82*(1+Data!G35)*(1+K_RetGrowth) | H82: =G82*(1+Data!H35)*(1+K_RetGrowth) | I82: =H82*(1+Data!I35)*(1+K_RetGrowth) | J82: =I82*(1+Data!J35)*(1+K_RetGrowth) | K82: =J82*(1+Data!K35)*(1+K_RetGrowth) | L82: =K82*(1+K_OpebTrendLong)*(1+K_RetGrowth) | M82: =L82*(1+K_OpebTrendLong)*(1+K_RetGrowth) | N82: =M82*(1+K_OpebTrendLong)*(1+K_RetGrowth) | O82: =N82*(1+K_OpebTrendLong)*(1+K_RetGrowth) | P82: =O82*(1+K_OpebTrendLong)*(1+K_RetGrowth) | Q82: =P82*(1+K_OpebTrendLong)*(1+K_RetGrowth)
A83: Retiree health: total liability, end of year | D83: =K_OpebTol27 | E83: =D83*(1+K_OpebRate)+E81-E82 | F83: =E83*(1+K_OpebRate)+F81-F82 | G83: =F83*(1+K_OpebRate)+G81-G82 | H83: =G83*(1+K_OpebRate)+H81-H82 | I83: =H83*(1+K_OpebRate)+I81-I82 | J83: =I83*(1+K_OpebRate)+J81-J82 | K83: =J83*(1+K_OpebRate)+K81-K82 | L83: =K83*(1+K_OpebRate)+L81-L82 | ... Q83: =P83*(1+K_OpebRate)+Q81-Q82
A84: Retiree health: trust, end of year | D84: =K_OpebA27 | E84: =MIN(D84*(1+K_OpebRate)+E86,E83) | F84: =MIN(E84*(1+K_OpebRate)+F86,F83) | G84: =MIN(F84*(1+K_OpebRate)+G86,G83) | H84: =MIN(G84*(1+K_OpebRate)+H86,H83) | I84: =MIN(H84*(1+K_OpebRate)+I86,I83) | J84: =MIN(I84*(1+K_OpebRate)+J86,J83) | K84: =MIN(J84*(1+K_OpebRate)+K86,K83) | L84: =MIN(K84*(1+K_OpebRate)+L86,L83) | ... Q84: =MIN(P84*(1+K_OpebRate)+Q86,Q83)
A85: Retiree health: planned deposit | D85: =A_OPEB | E85: =Data!E27 | F85: =Data!F27 | G85: =Data!G27+IF(AND(AND(PensionSlip>0,G$4>=2030,G$4<=2030+PensionSlip),Redirect=1),G69-G21,0) | H85: =IF(Redirect=1,Data!$H$27,Data!$G$27+K_OPEBStep*(H$4-2030))+IF(AND(AND(PensionSlip>0,H$4>=2030,H$4<=2030+PensionSlip),Redirect=1),H69-H21,0) | I85: =IF(Redirect=1,Data!$H$27,Data!$G$27+K_OPEBStep*(I$4-2030))+IF(AND(AND(PensionSlip>0,I$4>=2030,I$4<=2030+PensionSlip),Redirect=1),I69-I21,0) | J85: =IF(Redirect=1,Data!$H$27,Data!$G$27+K_OPEBStep*(J$4-2030))+IF(AND(AND(PensionSlip>0,J$4>=2030,J$4<=2030+PensionSlip),Redirect=1),J69-J21,0) | K85: =IF(Redirect=1,Data!$H$27,Data!$G$27+K_OPEBStep*(K$4-2030))+IF(AND(AND(PensionSlip>0,K$4>=2030,K$4<=2030+PensionSlip),Redirect=1),K69-K21,0) | L85: =IF(Redirect=1,Data!$H$27,Data!$G$27+K_OPEBStep*(L$4-2030))+IF(AND(AND(PensionSlip>0,L$4>=2030,L$4<=2030+PensionSlip),Redirect=1),L69-L21,0) | M85: =IF(Redirect=1,Data!$H$27,Data!$G$27+K_OPEBStep*(M$4-2030))+IF(AND(AND(PensionSlip>0,M$4>=2030,M$4<=2030+PensionSlip),Redirect=1),M69-M21,0) | N85: =IF(Redirect=1,Data!$H$27,Data!$G$27+K_OPEBStep*(N$4-2030))+IF(AND(AND(PensionSlip>0,N$4>=2030,N$4<=2030+PensionSlip),Redirect=1),N69-N21,0) | O85: =IF(Redirect=1,Data!$H$27,Data!$G$27+K_OPEBStep*(O$4-2030))+IF(AND(AND(PensionSlip>0,O$4>=2030,O$4<=2030+PensionSlip),Redirect=1),O69-O21,0) | ... Q85: =IF(Redirect=1,Data!$H$27,Data!$G$27+K_OPEBStep*(Q$4-2030))+IF(AND(AND(PensionSlip>0,Q$4>=2030,Q$4<=2030+PensionSlip),Redirect=1),Q69-Q21,0)
A86: Retiree health: deposit, stopping at the payoff | D86: =A_OPEB | E86: =MIN(E85,MAX(E83-D84*(1+K_OpebRate),0)) | F86: =MIN(F85,MAX(F83-E84*(1+K_OpebRate),0)) | G86: =MIN(G85,MAX(G83-F84*(1+K_OpebRate),0)) | H86: =MIN(H85,MAX(H83-G84*(1+K_OpebRate),0)) | I86: =MIN(I85,MAX(I83-H84*(1+K_OpebRate),0)) | J86: =MIN(J85,MAX(J83-I84*(1+K_OpebRate),0)) | K86: =MIN(K85,MAX(K83-J84*(1+K_OpebRate),0)) | L86: =MIN(L85,MAX(L83-K84*(1+K_OpebRate),0)) | ... Q86: =MIN(Q85,MAX(Q83-P84*(1+K_OpebRate),0))
A88: Fixed values worked out once
A89: FY2027 enrollment | C89: =$D$61
A90: FY2027 school staff | C90: =K_Staff26+A_FTEchg
A91: FY2027 students per staff | C91: =Enroll27/Staff27
A92: Students per staff a third back to FY2019 | C92: =Ratio27+(K_Ratio2019-Ratio27)/3
A93: FY2027 Town and school staff | C93: =K_TownFTE+Staff27
A94: Pay growth, FY2025 to FY2027 | C94: =(1+PayTown)^(2027-2025)
A95: Public Safety pay growth, FY2025 to FY2027 | C95: =(1+PayTown+PSPrem)^(2027-2025)
A96: Pension normal cost, FY2030 (FY2031's, one year back) | C96: =Data!$H$26/(1+PayTown+K_PenNCPrem)
A97: Pension slip: each installment of FY2030's catch-up | C97: =IF(PensionSlip>0,(Data!$G$26-PenNC30)/((1-(1+K_PenRate)^(-(PensionSlip+1)))/(1-1/(1+K_PenRate))),0)

Sheet Revenue build
A1: Revenue build: property tax and new growth
A2: How the levy grows: last year's levy limit plus 2.5%, plus new growth, plus any override. New growth comes in five kinds, each a share of last year's levy limit, set on Assumptions and moved by the New growth setting. For FY2026 to FY2031 the forecast starts from the Town's own plan and adds the difference its new growth makes over the Town's flat $2.5M; from FY2032 it carries the levy forward itself. Debt exclusions are shown but set aside on the Forecast sheet.
C4: 2026 | D4: 2027 | E4: 2028 | F4: 2029 | G4: 2030 | H4: 2031 | I4: 2032 | J4: 2033 | K4: 2034 | L4: 2035 | M4: 2036 | N4: 2037 | O4: 2038 | P4: 2039 | Q4: 2040
A6: New growth rates, share of last year's levy limit | C6: This run | D6: Recent trend
A7: New homes | C7: =(IF(OR(GrowthStep<=0,MixCode="mix"),K_ResNewPct*GrowthRate/K_TrendRate,K_ResNewPct+(GrowthRate-K_TrendRate)*IF(MixCode="housing",1,IF(MixCode="even",0.5,0))))*HomesShare | D7: =K_ResNewPct
A8: Home renovation | C8: =IF(OR(GrowthStep<=0,MixCode="mix"),K_ResRenoPct*GrowthRate/K_TrendRate,K_ResRenoPct) | D8: =K_ResRenoPct
A9: New commercial space | C9: =IF(OR(GrowthStep<=0,MixCode="mix"),K_ComNewPct*GrowthRate/K_TrendRate,K_ComNewPct+(GrowthRate-K_TrendRate)*IF(MixCode="commercial",1,IF(MixCode="even",0.5,0))) | D9: =K_ComNewPct
A10: Commercial renovation | C10: =IF(OR(GrowthStep<=0,MixCode="mix"),K_ComRenoPct*GrowthRate/K_TrendRate,K_ComRenoPct) | D10: =K_ComRenoPct
A11: Business equipment | C11: =IF(OR(GrowthStep<=0,MixCode="mix"),K_PP*GrowthRate/K_TrendRate,K_PP) | D11: =K_PP
A12: All new growth | C12: =SUM(C7:C11) | D12: =SUM(D7:D11)
A13: Below the trend every kind is scaled down together. Above it, today's mix scales every kind up; the other mixes add the extra to new homes, new commercial space, or half to each.
A16: The levy, FY2026 to FY2031: the Town's plan plus the difference
A17: Town plan: property tax less debt exclusions, before the May 2026 override | C17: =Data!C5-Data!C6 | D17: =Data!D5-Data!D6 | E17: =Data!E5-Data!E6 | F17: =Data!F5-Data!F6 | G17: =Data!G5-Data!G6 | H17: =Data!H5-Data!H6
A18: May 2026 override, built up (each year's amount, then 2.5% a year) | C18: =N(Data!C8) | D18: =C18*(1+K_LevyCap)+N(Data!D8) | E18: =D18*(1+K_LevyCap)+N(Data!E8) | F18: =E18*(1+K_LevyCap)+N(Data!F8) | G18: =F18*(1+K_LevyCap)+N(Data!G8) | H18: =G18*(1+K_LevyCap)+N(Data!H8)
A19: Town plan levy limit with the override | C19: =C17+C18 | D19: =D17+D18 | E19: =E17+E18 | F19: =F17+F18 | G19: =G17+G18 | H19: =H17+H18
A21: New growth this year
A22: Last year's levy limit (this forecast's: the Town plan's plus the difference, through FY2031) | C22: =Levy2025 | D22: =C36 | E22: =D36 | F22: =E36 | G22: =F36 | H22: =G36 | I22: =H36 | J22: =I36 | K22: =J36 | ... Q22: =P36
A23: Scale to the Town's budgeted new growth (FY2027 only) | C23: =1 | D23: =K_TownNG/((Rate_ResNew+Rate_ResReno+Rate_ComNew+Rate_ComReno+Rate_PP)*D22) | E23: =1 | F23: =1 | G23: =1 | H23: =1 | I23: =1 | J23: =1 | K23: =1 | L23: =1 | ... Q23: =1
A24: New homes | C24: =Rate_ResNew*C22*C23 | D24: =Rate_ResNew*D22*D23 | E24: =Rate_ResNew*E22*E23 | F24: =Rate_ResNew*F22*F23 | G24: =Rate_ResNew*G22*G23 | H24: =Rate_ResNew*H22*H23 | I24: =Rate_ResNew*I22*I23 | J24: =Rate_ResNew*J22*J23 | ... Q24: =Rate_ResNew*Q22*Q23
A25: Home renovation | C25: =Rate_ResReno*C22*C23 | D25: =Rate_ResReno*D22*D23 | E25: =Rate_ResReno*E22*E23 | F25: =Rate_ResReno*F22*F23 | G25: =Rate_ResReno*G22*G23 | H25: =Rate_ResReno*H22*H23 | I25: =Rate_ResReno*I22*I23 | J25: =Rate_ResReno*J22*J23 | ... Q25: =Rate_ResReno*Q22*Q23
A26: New commercial space | C26: =Rate_ComNew*C22*C23 | D26: =Rate_ComNew*D22*D23 | E26: =Rate_ComNew*E22*E23 | F26: =Rate_ComNew*F22*F23 | G26: =Rate_ComNew*G22*G23 | H26: =Rate_ComNew*H22*H23 | I26: =Rate_ComNew*I22*I23 | J26: =Rate_ComNew*J22*J23 | ... Q26: =Rate_ComNew*Q22*Q23
A27: Commercial renovation | C27: =Rate_ComReno*C22*C23 | D27: =Rate_ComReno*D22*D23 | E27: =Rate_ComReno*E22*E23 | F27: =Rate_ComReno*F22*F23 | G27: =Rate_ComReno*G22*G23 | H27: =Rate_ComReno*H22*H23 | I27: =Rate_ComReno*I22*I23 | J27: =Rate_ComReno*J22*J23 | ... Q27: =Rate_ComReno*Q22*Q23
A28: Business equipment | C28: =Rate_PP*C22*C23 | D28: =Rate_PP*D22*D23 | E28: =Rate_PP*E22*E23 | F28: =Rate_PP*F22*F23 | G28: =Rate_PP*G22*G23 | H28: =Rate_PP*H22*H23 | I28: =Rate_PP*I22*I23 | J28: =Rate_PP*J22*J23 | ... Q28: =Rate_PP*Q22*Q23
A29: Chestnut Hill: share built and on the roll | C29: =IF(C$4<K_ChcaStart,0,MIN((C$4-K_ChcaStart+1)/K_ChcaSpan,1)) | D29: =IF(D$4<K_ChcaStart,0,MIN((D$4-K_ChcaStart+1)/K_ChcaSpan,1)) | E29: =IF(E$4<K_ChcaStart,0,MIN((E$4-K_ChcaStart+1)/K_ChcaSpan,1)) | F29: =IF(F$4<K_ChcaStart,0,MIN((F$4-K_ChcaStart+1)/K_ChcaSpan,1)) | G29: =IF(G$4<K_ChcaStart,0,MIN((G$4-K_ChcaStart+1)/K_ChcaSpan,1)) | H29: =IF(H$4<K_ChcaStart,0,MIN((H$4-K_ChcaStart+1)/K_ChcaSpan,1)) | I29: =IF(I$4<K_ChcaStart,0,MIN((I$4-K_ChcaStart+1)/K_ChcaSpan,1)) | J29: =IF(J$4<K_ChcaStart,0,MIN((J$4-K_ChcaStart+1)/K_ChcaSpan,1)) | ... Q29: =IF(Q$4<K_ChcaStart,0,MIN((Q$4-K_ChcaStart+1)/K_ChcaSpan,1))
A30: Chestnut Hill: property tax once on the roll | C30: =C31 | D30: =C30*(1+K_LevyCap)+D31 | E30: =D30*(1+K_LevyCap)+E31 | F30: =E30*(1+K_LevyCap)+F31 | G30: =F30*(1+K_LevyCap)+G31 | H30: =G30*(1+K_LevyCap)+H31 | I30: =H30*(1+K_LevyCap)+I31 | J30: =I30*(1+K_LevyCap)+J31 | K30: =J30*(1+K_LevyCap)+K31 | ... Q30: =P30*(1+K_LevyCap)+Q31
A31: Chestnut Hill: added this year, at its entry year's value | C31: =C29*ChcaProp*(ChcaResShare*((1+K_ResApp)*(1+K_LevyGrowth)/(1+K_BlendApp))^(C$4-K_ChcaDollarYr)+(1-ChcaResShare)*((1+K_ComApp)*(1+K_LevyGrowth)/(1+K_BlendApp))^(C$4-K_ChcaDollarYr)) | D31: =(D29-C29)*ChcaProp*(ChcaResShare*((1+K_ResApp)*(1+K_LevyGrowth)/(1+K_BlendApp))^(D$4-K_ChcaDollarYr)+(1-ChcaResShare)*((1+K_ComApp)*(1+K_LevyGrowth)/(1+K_BlendApp))^(D$4-K_ChcaDollarYr)) | E31: =(E29-D29)*ChcaProp*(ChcaResShare*((1+K_ResApp)*(1+K_LevyGrowth)/(1+K_BlendApp))^(E$4-K_ChcaDollarYr)+(1-ChcaResShare)*((1+K_ComApp)*(1+K_LevyGrowth)/(1+K_BlendApp))^(E$4-K_ChcaDollarYr)) | F31: =(F29-E29)*ChcaProp*(ChcaResShare*((1+K_ResApp)*(1+K_LevyGrowth)/(1+K_BlendApp))^(F$4-K_ChcaDollarYr)+(1-ChcaResShare)*((1+K_ComApp)*(1+K_LevyGrowth)/(1+K_BlendApp))^(F$4-K_ChcaDollarYr)) | G31: =(G29-F29)*ChcaProp*(ChcaResShare*((1+K_ResApp)*(1+K_LevyGrowth)/(1+K_BlendApp))^(G$4-K_ChcaDollarYr)+(1-ChcaResShare)*((1+K_ComApp)*(1+K_LevyGrowth)/(1+K_BlendApp))^(G$4-K_ChcaDollarYr)) | H31: =(H29-G29)*ChcaProp*(ChcaResShare*((1+K_ResApp)*(1+K_LevyGrowth)/(1+K_BlendApp))^(H$4-K_ChcaDollarYr)+(1-ChcaResShare)*((1+K_ComApp)*(1+K_LevyGrowth)/(1+K_BlendApp))^(H$4-K_ChcaDollarYr)) | I31: =(I29-H29)*ChcaProp*(ChcaResShare*((1+K_ResApp)*(1+K_LevyGrowth)/(1+K_BlendApp))^(I$4-K_ChcaDollarYr)+(1-ChcaResShare)*((1+K_ComApp)*(1+K_LevyGrowth)/(1+K_BlendApp))^(I$4-K_ChcaDollarYr)) | J31: =(J29-I29)*ChcaProp*(ChcaResShare*((1+K_ResApp)*(1+K_LevyGrowth)/(1+K_BlendApp))^(J$4-K_ChcaDollarYr)+(1-ChcaResShare)*((1+K_ComApp)*(1+K_LevyGrowth)/(1+K_BlendApp))^(J$4-K_ChcaDollarYr)) | K31: =(K29-J29)*ChcaProp*(ChcaResShare*((1+K_ResApp)*(1+K_LevyGrowth)/(1+K_BlendApp))^(K$4-K_ChcaDollarYr)+(1-ChcaResShare)*((1+K_ComApp)*(1+K_LevyGrowth)/(1+K_BlendApp))^(K$4-K_ChcaDollarYr)) | ... Q31: =(Q29-P29)*ChcaProp*(ChcaResShare*((1+K_ResApp)*(1+K_LevyGrowth)/(1+K_BlendApp))^(Q$4-K_ChcaDollarYr)+(1-ChcaResShare)*((1+K_ComApp)*(1+K_LevyGrowth)/(1+K_BlendApp))^(Q$4-K_ChcaDollarYr))
A32: New growth, all | C32: =SUM(C24:C28)+C31 | D32: =IF(NgEarlyYears="trend",SUM(D24:D28)+D31,IF(NgEarlyYears="permits",K_Perm27,IF(NgEarlyYears="permits_low",K_Perm27Lo,K_Perm27Hi))+D28+D31) | E32: =IF(NgEarlyYears="trend",SUM(E24:E28)+E31,IF(NgEarlyYears="permits",K_Perm28,IF(NgEarlyYears="permits_low",K_Perm28Lo,K_Perm28Hi))+E28+E31) | F32: =SUM(F24:F28)+F31 | G32: =SUM(G24:G28)+G31 | H32: =SUM(H24:H28)+H31 | I32: =SUM(I24:I28)+I31 | J32: =SUM(J24:J28)+J31 | K32: =SUM(K24:K28)+K31 | L32: =SUM(L24:L28)+L31 | M32: =SUM(M24:M28)+M31 | ... Q32: =SUM(Q24:Q28)+Q31
A34: Property tax
A35: Difference from the Town plan's $2.5M a year, carried at 2.5% (FY2027 to FY2031; FY2026 is certified in both) | C35: =0 | D35: =C35*(1+K_LevyCap)+(D32-K_TownNG) | E35: =D35*(1+K_LevyCap)+(E32-K_TownNG) | F35: =E35*(1+K_LevyCap)+(F32-K_TownNG) | G35: =F35*(1+K_LevyCap)+(G32-K_TownNG) | H35: =G35*(1+K_LevyCap)+(H32-K_TownNG)
A36: Levy limit: Town plan plus the difference to FY2031, then last year plus 2.5% plus new growth | C36: =C19+C35 | D36: =D19+D35 | E36: =E19+E35 | F36: =F19+F35 | G36: =G19+G35 | H36: =H19+H35 | I36: =H36*(1+K_LevyCap)+I32 | J36: =I36*(1+K_LevyCap)+J32 | K36: =J36*(1+K_LevyCap)+K32 | L36: =K36*(1+K_LevyCap)+L32 | M36: =L36*(1+K_LevyCap)+M32 | N36: =M36*(1+K_LevyCap)+N32 | O36: =N36*(1+K_LevyCap)+O32 | P36: =O36*(1+K_LevyCap)+P32 | Q36: =P36*(1+K_LevyCap)+Q32
A37: Debt exclusion tax (Town plan, then held at FY2031) | C37: =Data!C6 | D37: =Data!D6 | E37: =Data!E6 | F37: =Data!F6 | G37: =Data!G6 | H37: =Data!H6 | I37: =Data!$H$6 | J37: =Data!$H$6 | K37: =Data!$H$6 | L37: =Data!$H$6 | M37: =Data!$H$6 | N37: =Data!$H$6 | O37: =Data!$H$6 | P37: =Data!$H$6 | Q37: =Data!$H$6
A38: Property tax, all | C38: =C36+C37 | D38: =D36+D37 | E38: =E36+E37 | F38: =F36+F37 | G38: =G36+G37 | H38: =H36+H37 | I38: =I36+I37 | J38: =J36+J37 | ... Q38: =Q36+Q37
A40: Homes and commercial space the new growth stands for
A41: Assessed value of a new home | C41: =K_ResValUnit*(1+K_ResApp)^(C$4-2026) | D41: =K_ResValUnit*(1+K_ResApp)^(D$4-2026) | E41: =K_ResValUnit*(1+K_ResApp)^(E$4-2026) | F41: =K_ResValUnit*(1+K_ResApp)^(F$4-2026) | G41: =K_ResValUnit*(1+K_ResApp)^(G$4-2026) | H41: =K_ResValUnit*(1+K_ResApp)^(H$4-2026) | I41: =K_ResValUnit*(1+K_ResApp)^(I$4-2026) | J41: =K_ResValUnit*(1+K_ResApp)^(J$4-2026) | ... Q41: =K_ResValUnit*(1+K_ResApp)^(Q$4-2026)
A42: Residential tax rate | C42: =K_ResTax*((1+K_LevyGrowth)/(1+K_BlendApp))^(C$4-2026) | D42: =K_ResTax*((1+K_LevyGrowth)/(1+K_BlendApp))^(D$4-2026) | E42: =K_ResTax*((1+K_LevyGrowth)/(1+K_BlendApp))^(E$4-2026) | F42: =K_ResTax*((1+K_LevyGrowth)/(1+K_BlendApp))^(F$4-2026) | G42: =K_ResTax*((1+K_LevyGrowth)/(1+K_BlendApp))^(G$4-2026) | H42: =K_ResTax*((1+K_LevyGrowth)/(1+K_BlendApp))^(H$4-2026) | I42: =K_ResTax*((1+K_LevyGrowth)/(1+K_BlendApp))^(I$4-2026) | J42: =K_ResTax*((1+K_LevyGrowth)/(1+K_BlendApp))^(J$4-2026) | ... Q42: =K_ResTax*((1+K_LevyGrowth)/(1+K_BlendApp))^(Q$4-2026)
A43: Commercial tax rate | C43: =K_ComTax*((1+K_LevyGrowth)/(1+K_BlendApp))^(C$4-2026) | D43: =K_ComTax*((1+K_LevyGrowth)/(1+K_BlendApp))^(D$4-2026) | E43: =K_ComTax*((1+K_LevyGrowth)/(1+K_BlendApp))^(E$4-2026) | F43: =K_ComTax*((1+K_LevyGrowth)/(1+K_BlendApp))^(F$4-2026) | G43: =K_ComTax*((1+K_LevyGrowth)/(1+K_BlendApp))^(G$4-2026) | H43: =K_ComTax*((1+K_LevyGrowth)/(1+K_BlendApp))^(H$4-2026) | I43: =K_ComTax*((1+K_LevyGrowth)/(1+K_BlendApp))^(I$4-2026) | J43: =K_ComTax*((1+K_LevyGrowth)/(1+K_BlendApp))^(J$4-2026) | ... Q43: =K_ComTax*((1+K_LevyGrowth)/(1+K_BlendApp))^(Q$4-2026)
A44: Assessed value per commercial square foot | C44: =K_ComValSqft*(1+K_ComApp)^(C$4-2026) | D44: =K_ComValSqft*(1+K_ComApp)^(D$4-2026) | E44: =K_ComValSqft*(1+K_ComApp)^(E$4-2026) | F44: =K_ComValSqft*(1+K_ComApp)^(F$4-2026) | G44: =K_ComValSqft*(1+K_ComApp)^(G$4-2026) | H44: =K_ComValSqft*(1+K_ComApp)^(H$4-2026) | I44: =K_ComValSqft*(1+K_ComApp)^(I$4-2026) | J44: =K_ComValSqft*(1+K_ComApp)^(J$4-2026) | ... Q44: =K_ComValSqft*(1+K_ComApp)^(Q$4-2026)
A45: Homes added this year | C45: =C24/(C41*C42) | D45: =D24/(D41*D42) | E45: =E24/(E41*E42) | F45: =F24/(F41*F42) | G45: =G24/(G41*G42) | H45: =H24/(H41*H42) | I45: =I24/(I41*I42) | J45: =J24/(J41*J42) | ... Q45: =Q24/(Q41*Q42)
A46: Commercial square feet added this year | C46: =C26/(C44*C43) | D46: =D26/(D44*D43) | E46: =E26/(E44*E43) | F46: =F26/(F44*F43) | G46: =G26/(G44*G43) | H46: =H26/(H44*H43) | I46: =I26/(I44*I43) | J46: =J26/(J44*J43) | ... Q46: =Q26/(Q44*Q43)
A47: Real-estate new growth (all but business equipment) | C47: =SUM(C24:C27) | D47: =SUM(D24:D27) | E47: =SUM(E24:E27) | F47: =SUM(F24:F27) | G47: =SUM(G24:G27) | H47: =SUM(H24:H27) | I47: =SUM(I24:I27) | J47: =SUM(J24:J27) | ... Q47: =SUM(Q24:Q27)
A49: Local receipts that grow with construction
A50: Building permit fee, share of construction cost | C50: =IF(C$4>=2027,K_PermitRate27,K_PermitRate26) | D50: =IF(D$4>=2027,K_PermitRate27,K_PermitRate26) | E50: =IF(E$4>=2027,K_PermitRate27,K_PermitRate26) | F50: =IF(F$4>=2027,K_PermitRate27,K_PermitRate26) | G50: =IF(G$4>=2027,K_PermitRate27,K_PermitRate26) | H50: =IF(H$4>=2027,K_PermitRate27,K_PermitRate26) | I50: =IF(I$4>=2027,K_PermitRate27,K_PermitRate26) | J50: =IF(J$4>=2027,K_PermitRate27,K_PermitRate26) | ... Q50: =IF(Q$4>=2027,K_PermitRate27,K_PermitRate26)
A51: Building permit fees (on the construction value behind this year's real-estate new growth) | C51: =C50*((C24+C25)/C42+(C26+C27)/C43) | D51: =D50*((D24+D25)/D42+(D26+D27)/D43) | E51: =E50*((E24+E25)/E42+(E26+E27)/E43) | F51: =F50*((F24+F25)/F42+(F26+F27)/F43) | G51: =G50*((G24+G25)/G42+(G26+G27)/G43) | H51: =H50*((H24+H25)/H42+(H26+H27)/H43) | I51: =I50*((I24+I25)/I42+(I26+I27)/I43) | J51: =J50*((J24+J25)/J42+(J26+J27)/J43) | ... Q51: =Q50*((Q24+Q25)/Q42+(Q26+Q27)/Q43)
A52: Meals tax at existing restaurants | C52: =K_Meals2025*(1+K_MealsGrowth)^(C$4-2025) | D52: =K_Meals2025*(1+K_MealsGrowth)^(D$4-2025) | E52: =K_Meals2025*(1+K_MealsGrowth)^(E$4-2025) | F52: =K_Meals2025*(1+K_MealsGrowth)^(F$4-2025) | G52: =K_Meals2025*(1+K_MealsGrowth)^(G$4-2025) | H52: =K_Meals2025*(1+K_MealsGrowth)^(H$4-2025) | I52: =K_Meals2025*(1+K_MealsGrowth)^(I$4-2025) | J52: =K_Meals2025*(1+K_MealsGrowth)^(J$4-2025) | ... Q52: =K_Meals2025*(1+K_MealsGrowth)^(Q$4-2025)
A53: Commercial square feet added since FY2026 | C53: =SUM($C$46:C46) | D53: =SUM($C$46:D46) | E53: =SUM($C$46:E46) | F53: =SUM($C$46:F46) | G53: =SUM($C$46:G46) | H53: =SUM($C$46:H46) | I53: =SUM($C$46:I46) | J53: =SUM($C$46:J46) | ... Q53: =SUM($C$46:Q46)
A54: Meals tax from new commercial space | C54: =K_MealsPerSqft*C53 | D54: =K_MealsPerSqft*D53 | E54: =K_MealsPerSqft*E53 | F54: =K_MealsPerSqft*F53 | G54: =K_MealsPerSqft*G53 | H54: =K_MealsPerSqft*H53 | I54: =K_MealsPerSqft*I53 | J54: =K_MealsPerSqft*J53 | ... Q54: =K_MealsPerSqft*Q53
A55: Chestnut Hill: rooms tax and motor vehicle excise | C55: =ChcaLR*C29*(1+R_LRbase)^(C$4-K_ChcaDollarYr) | D55: =ChcaLR*D29*(1+R_LRbase)^(D$4-K_ChcaDollarYr) | E55: =ChcaLR*E29*(1+R_LRbase)^(E$4-K_ChcaDollarYr) | F55: =ChcaLR*F29*(1+R_LRbase)^(F$4-K_ChcaDollarYr) | G55: =ChcaLR*G29*(1+R_LRbase)^(G$4-K_ChcaDollarYr) | H55: =ChcaLR*H29*(1+R_LRbase)^(H$4-K_ChcaDollarYr) | I55: =ChcaLR*I29*(1+R_LRbase)^(I$4-K_ChcaDollarYr) | J55: =ChcaLR*J29*(1+R_LRbase)^(J$4-K_ChcaDollarYr) | ... Q55: =ChcaLR*Q29*(1+R_LRbase)^(Q$4-K_ChcaDollarYr)
A56: Local receipts tied to growth | C56: =C51+C52+C54+C55+K_InvFlat | D56: =D51+D52+D54+D55+K_InvFlat | E56: =E51+E52+E54+E55+K_InvFlat | F56: =F51+F52+F54+F55+K_InvFlat | G56: =G51+G52+G54+G55+K_InvFlat | H56: =H51+H52+H54+H55+K_InvFlat | I56: =I51+I52+I54+I55+K_InvFlat | J56: =J51+J52+J54+J55+K_InvFlat | ... Q56: =Q51+Q52+Q54+Q55+K_InvFlat
A58: Other available funds
A59: Other available funds (Town plan; FY2027 adopted; override fund drawn FY2028 to FY2030; FY2031 level after) | C59: =Data!C7+N(Data!C9) | D59: =A_OtherFunds | E59: =Data!E7+N(Data!E9) | F59: =Data!F7+N(Data!F9) | G59: =Data!G7+N(Data!G9) | H59: =Data!H7+N(Data!H9) | I59: =$H$59 | J59: =$H$59 | K59: =$H$59 | L59: =$H$59 | M59: =$H$59 | N59: =$H$59 | O59: =$H$59 | P59: =$H$59 | Q59: =$H$59
A61: The same at the recent trend, for comparison (the Explorer's planning staff and student counts need it)
A62: Last year's levy limit, trend | C62: =Levy2025 | D62: =C65 | E62: =D65 | F62: =E65 | G62: =F65 | H62: =G65 | I62: =H65 | J62: =I65 | K62: =J65 | ... Q62: =P65
A63: New growth, all, trend | C63: =(K_ResNewPct+K_ResRenoPct+K_ComNewPct+K_ComRenoPct+K_PP)*C62+C31 | D63: =K_TownNG | E63: =(K_ResNewPct+K_ResRenoPct+K_ComNewPct+K_ComRenoPct+K_PP)*E62+E31 | F63: =(K_ResNewPct+K_ResRenoPct+K_ComNewPct+K_ComRenoPct+K_PP)*F62+F31 | G63: =(K_ResNewPct+K_ResRenoPct+K_ComNewPct+K_ComRenoPct+K_PP)*G62+G31 | H63: =(K_ResNewPct+K_ResRenoPct+K_ComNewPct+K_ComRenoPct+K_PP)*H62+H31 | I63: =(K_ResNewPct+K_ResRenoPct+K_ComNewPct+K_ComRenoPct+K_PP)*I62+I31 | J63: =(K_ResNewPct+K_ResRenoPct+K_ComNewPct+K_ComRenoPct+K_PP)*J62+J31 | K63: =(K_ResNewPct+K_ResRenoPct+K_ComNewPct+K_ComRenoPct+K_PP)*K62+K31 | L63: =(K_ResNewPct+K_ResRenoPct+K_ComNewPct+K_ComRenoPct+K_PP)*L62+L31 | ... Q63: =(K_ResNewPct+K_ResRenoPct+K_ComNewPct+K_ComRenoPct+K_PP)*Q62+Q31
A64: Difference from the Town plan, trend | C64: =0 | D64: =C64*(1+K_LevyCap)+(D63-K_TownNG) | E64: =D64*(1+K_LevyCap)+(E63-K_TownNG) | F64: =E64*(1+K_LevyCap)+(F63-K_TownNG) | G64: =F64*(1+K_LevyCap)+(G63-K_TownNG) | H64: =G64*(1+K_LevyCap)+(H63-K_TownNG)
A65: Levy limit, trend | C65: =C19+C64 | D65: =D19+D64 | E65: =E19+E64 | F65: =F19+F64 | G65: =G19+G64 | H65: =H19+H64 | I65: =H65*(1+K_LevyCap)+I63 | J65: =I65*(1+K_LevyCap)+J63 | K65: =J65*(1+K_LevyCap)+K63 | L65: =K65*(1+K_LevyCap)+L63 | M65: =L65*(1+K_LevyCap)+M63 | N65: =M65*(1+K_LevyCap)+N63 | O65: =N65*(1+K_LevyCap)+O63 | P65: =O65*(1+K_LevyCap)+P63 | Q65: =P65*(1+K_LevyCap)+Q63
A66: Homes added this year, trend | C66: =K_ResNewPct*C62/(C41*C42) | D66: =K_ResNewPct*D62/(D41*D42) | E66: =K_ResNewPct*E62/(E41*E42) | F66: =K_ResNewPct*F62/(F41*F42) | G66: =K_ResNewPct*G62/(G41*G42) | H66: =K_ResNewPct*H62/(H41*H42) | I66: =K_ResNewPct*I62/(I41*I42) | J66: =K_ResNewPct*J62/(J41*J42) | ... Q66: =K_ResNewPct*Q62/(Q41*Q42)
A67: Real-estate new growth, trend | C67: =(K_ResNewPct+K_ResRenoPct+K_ComNewPct+K_ComRenoPct)*C62 | D67: =(K_ResNewPct+K_ResRenoPct+K_ComNewPct+K_ComRenoPct)*D62 | E67: =(K_ResNewPct+K_ResRenoPct+K_ComNewPct+K_ComRenoPct)*E62 | F67: =(K_ResNewPct+K_ResRenoPct+K_ComNewPct+K_ComRenoPct)*F62 | G67: =(K_ResNewPct+K_ResRenoPct+K_ComNewPct+K_ComRenoPct)*G62 | H67: =(K_ResNewPct+K_ResRenoPct+K_ComNewPct+K_ComRenoPct)*H62 | I67: =(K_ResNewPct+K_ResRenoPct+K_ComNewPct+K_ComRenoPct)*I62 | J67: =(K_ResNewPct+K_ResRenoPct+K_ComNewPct+K_ComRenoPct)*J62 | ... Q67: =(K_ResNewPct+K_ResRenoPct+K_ComNewPct+K_ComRenoPct)*Q62

Sheet Worked example
A1: Worked example: FY2033, step by step
A2: FY2033 is the first full year after the Town's plan ends, so the levy is carried forward by the forecast alone. Each value is a live cell: change a setting and this page follows. The last column says where the same step is done for every year.
A4: Step | B4: Value | C4: How | D4: Where every year is done
A5: Property tax
A6: Levy limit, FY2032 | B6: ='Revenue build'!I36 | C6: Debt exclusions set aside. | D6: Revenue build
A7: Plus 2.5% | B7: =B6*K_LevyCap | C7: Proposition 2½. | D7: Revenue build
A8: Plus new growth: new homes | B8: ='Revenue build'!J24 | C8: ="Rate "&TEXT(Rate_ResNew,"0.000%")&" of last year's levy limit" | D8: Revenue build
A9: Plus new growth: home renovation | B9: ='Revenue build'!J25 | C9: ="Rate "&TEXT(Rate_ResReno,"0.000%") | D9: Revenue build
A10: Plus new growth: new commercial space | B10: ='Revenue build'!J26 | C10: ="Rate "&TEXT(Rate_ComNew,"0.000%") | D10: Revenue build
A11: Plus new growth: commercial renovation | B11: ='Revenue build'!J27 | C11: ="Rate "&TEXT(Rate_ComReno,"0.000%") | D11: Revenue build
A12: Plus new growth: business equipment | B12: ='Revenue build'!J28 | C12: ="Rate "&TEXT(Rate_PP,"0.000%") | D12: Revenue build
A13: Plus Chestnut Hill added this year | B13: ='Revenue build'!J31 | C13: Fully built by FY2034. | D13: Revenue build
A14: Levy limit, FY2033 | B14: =SUM(B6:B13) | D14: Revenue build
A15: Check: same as Revenue build | B15: =B14-'Revenue build'!J36 | C15: Should be 0.
A16: Homes the new-homes growth stands for | B16: =B8/('Revenue build'!J41*'Revenue build'!J42) | C16: ="New homes growth / (value of a new home "&TEXT('Revenue build'!J41,"$#,##0")&" x residential tax rate "&TEXT('Revenue build'!J42,"0.000%")&")" | D16: Revenue build
A17: Revenue
A18: Property tax, debt exclusions set aside | B18: =Forecast!J7 | C18: The levy limit above. | D18: Forecast
A19: State aid | B19: =Forecast!J8 | C19: ="FY2027 state aid grown "&TEXT(StateAidGrowth,"0.00%")&" a year" | D19: Forecast
A20: Local receipts, as budgeted | B20: =Forecast!J9 | C20: ="Receipts not tied to growth, grown "&TEXT(ReceiptsGrowth,"0.00%")&" a year, plus permits and meals tax; budgeted at "&TEXT(R_BudgetRatio,"0%")&" of what is collected" | D20: Forecast
A21: Free cash | B21: =Forecast!J10 | C21: ="The surplus of FY2031 times "&TEXT(R_ApprShare,"0%") | D21: Forecast
A22: Other available funds and any further override | B22: =Forecast!J11+Forecast!J12 | D22: Forecast
A23: Total revenue | B23: =SUM(B18:B22) | D23: Forecast
A24: Spending
A25: Town departments, today's services | B25: =Forecast!J16 | C25: ="FY2027 budget x ("&TEXT(K_pD,"0%")&" pay x pay index "&TEXT(Forecast!J66,"0.000")&" + the rest x price index "&TEXT(Forecast!J58,"0.000")&")" | D25: Forecast
A26: Town services for added homes and businesses | B26: =Forecast!J17 | C26: =TEXT(Forecast!J34,"#,##0")&" homes added since FY2027 at "&TEXT(CostHome,"$#,##0")&" (FY2025 $, less fire's share, which comes as a company), plus any fire company and police steps" | D26: Forecast
A27: Schools | B27: =Forecast!J18 | C27: ="FY2027 budget: pay part x pay index x staff "&TEXT(Forecast!J33,"#,##0")&" / "&TEXT(Staff27,"#,##0")&"; the rest x prices, two thirds moving with enrollment "&TEXT(Forecast!J32,"#,##0") | D27: Forecast
A28: Health insurance | B28: =Forecast!J19 | C28: ="FY2027 budget x subscribers "&TEXT(Forecast!J71,"0.000")&" x premiums "&TEXT(Forecast!J60,"0.000") | D28: Forecast
A29: Pensions, retiree health, other benefits | B29: =Forecast!J21+Forecast!J22+Forecast!J23+Forecast!J20 | C29: Town schedules to FY2031, then with payroll; benefits for staff added by growth. | D29: Forecast
A30: Debt within the levy; capital, reserves and other | B30: =Forecast!J24+Forecast!J25 | D30: Forecast
A31: Total spending | B31: =SUM(B25:B30) | D31: Forecast
A32: Room: revenue minus spending | B32: =B23-B31 | D32: Forecast
A33: Check: same as Forecast | B33: =B32-Forecast!J29 | C33: Should be 0.

Sheet Assumptions
A1: Assumptions
A2: Every fixed number the forecast uses. Black values are formulas: measured from the History sheet or worked out from published figures, so you can change the years averaged or a source figure and the whole forecast follows. Blue values are typed from the source named. The settings you are meant to vary are on the Settings sheet; these are the numbers underneath them.
A4: Name | B4: Assumption | C4: Value used | D4: How it is worked out | E4: Source
A6: Property tax: the levy limit and new growth
A7: K_LevyCap | B7: Yearly increase allowed on the levy limit | C7: 0.025 | D7: Proposition 2½: the levy limit rises 2.5% a year, plus new growth and any override. | E7: Massachusetts General Laws c.59 §21C
A8: K_ResTrail | B8: Residential new growth, share of the prior year's levy limit | C8: =ROUND(AVERAGE(History!$S$22:$S$26),5) | D8: Average of FY2022 to FY2026 on History, rounded to 0.001 point. Change the years to test another window. | E8: DLS new growth (History)
A9: K_ComTrail | B9: Commercial, industrial and business equipment new growth, share of the prior levy limit | C9: =ROUND(AVERAGE(History!$U$22:$U$26),5) | D9: Average of FY2022 to FY2026 on History, rounded the same way. | E9: DLS new growth (History)
A10: K_TrendRate | B10: Recent new growth rate, all property | C10: =K_ResTrail+K_ComTrail | D10: The two together. The New growth setting moves the rate up or down from here in tenths of a point.
A11: K_ResNewShare | B11: Share of residential new growth from net new homes (the rest is renovation) | C11: =ROUND(K_HomesPace*K_ResValUnit*K_ResTax/(K_ResTrail*Levy2025),4) | D11: Set so FY2026 carries the recent pace of net new homes at the value each adds. Total residential new growth stays at its trend rate, which has held at 0.8% to 1.0% of the levy whether few or many homes were built; renovation, including houses rebuilt as houses, is the rest. | E11: Building permits and assessment rolls (new_homes_parameters.py)
A12: K_ComNewShare | B12: Share of commercial new growth from new or converted buildings | C12: =ROUND(AVERAGE(History!$G$46:$G$50),4) | D12: Average of FY2021 to FY2025, same table. Most commercial new growth is renovation and fit-out. | E12: Same
A13: K_PP | B13: Business equipment (personal property) new growth, share of the prior levy limit | C13: 0.002407 | D13: Average of FY2022 to FY2026 on History (=AVERAGE(History!$B$55:$B$59) gives 0.24070%), rounded to 0.2407%. Part of the commercial rate above, not added to it. | E13: Board of Assessors classification hearings
A14: K_ResNewPct | B14: New growth rate from new homes | C14: =K_ResTrail*K_ResNewShare | D14: Residential rate times the new-homes share.
A15: K_ResRenoPct | B15: New growth rate from home renovation | C15: =K_ResTrail*(1-K_ResNewShare) | D15: Residential rate times the rest.
A16: K_ComNewPct | B16: New growth rate from new commercial space | C16: =K_ComTrail*K_ComNewShare | D16: Commercial rate times the new-buildings share.
A17: K_ComRenoPct | B17: New growth rate from commercial renovation | C17: =K_ComTrail-K_ComNewPct-K_PP | D17: What is left of the commercial rate after new buildings and equipment.
A18: K_TownNG | B18: New growth in the Town's own plan, each year | C18: 2500000 | D18: The Town's long-range plan assumes a flat $2.5M. For FY2026 to FY2031 the forecast starts from the Town's own property tax figures and adds only the difference its new growth makes; see Revenue build. | E18: Town long-range plan, Jan 2026
A19: K_Perm27 | B19: FY2027 real estate new growth tax the 2024 permits point to, middle of past rates | C19: 1946151 | D19: Taxable permits times the middle of past ratios of new growth to permits, at the FY2026 tax rate. | E19: Town permit records; DLS new growth (permit_leading_indicator.py)
A20: K_Perm27Lo | B20: The same, low end of past rates | C20: 1783406 | E20: Same
A21: K_Perm27Hi | B21: The same, high end of past rates | C21: 2454037 | E21: Same
A22: K_Perm28 | B22: FY2028 real estate new growth tax the 2025 permits point to, middle of past rates | C22: 2037866 | D22: As above. FY2028 is taxed at the FY2027 rate, a little higher after the override, so this runs about 3% low. | E22: Same
A23: K_Perm28Lo | B23: The same, low end of past rates | C23: 1867452 | E23: Same
A24: K_Perm28Hi | B24: The same, high end of past rates | C24: 2569687 | E24: Same
A25: K_NG2026 | B25: New growth in FY2026, as certified | C25: =History!$D$26 | D25: FY2026 is past, so every run uses the certified figure; the rates above apply from FY2027. | E25: DLS new growth (History)
A26: Levy2025 | B26: FY2025 levy, debt exclusions set aside | C26: =History!$G$25-History!$F$25 | D26: Total levy raised less debt exclusion tax. New growth in FY2026 is measured against it. | E26: History
A28: Turning new growth dollars into homes and commercial space
A29: K_HomesPace | B29: Net new homes a year, building permits issued 2016 to 2025 | C29: 104.7 | D29: Every permit read and coded by hand, net of demolitions, assisted living counted separately. | E29: Town building permits (output/permit_homes_by_year.csv)
A30: K_ResValUnit | B30: Assessed value added by one net new home, FY2026 | C30: 585000 | D30: The forecast adds apartments and condominiums, in their 2016 to 2025 proportions (about 80 to 20): apartments add about $521,000 of assessed value per net home and small multifamily and condominium buildings about $864,000, measured on the new-growth basis. | E30: Building permits followed onto the assessment rolls, FY2016 to FY2026
A31: K_ResApp | B31: Yearly rise in the value of a new home | C31: 0.0496 | D31: Town-wide residential value growth net of new growth, FY2018 to FY2024 average. | E31: Assessment rolls
A32: K_ComValSqft | B32: Assessed value per square foot of new commercial space, FY2026 | C32: 518 | D32: Taxable commercial value divided by commercial floor area, weighted (median $529). | E32: Assessment rolls
A33: K_ComApp | B33: Yearly rise in commercial value per square foot | C33: 0.0128 | D33: Town-wide commercial value growth net of new growth, FY2018 to FY2024; volatile in 2020 to 2023. | E33: Assessment rolls
A34: K_ResTax | B34: Residential tax rate, FY2026 (per dollar of value) | C34: 0.009836 | D34: $9.836 per $1,000. | E34: Board of Assessors, FY2026 classification
A35: K_ComTax | B35: Commercial tax rate, FY2026 (per dollar of value) | C35: 0.016238 | D35: $16.238 per $1,000. | E35: Board of Assessors, FY2026 classification
A36: K_ResValShare | B36: Residential share of taxable value, FY2026 | C36: =30758464684/33832309213 | D36: Residential value over all taxable value. | E36: Board of Assessors, FY2026 classification
A37: K_LevyGrowth | B37: Yearly levy growth at the recent pace | C37: =K_LevyCap+K_ResTrail+K_ComTrail | D37: 2.5% plus recent new growth.
A38: K_BlendApp | B38: Yearly rise in taxable value, all property | C38: =K_ResValShare*K_ResApp+(1-K_ResValShare)*K_ComApp | D38: The two value growth rates weighted by value. Tax rates drift by the levy's growth over this.
A40: Local receipts and state aid
A41: K_PermitRate26 | B41: Building permit fee, through FY2026 (share of construction cost) | C41: 0.02 | D41: $20 per $1,000 of estimated cost. | E41: Town fee schedule, 2022
A42: K_PermitRate27 | B42: Building permit fee, from FY2027 | C42: 0.021 | D42: $21 per $1,000, effective July 1, 2026. | E42: Town fee schedule, 2026
A43: K_Permits2025 | B43: Building permit revenue, FY2025 | C43: 4439224 | E43: DLS local receipts, FY2025
A44: K_Inv2019 | B44: Investment income, FY2019 | C44: 1317178 | E44: DLS local receipts
A45: K_Inv2025 | B45: Investment income, FY2025 | C45: 5146469 | D45: Raised by high interest rates on Town cash, including unspent federal pandemic aid. Set aside from the growth rate. | E45: DLS local receipts
A46: K_InvEst2025 | B46: Investment income budgeted, FY2025 | C46: 790593 | E46: DLS local receipts
A47: K_InvFlat | B47: Investment income, each forecast year | C47: 934259 | D47: Held flat at the Town's FY2027 budget for investment income. It is part of the growth-linked receipts row on the Growth sheet. | E47: FY2027 Financial Plan, p. III-98
A48: K_Meals2019 | B48: Meals tax, FY2019 | C48: 1249434 | E48: DLS local receipts
A49: K_Meals2025 | B49: Meals tax, FY2025 | C49: 1768323 | E49: DLS local receipts
A50: K_MealsGrowth | B50: Yearly growth of meals tax at existing restaurants | C50: =ROUND((K_Meals2025/K_Meals2019)^(1/6)-1,4) | D50: FY2019 to FY2025 compound growth, rounded to 0.01 point.
A51: K_MealsPerSqft | B51: Meals tax per square foot of commercial space | C51: =ROUND(K_Meals2025/6364845,4) | D51: FY2025 meals tax over 6,364,845 square feet of taxable commercial space. New commercial space is assumed to bring meals tax at the average rate. | E51: Assessment rolls
A52: R_LRresid2025 | B52: Local receipts not tied to growth, FY2025 | C52: =History!$K$25-K_Meals2025-K_Permits2025-K_Inv2025 | D52: Actual local receipts less meals tax, building permits and investment income, which are forecast separately. | E52: History
A53: R_LRbase | B53: Base case growth of those receipts | C53: =((History!$K$25-K_Meals2025-K_Inv2025)/(History!$K$19-K_Meals2019-K_Inv2019))^(1/6)-1 | D53: FY2019 to FY2025 compound growth, meals tax and investment income set aside. The Local receipts setting starts here. | E53: History
A54: R_SA2026 | B54: State aid, FY2026 | C54: 25915570 | D54: The Town's FY2026 figure. | E54: Town long-range plan
A55: R_SA2027 | B55: State aid, FY2027 | C55: 26693757 | D55: The adopted FY2027 budget. | E55: FY2027 adopted budget
A56: R_SAbase | B56: Base case state aid growth | C56: 0.025 | D56: The rate in the Town's own long-range plan, chosen to be conservative. FY2015 to FY2025 was 3.5%, including FY2019's one-year 8.6% rise; FY2019 to FY2025 was 2.0%. The State aid setting starts here. | E56: Town long-range plan
A58: The free cash cycle
A59: R_BudgetRatio | B59: Local receipts budgeted, as a share of what is collected | C59: =(History!$J$25-K_InvEst2025+K_InvFlat)/(History!$K$25-K_Inv2025+K_InvFlat) | D59: FY2025 budget estimate over actual, with investment income at its flat forecast level on both sides. The Town budgets receipts below what it expects to collect. | E59: History
A60: R_OtherSurplus | B60: Other year-end surplus, share of revenue | C60: =AVERAGE(History!$V$22:$V$25) | D60: Surplus beyond receipts beating budget (unspent appropriations and the like), FY2022 to FY2025 average. Measured on the state's total revenues (actual receipts, no free cash), and applied to the same. | E60: History
A61: R_ApprShare | B61: Share of free cash the Town appropriates | C61: =AVERAGE(Data!$C$37/History!$L$24,18280805/History!$L$25) | D61: Free cash used in the FY2026 budget and the adopted FY2027 budget over the surplus two years earlier; the rest stays in reserves. | E61: Town plan; FY2027 adopted budget; History
A63: Chestnut Hill redevelopment
A64: K_ChcaStart | B64: First fiscal year with Chestnut Hill on the tax roll | C64: 2032 | E64: Forecast assumption
A65: K_ChcaSpan | B65: Years to build out | C65: 3 | D65: A third of the project each year from the first.
A66: K_ChcaDollarYr | B66: Dollar year of the revenue estimates | C66: 2025 | D66: RKG built the model on the FY2025 budget. Each third's property tax enters at its entry year's value (value growth times tax-rate drift, by class), then grows with the levy; rooms tax and excise grow at the base rate of the other local receipts. | E66: ERSC report, Appendix E
A67: K_ChcaUnits | B67: Homes | C67: 266 | E67: Town Meeting approval, May 2026
A68: K_ChcaSPU | B68: School-age children per home | C68: 0.126 | D68: High-rise, mostly studios and one-bedrooms. | E68: Fiscal impact estimate for a comparable high-rise
A69: K_ChcaEmp | B69: Employees | C69: =(79000+105000)/200+200*500/2300 | D69: 184,000 square feet of office and retail at one employee per 200, plus a 200-room hotel. | E69: City Realty scenario 1
A71: Town services
A72: K_pD | B72: Town departments: share of spending that is pay | C72: =History!$E$37/History!$C$37 | D72: The pay table on History. | E72: History; FY2019 Financial Plan
A73: K_psD | B73: Town pay: Public Safety share | C73: =History!$E$33/History!$E$37 | D73: Public Safety's pay over all departments' pay, same table.
A74: K_TownFTE | B74: Town staff, full-time equivalents, FY2027 | C74: 707.47 | E74: FY2027 Financial Plan
A75: K_BasePay | B75: Town pay target | C75: 0.03 | D75: The Pay setting moves every group from here. | E75: Town bargaining target
A76: K_BenLoad | B76: Benefits per dollar of added Town department cost | C76: =262/1109 | D76: RKG's benefits per home over its department cost per home. | E76: RKG fiscal impact study, FY2025
A77: K_CostPerEmp | B77: Town cost per added commercial employee (FY2025 $) | C77: =219*1109/1371 | D77: RKG's $219 per employee, department share only. | E77: RKG fiscal impact study, FY2025
A78: K_SqftPerEmp | B78: Commercial square feet per employee | C78: 200 | E78: RKG fiscal impact study
A79: K_Permit | B79: Planning and permitting staff, FY2027 | C79: =1384996+892085+316790 | D79: Planning and Community Development, Building Code Enforcement and Building Administration. Grows with real-estate new growth above the trend. | E79: FY2027 Financial Plan
A80: K_CIP | B80: Capital policy: share of the prior year's net revenue | C80: 0.066 | D80: 4.5% for debt and 2.1% cash. Held at 6% for FY2026 and FY2027 only. | E80: Select Board policy; FY2027 Financial Plan pp.352, 363, 459
A81: K_NonApp | B81: Non-appropriated items left out of the policy's net revenue, FY2027 | C81: 10792034 | D81: State assessments and the like. | E81: FY2027 Financial Plan p.384
A82: K_NonAppG | B82: Non-appropriated items, yearly growth | C82: 0.0238 | D82: The Town's own table, FY2027 to FY2032. | E82: FY2027 Financial Plan p.384
A83: K_Reserve | B83: Reserve fund: share of the prior year's net revenue | C83: 0.01 | D83: Town policy: 0.75% from the levy and 0.25% from free cash. Applied from FY2028. | E83: Reserve Policies, May 2026 Annual Town Meeting Combined Reports pp.8-8 to 8-9
A84: K_GenFY31 | B84: General non-departmental, FY2031 (Town plan) | C84: =Data!$H$33 | D84: Mostly stabilization and liability fund deposits, whose targets are shares of revenue, so it grows with net revenue after FY2031. | E84: Town long-range plan
A85: K_NonAppFY31 | B85: Non-appropriated items, FY2031 (Town plan) | C85: 11977091 | D85: MBTA and county assessments (capped at 2.5% a year by law) and the overlay. Grows at K_NonAppG after FY2031. | E85: Town long-range plan
A86: K_ActShare | B86: Health plan: share of cost for active employees | C86: 0.64 | D86: Actives follow staffing; retirees grow on their own. Retirees are 49% of subscribers but 36% of cost (many are on Medicare supplement plans). | E86: FY2024 audit retiree benefit payments over FY2024 group health spending
A87: K_RetGrowth | B87: Health plan: yearly growth in retiree subscribers | C87: 0.0092182099 | D87: 1,459 in FY2011 to 1,659 in FY2025. | E87: Financial Plan subscriber tables
A88: K_OPEBStep | B88: Retiree health (OPEB) yearly increase if pension savings are kept | C88: 250000 | D88: The Town plan's own yearly step, FY2026 to FY2030. | E88: Town long-range plan
A89: K_PenNCPrem | B89: Pension normal cost growth above Town pay, after FY2031 | C89: 0.0065 | D89: The actuary's 3.5% payroll growth plus 0.15% for mortality improvement, against the 3.0% pay target. | E89: Brookline Retirement System 2024 valuation, funding schedule notes
A90: K_PenRate | B90: Pension system assumed return | C90: 0.068 | D90: Used to spread FY2030's catch-up payment if full funding slips. | E90: Brookline Retirement System 2024 valuation
A91: K_DebtGrowth | B91: Debt within the levy, yearly growth after FY2032 | C91: 0.035 | D91: Close to revenue growth, as the capital policy ties capital to revenue. | E91: Forecast assumption
A93: Police and fire
A94: K_Homes25 | B94: Homes in town, FY2025 | C94: 28718 | D94: 2020 Census plus about 151 a year. | E94: Census
A95: K_FireHomes | B95: Homes at which a fire company is added | C95: =ROUND(161/5.16*1000,-2) | D95: Brookline's 161 firefighters over the median of 21 nearby cities and towns, 5.16 per 1,000 homes. | E95: Peer staffing, 2020
A96: K_FireCost | B96: A fire company, 20 firefighters a year (FY2025 $, health included) | C96: 3038292 | D96: 20 at $123,639 plus $565,512 overtime at current leave rates. | E96: Fire Department overtime memo, March 2025, p.7
A97: K_PSShare | B97: Police and fire share of the Town cost of a new home | C97: =234/663 | D97: Cross-town estimate. | E97: 350-town spending comparison
A98: K_PSPos | B98: One police or fire position a year (FY2025 $, health included) | C98: 123639 | E98: Fire Department overtime memo, March 2025
A99: K_PSRestoreN | B99: Positions restored: police to 136, fire to 168 | C99: =(136-128)+(168-160) | D99: Police at the FY2018 to FY2020 level, fire at the FY2004 level. | E99: Financial Plans
A100: K_FireSteps | B100: Fire contract: new 5- and 10-year steps, from FY2028 (FY2028 $) | C100: 909471 | D100: Agreed in the 2025 contract; grows with Public Safety pay after FY2028. | E100: ERSC Final Report, March 2026, pp.108-109
A101: K_PolRefill28 | B101: Police positions refilled by FY2028 | C101: 2 | D101: Six positions held open to fund the contract are refilled with the override: two in FY2027 (in the budget), two more in each of FY2028 and FY2029. Already counted when staffing is restored. | E101: Advisory Committee report, May 2026 Combined Reports p.8-19
A102: K_PolRefill29 | B102: Police positions refilled by FY2029 | C102: 4 | E102: Advisory Committee report, May 2026
A103: K_FCDeposit | B103: Free cash deposits: share of general non-departmental | C103: 0.79672405 | D103: Stabilization, liability and housing trust deposits, FY2027: $6.75M of $8.48M. | E103: FY2027 budget as adopted
A104: K_FCReserve | B104: Free cash share of the reserve fund (of prior-year net revenue) | C104: 0.0025 | D104: Free cash never pays for the operating budget; what is left after these uses goes to capital and one-time uses. | E104: Free Cash Policies, May 2026 Combined Reports p.8-8
A105: K_OpebRate | B105: Retiree health liability: interest (discount) rate | C105: 0.069 | D105: The trust's assumed return; the liability grows at this rate too. | E105: FY2024 audit, OPEB note p.84
A106: K_OpebTrendLong | B106: Retiree health: the actuary's long-run premium trend | C106: 0.045 | D106: The liability's service cost and benefits grow at the actuary's trend, not at the premium settings, which move the health insurance line only. | E106: FY2024 audit, OPEB note
A107: K_OpebTol27 | B107: Retiree health total liability, June 30, 2027 | C107: 353188734 | D107: Rolled forward from the FY2024 audit ($301.8M) on the actuary's trend. | E107: FY2024 audit; this model
A108: K_OpebA27 | B108: Retiree health trust, June 30, 2027 | C108: 138909672 | D108: FY2024 audit ($100.3M) plus deposits and 6.90% a year. | E108: FY2024 audit; this model
...

Sheet History
A1: History, FY2005 to FY2025
A2: The record the assumptions are measured from (FY2026: new growth only, as certified). Levy, new growth and overrides: Massachusetts Division of Local Services (DLS) levy limit and new growth reports. Revenue and spending: DLS Schedule A. State aid and local receipts: DLS recap sheets and Local Receipts Actual vs Estimate. Surplus: DLS certified free cash. Grey columns are worked out here.
A4: Fiscal year | B4: Levy limit, prior year | C4: 2.5% increase | D4: New growth applied to the levy | E4: Override | F4: Debt exclusions | G4: Total levy raised | H4: Residential new growth applied | I4: State aid | J4: Local receipts, budget estimate | K4: Local receipts, actual | L4: General Fund surplus (certified free cash basis) | M4: Total revenues, Schedule A | N4: Spending: General Government | O4: Spending: Public Safety | P4: Spending: Public Works | Q4: Spending: Human Services | R4: Spending: Culture and Recreation | S4: Residential new growth, share of prior levy limit | T4: All new growth, share of prior levy limit | U4: Commercial, industrial and business equipment new growth, share | V4: Surplus not from receipts beating budget, share of revenue
A5: 2005 | B5: 112976154 | C5: 2824404 | D5: 2386251 | E5: 0 | F5: 1676384 | G5: 119852046 | H5: 1744877 | I5: 17094030 | L5: -1032557 | M5: 167934717 | N5: 12211085 | O5: 25373371 | P5: 13742331 | Q5: 1652626 | R5: 6481806 | S5: =IFERROR(H5/B5,"") | T5: =IFERROR(D5/B5,"") | U5: =IFERROR(T5-S5,"") | V5: =IFERROR((L5-(K5-J5))/M5,"")
A6: 2006 | B6: 118188364 | C6: 2954709 | D6: 2232945 | E6: 0 | F6: 1648735 | G6: 125014839 | H6: 1621827 | I6: 18027706 | L6: -1357404 | M6: 168890619 | N6: 10787649 | O6: 26195248 | P6: 13221815 | Q6: 1765849 | R6: 7220217 | S6: =IFERROR(H6/B6,"") | T6: =IFERROR(D6/B6,"") | U6: =IFERROR(T6-S6,"") | V6: =IFERROR((L6-(K6-J6))/M6,"")
A7: 2007 | B7: 123389202 | C7: 3084730 | D7: 1989683 | E7: 0 | F7: 1614854 | G7: 130076534 | H7: 1241582 | I7: 18021104 | L7: -142494 | M7: 178383652 | N7: 12219549 | O7: 27115817 | P7: 12908584 | Q7: 1838460 | R7: 7020520 | S7: =IFERROR(H7/B7,"") | T7: =IFERROR(D7/B7,"") | U7: =IFERROR(T7-S7,"") | V7: =IFERROR((L7-(K7-J7))/M7,"")
A8: 2008 | B8: 128463616 | C8: 3211590 | D8: 2584680 | E8: 0 | F8: 1568947 | G8: 135811901 | H8: 2157624 | I8: 18973131 | L8: -913423 | M8: 185803513 | N8: 11203008 | O8: 26915155 | P8: 12454642 | Q8: 1819321 | R8: 7264628 | S8: =IFERROR(H8/B8,"") | T8: =IFERROR(D8/B8,"") | U8: =IFERROR(T8-S8,"") | V8: =IFERROR((L8-(K8-J8))/M8,"")
A9: 2009 | B9: 134259886 | C9: 3356497 | D9: 1828261 | E9: 6200000 | F9: 1692697 | G9: 147273068 | H9: 1306004 | I9: 19623724 | L9: 1826552 | M9: 192482479 | N9: 12366076 | O9: 28141128 | P9: 13670118 | Q9: 1950819 | R9: 6951910 | S9: =IFERROR(H9/B9,"") | T9: =IFERROR(D9/B9,"") | U9: =IFERROR(T9-S9,"") | V9: =IFERROR((L9-(K9-J9))/M9,"")
A10: 2010 | B10: 145644644 | C10: 3641116 | D10: 1762212 | E10: 0 | F10: 1667074 | G10: 152681998 | H10: 1474371 | I10: 16536492 | L10: 8812147 | M10: 195166931 | N10: 9531358 | O10: 27080345 | P10: 10509904 | Q10: 1840552 | R10: 5961909 | S10: =IFERROR(H10/B10,"") | T10: =IFERROR(D10/B10,"") | U10: =IFERROR(T10-S10,"") | V10: =IFERROR((L10-(K10-J10))/M10,"")
A11: 2011 | B11: 151047972 | C11: 3776199 | D11: 1829084 | E11: 0 | F11: 1258944 | G11: 157878286 | H11: 1382518 | I11: 13796542 | L11: 10153141 | M11: 197401346 | N11: 9347954 | O11: 28030700 | P11: 11997166 | Q11: 1992869 | R11: 5863962 | S11: =IFERROR(H11/B11,"") | T11: =IFERROR(D11/B11,"") | U11: =IFERROR(T11-S11,"") | V11: =IFERROR((L11-(K11-J11))/M11,"")
A12: 2012 | B12: 156653255 | C12: 3916331 | D12: 1984224 | E12: 0 | F12: 1090408 | G12: 163620490 | H12: 1565148 | I12: 13383563 | L12: -890993 | M12: 212032653 | N12: 9589942 | O12: 28551429 | P12: 10630118 | Q12: 1973567 | R12: 6151817 | S12: =IFERROR(H12/B12,"") | T12: =IFERROR(D12/B12,"") | U12: =IFERROR(T12-S12,"") | V12: =IFERROR((L12-(K12-J12))/M12,"")
A13: 2013 | B13: 162553810 | C13: 4063845 | D13: 1920101 | E13: 0 | F13: 1630808 | G13: 170137612 | H13: 1578310 | I13: 15131276 | L13: 13901701 | M13: 225013338 | N13: 9818063 | O13: 28793603 | P13: 11529565 | Q13: 2101592 | R13: 6679258 | S13: =IFERROR(H13/B13,"") | T13: =IFERROR(D13/B13,"") | U13: =IFERROR(T13-S13,"") | V13: =IFERROR((L13-(K13-J13))/M13,"")
A14: 2014 | B14: 168537757 | C14: 4213444 | D14: 1935408 | E14: 0 | F14: 1112800 | G14: 175783902 | H14: 1368618 | I14: 16659162 | L14: 10338640 | M14: 223722368 | N14: 10106970 | O14: 29099113 | P14: 12148636 | Q14: 2045258 | R14: 6816841 | S14: =IFERROR(H14/B14,"") | T14: =IFERROR(D14/B14,"") | U14: =IFERROR(T14-S14,"") | V14: =IFERROR((L14-(K14-J14))/M14,"")
A15: 2015 | B15: 174686609 | C15: 4367165 | D15: 2100566 | E15: 0 | F15: 1094400 | G15: 182239297 | H15: 1435526 | I15: 17634875 | L15: 9687851 | M15: 231276828 | N15: 10437557 | O15: 30219418 | P15: 13519758 | Q15: 2138615 | R15: 6868458 | S15: =IFERROR(H15/B15,"") | T15: =IFERROR(D15/B15,"") | U15: =IFERROR(T15-S15,"") | V15: =IFERROR((L15-(K15-J15))/M15,"")
A16: 2016 | B16: 181154340 | C16: 4528858 | D16: 2090726 | E16: 7665000 | F16: 1076000 | G16: 195049924 | H16: 1568178 | I16: 18837306 | L16: 15546838 | M16: 249427185 | N16: 10864873 | O16: 30701920 | P16: 11878933 | Q16: 2185490 | R16: 7014558 | S16: =IFERROR(H16/B16,"") | T16: =IFERROR(D16/B16,"") | U16: =IFERROR(T16-S16,"") | V16: =IFERROR((L16-(K16-J16))/M16,"")
A17: 2017 | B17: 195438924 | C17: 4885973 | D17: 2711620 | E17: 0 | F17: 1048400 | G17: 204064199 | H17: 1842898 | I17: 19657251 | J17: 24212598 | K17: 29013746 | L17: 13613951 | M17: 259094788 | N17: 11619881 | O17: 32523188 | P17: 12311822 | Q17: 2202722 | R17: 7165225 | S17: =IFERROR(H17/B17,"") | T17: =IFERROR(D17/B17,"") | U17: =IFERROR(T17-S17,"") | V17: =IFERROR((L17-(K17-J17))/M17,"")
A18: 2018 | B18: 203036517 | C18: 5075913 | D18: 2264107 | E18: 0 | F18: 1020800 | G18: 211374488 | H18: 1646231 | I18: 20352973 | J18: 29836380 | K18: 36696432 | L18: 12688465 | M18: 269899635 | N18: 11723637 | O18: 32252448 | P18: 13330596 | Q18: 2163588 | R18: 7234336 | S18: =IFERROR(H18/B18,"") | T18: =IFERROR(D18/B18,"") | U18: =IFERROR(T18-S18,"") | V18: =IFERROR((L18-(K18-J18))/M18,"")
A19: 2019 | B19: 210376535 | C19: 5259413 | D19: 2601328 | E19: 6575425 | F19: 3408089 | G19: 224490569 | H19: 1617248 | I19: 22112765 | J19: 30055136 | K19: 36314826 | L19: 14992579 | M19: 285287238 | N19: 12444751 | O19: 34584040 | P19: 13321964 | Q19: 2318926 | R19: 7353301 | S19: =IFERROR(H19/B19,"") | T19: =IFERROR(D19/B19,"") | U19: =IFERROR(T19-S19,"") | V19: =IFERROR((L19-(K19-J19))/M19,"")
A20: 2020 | B20: 224812701 | C20: 5620318 | D20: 2765718 | E20: 0 | F20: 5700171 | G20: 238487743 | H20: 1812547 | I20: 22386947 | J20: 31591215 | K20: 37330419 | L20: 13077815 | M20: 297528480 | N20: 12581935 | O20: 35129432 | P20: 12741652 | Q20: 2362158 | R20: 7515548 | S20: =IFERROR(H20/B20,"") | T20: =IFERROR(D20/B20,"") | U20: =IFERROR(T20-S20,"") | V20: =IFERROR((L20-(K20-J20))/M20,"")
A21: 2021 | B21: 233198737 | C21: 5829968 | D21: 3320392 | E21: 0 | F21: 13369914 | G21: 255719011 | H21: 1792131 | I21: 22388437 | J21: 24909221 | K21: 30743773 | L21: 12262725 | M21: 310021983 | N21: 12790198 | O21: 35067861 | P21: 13221233 | Q21: 2438501 | R21: 7607961 | S21: =IFERROR(H21/B21,"") | T21: =IFERROR(D21/B21,"") | U21: =IFERROR(T21-S21,"") | V21: =IFERROR((L21-(K21-J21))/M21,"")
A22: 2022 | B22: 242349097 | C22: 6058727 | D22: 3458837 | E22: 0 | F22: 20258192 | G22: 272124853 | H22: 1876470 | I22: 22825559 | J22: 26197174 | K22: 36998699 | L22: 24053234 | M22: 339419364 | N22: 12441283 | O22: 36633271 | P22: 13875924 | Q22: 2503622 | R22: 7802448 | S22: =IFERROR(H22/B22,"") | T22: =IFERROR(D22/B22,"") | U22: =IFERROR(T22-S22,"") | V22: =IFERROR((L22-(K22-J22))/M22,"")
A23: 2023 | B23: 251866661 | C23: 6296667 | D23: 2660313 | E23: 0 | F23: 20555634 | G23: 281379275 | H23: 1867685 | I23: 23230992 | J23: 29525786 | K23: 41208035 | L23: 25065431 | M23: 350331838 | N23: 13924496 | O23: 36382869 | P23: 13588421 | Q23: 2425972 | R23: 7958580 | S23: =IFERROR(H23/B23,"") | T23: =IFERROR(D23/B23,"") | U23: =IFERROR(T23-S23,"") | V23: =IFERROR((L23-(K23-J23))/M23,"")
A24: 2024 | B24: 260823641 | C24: 6520591 | D24: 3534463 | E24: 11983367 | F24: 20554161 | G24: 297973561 | H24: 2666497 | I24: 23970474 | J24: 30489569 | K24: 45191956 | L24: 24395985 | M24: 367822295 | N24: 13587487 | O24: 41470109 | P24: 13663245 | Q24: 2627566 | R24: 8273220 | S24: =IFERROR(H24/B24,"") | T24: =IFERROR(D24/B24,"") | U24: =IFERROR(T24-S24,"") | V24: =IFERROR((L24-(K24-J24))/M24,"")
A25: 2025 | B25: 282862062 | C25: 7071552 | D25: 3178133 | E25: 0 | F25: 22012492 | G25: 312568372 | H25: 2519163 | I25: 24973542 | J25: 33050910 | K25: 44398178 | L25: 25306322 | M25: 389982477 | N25: 14585216 | O25: 43497816 | P25: 15080716 | Q25: 2793578 | R25: 8665288 | S25: =IFERROR(H25/B25,"") | T25: =IFERROR(D25/B25,"") | U25: =IFERROR(T25-S25,"") | V25: =IFERROR((L25-(K25-J25))/M25,"")
A26: 2026 | B26: 293111747 | D26: 3561227 | H26: 2425577 | S26: =IFERROR(H26/B26,"") | T26: =IFERROR(D26/B26,"") | U26: =IFERROR(T26-S26,"") | V26: =IFERROR((L26-(K26-J26))/M26,"")
A29: Town departments: how much of spending is pay
A30: Each department's FY2019 salary budget (FY2019 Financial Plan) as a share of its FY2019 spending, applied to FY2025 spending.
A31: Department | B31: Spending FY2019 | C31: Spending FY2025 | D31: Salary budget FY2019 | E31: Pay, FY2025 estimate
A32: General Government | B32: =History!$N$19 | C32: =History!$N$25 | D32: 9688684 | E32: =C32*D32/B32
A33: Public Safety | B33: =History!$O$19 | C33: =History!$O$25 | D33: 29583218 | E33: =C33*D33/B33
A34: Public Works | B34: =History!$P$19 | C34: =History!$P$25 | D34: 8152083 | E34: =C34*D34/B34
A35: Human Services | B35: =History!$Q$19 | C35: =History!$Q$25 | D35: 1935898 | E35: =C35*D35/B35
A36: Culture & Recreation | B36: =History!$R$19 | C36: =History!$R$25 | D36: 3858234 | E36: =C36*D36/B36
A37: Total | C37: =SUM(C32:C36) | E37: =SUM(E32:E36)
A40: New growth by type, FY2018 to FY2025
A41: Value the assessors added from identified new construction (parcel-by-parcel classifier on the assessment rolls, land-value-map), against the total new growth value DLS certified for that class.
A42: Fiscal year | B42: Homes: identified new construction | C42: Homes: all new growth value (DLS) | D42: Homes: new construction share | E42: Commercial: identified new or reclassified | F42: Commercial, industrial and equipment: all new growth value (DLS) | G42: Commercial: new share
A43: 2018 | B43: 41392300 | C43: 166622570 | D43: =B43/C43 | E43: 91200 | F43: 38140470 | G43: =E43/F43
A44: 2019 | B44: 32623500 | C44: 170956400 | D44: =B44/C44 | E44: 0 | F44: 62600476 | G44: =E44/F44
A45: 2020 | B45: 20647900 | C45: 193441475 | D45: =B45/C45 | E45: 2893000 | F45: 62015010 | G45: =E45/F45
A46: 2021 | B46: 88784900 | C46: 189643525 | D46: =B46/C46 | E46: 3037400 | F46: 98407020 | G46: =E46/F46
A47: 2022 | B47: 42919500 | C47: 191476500 | D47: =B47/C47 | E47: 2826400 | F47: 98959780 | G47: =E47/F47
A48: 2023 | B48: 49068000 | C48: 183286030 | D48: =B48/C48 | E48: 0 | F48: 47864008 | G48: =E48/F48
A49: 2024 | B49: 57820300 | C49: 267452056 | D49: =B49/C49 | E49: 0 | F49: 51973982 | G49: =E49/F49
A50: 2025 | B50: 66326600 | C50: 257846768 | D50: =B50/C50 | E50: 2038700 | F50: 40156628 | G50: =E50/F50
A53: Business equipment (personal property) new growth, share of prior levy limit
A54: Board of Assessors, FY2022 to FY2025 Tax Classification Hearing presentations (the only years this split is published).
A55: 2022 | B55: 0.002374
A56: 2023 | B56: 0.002164
A57: 2024 | B57: 0.002629
A58: 2025 | B58: 0.002011
A59: 2026 | B59: 0.002857

Sheet Data
A1: Year-by-year inputs
A2: Schedules the forecast reads year by year: the Town's own long-range plan (January 2026), the FY2027 budget as adopted, the override voters approved in May 2026, and the two enrollment forecasts. The Revenue build and Forecast sheets read them with formulas; nothing here needs editing.
A4: Series | B4: Source | C4: 2026 | D4: 2027 | E4: 2028 | F4: 2029 | G4: 2030 | H4: 2031 | I4: 2032 | J4: 2033 | K4: 2034 | L4: 2035 | M4: 2036 | N4: 2037 | O4: 2038 | P4: 2039 | Q4: 2040
A5: Town plan: property tax, including debt exclusions (before the May 2026 override) | B5: Town long-range plan, Jan 2026 | C5: 332554581 | D5: 349452499 | E5: 360438187 | F5: 371761674 | G5: 382631951 | H5: 393779676
A6: Town plan: debt exclusion tax | B6: Town long-range plan, Jan 2026 | C6: 28596860 | D6: 35379833 | E6: 36013706 | F6: 36726580 | G6: 36720980 | H6: 36720930
A7: Town plan: other available funds | B7: Town long-range plan, Jan 2026 | C7: 4948498 | D7: 4487480 | E7: 4706060 | F7: 4890153 | G7: 5138390 | H7: 4311795
A8: May 2026 override: amount added each year | B8: Override Guide; ballot of May 5, 2026 | D8: 9852330 | E8: 5602871 | F8: 7799238
A9: Override stabilization fund, drawn over three budgets | B9: FY2027 budget as adopted | E9: 1189434.3 | F9: 1189434.3 | G9: 1189434.3
A10: Enrollment, NESDEC projection | B10: NESDEC 2023, scaled to Oct 2025 | C10: 6949 | D10: 6833 | E10: 6661.5193 | F10: 6501.1345 | G10: 6402.2809 | H10: 6262.0703 | I10: 6160.1906 | J10: 6032.0844 | K10: 5892.8825 | L10: 5772.8892 | M10: 5646.0388 | N10: 5550.9518 | O10: 5435.6632 | P10: 5401.7997 | Q10: 5366.2038
A11: Enrollment, NESDEC path: students with 0 years of families moving in | B11: expense_driver_forecast.py | C11: 6949 | D11: 6833 | E11: 260.24712 | F11: 260.24712 | G11: 261.25583 | H11: 261.25583 | I11: 262.26454 | J11: 262.26454 | K11: 262.26454 | L11: 262.26454 | M11: 262.26454 | N11: 262.26454 | O11: 262.26454 | P11: 262.26454 | Q11: 262.26454
A12: Enrollment, NESDEC path: students with 1 year of families moving in | B12: expense_driver_forecast.py | C12: 0 | D12: 0 | E12: 6401.2722 | F12: 0 | G12: 0 | H12: 0 | I12: 0 | J12: 0 | K12: 0 | L12: 0 | M12: 0 | N12: 0 | O12: 0 | P12: 0 | Q12: 0
A13: Enrollment, NESDEC path: students with 2 years of families moving in | B13: expense_driver_forecast.py | C13: 0 | D13: 0 | E13: 0 | F13: 6240.8874 | G13: 0 | H13: 0 | I13: 0 | J13: 0 | K13: 0 | L13: 0 | M13: 0 | N13: 0 | O13: 0 | P13: 0 | Q13: 0
A14: Enrollment, NESDEC path: students with 3 years of families moving in | B14: expense_driver_forecast.py | C14: 0 | D14: 0 | E14: 0 | F14: 0 | G14: 6141.0251 | H14: 0 | I14: 0 | J14: 0 | K14: 0 | L14: 0 | M14: 0 | N14: 0 | O14: 0 | P14: 0 | Q14: 0
A15: Enrollment, NESDEC path: students with 4 years of families moving in | B15: expense_driver_forecast.py | C15: 0 | D15: 0 | E15: 0 | F15: 0 | G15: 0 | H15: 6000.8144 | I15: 0 | J15: 0 | K15: 0 | L15: 0 | M15: 0 | N15: 0 | O15: 0 | P15: 0 | Q15: 0
A16: Enrollment, NESDEC path: students with 5 years of families moving in | B16: expense_driver_forecast.py | C16: 0 | D16: 0 | E16: 0 | F16: 0 | G16: 0 | H16: 0 | I16: 5897.926 | J16: 0 | K16: 0 | L16: 0 | M16: 0 | N16: 0 | O16: 0 | P16: 0 | Q16: 0
A17: Enrollment, NESDEC path: students with 6 years of families moving in | B17: expense_driver_forecast.py | C17: 0 | D17: 0 | E17: 0 | F17: 0 | G17: 0 | H17: 0 | I17: 0 | J17: 5769.8199 | K17: 382.301 | L17: 382.301 | M17: 382.301 | N17: 382.301 | O17: 382.301 | P17: 382.301 | Q17: 382.301
A18: Enrollment, NESDEC path: students with 7 years of families moving in | B18: expense_driver_forecast.py | C18: 0 | D18: 0 | E18: 0 | F18: 0 | G18: 0 | H18: 0 | I18: 0 | J18: 0 | K18: 5248.3169 | L18: 393.78381 | M18: 393.78381 | N18: 393.78381 | O18: 393.78381 | P18: 393.78381 | Q18: 393.78381
A19: Enrollment, NESDEC path: students with 8 years of families moving in | B19: expense_driver_forecast.py | C19: 0 | D19: 0 | E19: 0 | F19: 0 | G19: 0 | H19: 0 | I19: 0 | J19: 0 | K19: 0 | L19: 4734.5398 | M19: 403.21041 | N19: 403.21041 | O19: 403.21041 | P19: 403.21041 | Q19: 403.21041
A20: Enrollment, NESDEC path: students with 9 years of families moving in | B20: expense_driver_forecast.py | C20: 0 | D20: 0 | E20: 0 | F20: 0 | G20: 0 | H20: 0 | I20: 0 | J20: 0 | K20: 0 | L20: 0 | M20: 4204.479 | N20: 403.21041 | O20: 403.21041 | P20: 403.21041 | Q20: 403.21041
A21: Enrollment, NESDEC path: students with 10 years of families moving in | B21: expense_driver_forecast.py | C21: 0 | D21: 0 | E21: 0 | F21: 0 | G21: 0 | H21: 0 | I21: 0 | J21: 0 | K21: 0 | L21: 0 | M21: 0 | N21: 3706.1816 | O21: 407.15204 | P21: 407.15204 | Q21: 407.15204
... A25: Enrollment, Cropper-McKibben (the schools' forecast) | B25: Cropper-McKibben 2023 | C25: 6949 | D25: 6833 | E25: 6802.3765 | F25: 6848.8057 | G25: 6964.3848 | H25: 7031.5591 | I25: 7157.0168 | J25: 7254.8145 | K25: 7353.6001 | L25: 7353.6001 | M25: 7353.6001 | N25: 7353.6001 | O25: 7353.6001 | P25: 7353.6001 | Q25: 7353.6001
A26: Town plan: pensions | B26: Town long-range plan, Jan 2026 | E26: 44290129 | F26: 47766904 | G26: 44088421 | H26: 7276167
A27: Town plan: retiree health (OPEB) | B27: Town long-range plan, Jan 2026 | E27: 5431980 | F27: 5681980 | G27: 5931980 | H27: 42994233
A28: Town plan: other benefits | B28: Town long-range plan, Jan 2026 | E28: 7065901 | F28: 7387023 | G28: 7727010 | H28: 8087057
A29: Capital table: debt within the levy | B29: FY2027 Financial Plan p.384 | E29: 14367683 | F29: 16096302 | G29: 16462008 | H29: 17594808 | I29: 17514813
A30: Town plan: capital, reserves and other | B30: Town long-range plan, Jan 2026 | E30: 43656513 | F30: 44003384 | G30: 45537525 | H30: 46358295 | I30: 48111392 | J30: 49305486 | K30: 50262276 | L30: 51255972 | M30: 52208592 | N30: 53194801 | O30: 54217077 | P30: 55276759 | Q30: 56375242
A31: Town plan: capital funded from revenue | B31: Town long-range plan, Jan 2026 | E31: 10186128 | F31: 9207977 | G31: 9623797 | H31: 9292699 | I31: 10109080 | J31: 10810240 | K31: 11233682 | L31: 11673456 | M31: 12095052 | N31: 12531514 | O31: 12983936 | P31: 13452914 | Q31: 13939064
A32: Town plan: reserve fund | B32: Town long-range plan, Jan 2026 | E32: 3701523 | F32: 3817321 | G32: 3935559 | H32: 4056845
A33: Town plan: general non-departmental | B33: Town long-range plan, Jan 2026 | E33: 8572176 | F33: 8646548 | G33: 8743192 | H33: 8845193
A34: Capital paid from free cash | B34: FY2027 Financial Plan p.384 to FY2032, then a share of net revenue | E34: 10034894 | F34: 10904662 | G34: 11536390 | H34: 12186467 | I34: 13123183 | J34: 13616116 | K34: 14149465 | L34: 14703386 | M34: 15234411 | N34: 15784159 | O34: 16354011 | P34: 16944716 | Q34: 17557049
A35: Retiree health: the actuary's premium trend | B35: FY2024 audit, OPEB note (Medicare and non-Medicare averaged) | E35: 0.055 | F35: 0.0525 | G35: 0.05125 | H35: 0.05 | I35: 0.04875 | J35: 0.0475 | K35: 0.04625
A36: Budgeted local receipts, adopted | B36: FY2026 budget (Town plan) and FY2027 budget as adopted | C36: 34886166 | D36: 37633556
A37: Town plan: free cash | B37: Town long-range plan, Jan 2026 | C37: 21303316 | D37: 20200000 | E37: 20967559 | F37: 21849267 | G37: 22511258 | H37: 23192931
A38: Free cash, known (adopted budget, or the Town plan) | B38: FY2027 adopted; FY2026 Town plan | C38: 21303316 | D38: 18280805
A40: Choices for the settings
A41: Setting | C41: Choice | D41: How the model reads it
A42: opeb | C42: Moved to retiree health (OPEB), the Town's plan; once it's paid off, held for a decision | D42: redirect
C43: Moved to retiree health (OPEB); once it's paid off, counted as room | D43: spend
C44: Kept in the budget as room | D44: keep
A45: staffing | C45: Fall half as fast as enrollment, as in FY2019 to FY2025 | D45: half
C46: Held at the FY2027 level | D46: keep
C47: Follow enrollment, students per staff held | D47: hold
C48: Follow enrollment, students per staff a third back to FY2019 | D48: partial
A49: mix | C49: Today's mix | D49: mix
C50: New homes | D50: housing
C51: New commercial space | D51: commercial
C52: Half homes, half commercial | D52: even
A53: homes | C53: As expected | D53: all
C54: Half as many | D54: half
C55: None: renovation and commercial growth only | D55: none
A56: fill | C56: Each brings new staff at today's ratio | D56: staff
C57: Fill seats left open as enrollment falls | D57: fill
A58: enroll | C58: NESDEC (declines) | D58: nesdec
C59: Flat at FY2027 | D59: flat
C60: Cropper-McKibben, the schools' forecast (rises) | D60: cm
A61: capital | C61: The 6.6% policy, from FY2028 | D61: full
C62: Held at the Town's six-year table, about 6% | D62: table
A63: chca | C63: Approved program, Town Meeting May 2026 | D63: approved
C64: City Realty's average estimate | D64: cr_avg
C65: RKG's estimate | D65: rkg
C66: Already inside trend growth | D66: in_trend
A67: ps_staff | C67: FY2027 budget, plus a fire company at about 31,200 homes | D67: budget
C68: FY2027 budget and the fire company, with police growing with homes | D68: police
C69: Restored to earlier levels, police 136 and fire 168, plus the company | D69: restore
C70: FY2027 budget, no added fire company | D70: none
A71: ng2728 | C71: The recent trend (the base case) | D71: trend
C72: What the 2024 and 2025 permits point to | D72: permits
C73: Permits, low end of past rates | D73: permits_low
C74: Permits, high end of past rates | D74: permits_high
A75: slip | C75: On schedule, FY2030 | D75: 0
C76: One year late | D76: 1
C77: Two years late | D77: 2
C78: Three years late | D78: 3

Sheet Checks
A1: Checks against the Forecast Explorer
A2: The Explorer's own engine, run for the base case, beside this workbook's Forecast sheet. With every setting at its base case the gaps should all be within $5 a year; red marks a larger gap. If you change a setting, the gaps will show the effect of your change instead.
D4: 2027 | E4: 2028 | F4: 2029 | G4: 2030 | H4: 2031 | I4: 2032 | J4: 2033 | K4: 2034 | L4: 2035 | M4: 2036 | N4: 2037 | O4: 2038 | P4: 2039 | Q4: 2040
A5: Explorer engine: total revenue | D5: 415288675 | E5: 4.2853785e+08 | F5: 4.4898678e+08 | G5: 4.6833359e+08 | H5: 4.8280772e+08 | I5: 5.0167823e+08 | J5: 5.2121526e+08 | K5: 5.4166584e+08 | L5: 5.6077435e+08 | M5: 5.8054949e+08 | N5: 6.0093965e+08 | O5: 6.2206856e+08 | P5: 6.4397023e+08 | Q5: 6.6667346e+08
A6: Explorer engine: total spending | D6: 415288675 | E6: 4.2778509e+08 | F6: 4.4445329e+08 | G6: 4.5955636e+08 | H6: 4.747949e+08 | I6: 4.9122931e+08 | J6: 5.0823045e+08 | K6: 5.260038e+08 | L6: 5.4454407e+08 | M6: 5.6367922e+08 | N6: 5.842623e+08 | O6: 6.0544955e+08 | P6: 6.2946036e+08 | Q6: 6.547088e+08
A7: Explorer engine: room | D7: 0 | E7: 752760.78 | F7: 4533487.8 | G7: 8777230.2 | H7: 8012814.8 | I7: 10448920 | J7: 12984816 | K7: 15662040 | L7: 16230287 | M7: 16870273 | N7: 16677355 | O7: 16619010 | P7: 14509868 | Q7: 11964653
A9: Gap: total revenue | D9: =Forecast!D13-D5 | E9: =Forecast!E13-E5 | F9: =Forecast!F13-F5 | G9: =Forecast!G13-G5 | H9: =Forecast!H13-H5 | I9: =Forecast!I13-I5 | J9: =Forecast!J13-J5 | K9: =Forecast!K13-K5 | ... Q9: =Forecast!Q13-Q5
A10: Gap: total spending | D10: =Forecast!D26-D6 | E10: =Forecast!E26-E6 | F10: =Forecast!F26-F6 | G10: =Forecast!G26-G6 | H10: =Forecast!H26-H6 | I10: =Forecast!I26-I6 | J10: =Forecast!J26-J6 | K10: =Forecast!K26-K6 | ... Q10: =Forecast!Q26-Q6
A11: Gap: room | D11: =Forecast!D29-D7 | E11: =Forecast!E29-E7 | F11: =Forecast!F29-F7 | G11: =Forecast!G29-G7 | H11: =Forecast!H29-H7 | I11: =Forecast!I29-I7 | J11: =Forecast!J29-J7 | K11: =Forecast!K29-K7 | ... Q11: =Forecast!Q29-Q7
A13: Largest gap, any year | C13: =MAX(MAX(D9:Q11),-MIN(D9:Q11))

Sheet Appendix History FY05-25
A1: Appendix: history, FY2005 to FY2025
A3: History, not forecast: Massachusetts Division of Local Services Schedule A, Department of Revenue recap data and the Town's audited financial statements, FY2005 to FY2025. The cohort split at the bottom is the one calculated section: it follows property that existed in FY2005 separately from new growth since.
A5: Property Tax Levy Mechanics (Prop 2½)
A6: Line item | C6: FY2005 | D6: FY2006 | E6: FY2007 | F6: FY2008 | G6: FY2009 | H6: FY2010 | I6: FY2011 | J6: FY2012 | K6: FY2013 | L6: FY2014 | M6: FY2015 | N6: FY2016 | O6: FY2017 | P6: FY2018 | Q6: FY2019 | R6: FY2020 | S6: FY2021 | T6: FY2022 | U6: FY2023 | V6: FY2024 | W6: FY2025
A7: Prior year levy limit | C7: 112976154 | D7: 118188364 | E7: 123389202 | F7: 128463616 | G7: 134259886 | H7: 145644644 | I7: 151047972 | J7: 156653255 | K7: 162553810 | L7: 168537757 | M7: 174686609 | N7: 181154340 | O7: 195438924 | P7: 203036517 | Q7: 210376535 | R7: 224812701 | S7: 233198737 | T7: 242349097 | U7: 251866661 | V7: 260823641 | W7: 282862062
A8: 2.5% statutory increase | C8: 2824404 | D8: 2954709 | E8: 3084730 | F8: 3211590 | G8: 3356497 | H8: 3641116 | I8: 3776199 | J8: 3916331 | K8: 4063845 | L8: 4213444 | M8: 4367165 | N8: 4528858 | O8: 4885973 | P8: 5075913 | Q8: 5259413 | R8: 5620318 | S8: 5829968 | T8: 6058727 | U8: 6296667 | V8: 6520591 | W8: 7071552
A9: New growth ($) | C9: 2386251 | D9: 2232945 | E9: 1989683 | F9: 2584680 | G9: 1828261 | H9: 1762212 | I9: 1829084 | J9: 1984224 | K9: 1920101 | L9: 1935408 | M9: 2100566 | N9: 2090726 | O9: 2711620 | P9: 2264017 | Q9: 2601328 | R9: 2765718 | S9: 3320392 | T9: 3458837 | U9: 2660313 | V9: 3534463 | W9: 3178133
A10: Override (voter-approved, this year) | C10: 0 | D10: 0 | E10: 0 | F10: 0 | G10: 6200000 | H10: 0 | I10: 0 | J10: 0 | K10: 0 | L10: 0 | M10: 0 | N10: 7665000 | O10: 0 | P10: 0 | Q10: 6575425 | R10: 0 | S10: 0 | T10: 0 | U10: 0 | V10: 11983367 | W10: 0
A11: Debt exclusion revenue | C11: 1676384 | D11: 1648735 | E11: 1614854 | F11: 1568947 | G11: 1692697 | H11: 1667074 | I11: 1258944 | J11: 1090408 | K11: 1630808 | L11: 1112800 | M11: 1094400 | N11: 1076000 | O11: 1048400 | P11: 1020800 | Q11: 3408089 | R11: 5700171 | S11: 13369914 | T11: 20258192 | U11: 20555634 | V11: 20554161 | W11: 22012492
A12: Excess capacity (allowed but not raised) | C12: -11147 | D12: -9914 | E12: -1935 | F12: -16932 | G12: -64273 | H12: -33048 | I12: -33912 | J12: -23729 | K12: -30953 | L12: -15507 | M12: -9443 | N12: -1465000 | O12: -20718 | P12: -22759 | Q12: -3730221 | R12: -411164 | S12: 0 | T12: 0 | U12: 0 | V12: -5442663 | W12: -2555866
A13: TOTAL LEVY (property tax raised) | C13: =SUM(C7:C12) | D13: =SUM(D7:D12) | E13: =SUM(E7:E12) | F13: =SUM(F7:F12) | G13: =SUM(G7:G12) | H13: =SUM(H7:H12) | I13: =SUM(I7:I12) | J13: =SUM(J7:J12) | ... W13: =SUM(W7:W12)
A15: Revenue
A16: State aid | C16: 17094030 | D16: 18027706 | E16: 18021104 | F16: 18973131 | G16: 19623724 | H16: 16536492 | I16: 13796542 | J16: 13383563 | K16: 15131276 | L16: 16659162 | M16: 17634875 | N16: 18837306 | O16: 19657251 | P16: 20352973 | Q16: 22112765 | R16: 22386947 | S16: 22388437 | T16: 22825559 | U16: 23230992 | V16: 23970474 | W16: 24973542
A17: Local receipts (actual) | O17: 29013746 | P17: 36696432 | Q17: 36314826 | R17: 37330419 | S17: 30743773 | T17: 36998699 | U17: 41208035 | V17: 45191956 | W17: 44398178
A18: Total General Fund revenue | C18: 167934717 | D18: 168890619 | E18: 178383652 | F18: 185803513 | G18: 192482479 | H18: 195166931 | I18: 197401346 | J18: 212032653 | K18: 225013338 | L18: 223722368 | M18: 231276828 | N18: 249427185 | O18: 259094788 | P18: 269899635 | Q18: 285287238 | R18: 297528480 | S18: 310021983 | T18: 339419364 | U18: 350331838 | V18: 367822295 | W18: 389982477
A20: Expense (Schedule A functional categories)
A21: Departmental (Town, ex-schools) | C21: 59461219 | D21: 59190778 | E21: 61102930 | F21: 59656754 | G21: 63080051 | H21: 54924068 | I21: 57232651 | J21: 56896873 | K21: 58922081 | L21: 60216818 | M21: 63183806 | N21: 62645774 | O21: 65822838 | P21: 66704605 | Q21: 70022982 | R21: 70330725 | S21: 71125754 | T21: 73256548 | U21: 74280338 | V21: 79621627 | W21: 84622614
A22: Schools (education) | C22: 60438282 | D22: 62851151 | E22: 65126712 | F22: 68709239 | G22: 73794431 | H22: 74506548 | I22: 77435614 | J22: 80636512 | K22: 83991890 | L22: 87479926 | M22: 91894719 | N22: 101064924 | O22: 106968328 | P22: 110623908 | Q22: 116389275 | R22: 123764357 | S22: 126667840 | T22: 128842776 | U22: 130884869 | V22: 140247931 | W22: 146446110
A23: Benefits (fixed_costs: pensions, health, OPEB) | C23: 30467373 | D23: 29290151 | E23: 32545112 | F23: 34761771 | G23: 35997394 | H23: 39478782 | I23: 37512887 | J23: 54074007 | K23: 45542506 | L23: 50186015 | M23: 50885262 | N23: 54609787 | O23: 56010566 | P23: 60824387 | Q23: 61594549 | R23: 65533832 | S23: 68065399 | T23: 72160184 | U23: 77360296 | V23: 80309607 | W23: 89361296
A24: Debt service (total) | C24: 13247416 | D24: 13831466 | E24: 14268142 | F24: 13824443 | G24: 12290160 | H24: 11886156 | I24: 9491021 | J24: 15662064 | K24: 16549607 | L24: 9304648 | M24: 9403333 | N24: 9276014 | O24: 10255514 | P24: 12577453 | Q24: 15631274 | R24: 17976346 | S24: 25056165 | T24: 34262603 | U24: 35445846 | V24: 35718059 | W24: 36286410
A25: Other (residual) | C25: 5352984 | D25: 5084477 | E25: 5483250 | F25: 9764729 | G25: 5493891 | H25: 5559230 | I25: 5576032 | J25: 5654190 | K25: 6105553 | L25: 6196321 | M25: 6221857 | N25: 6283848 | O25: 6423591 | P25: 6480817 | Q25: 6656579 | R25: 6845405 | S25: 6844100 | T25: 6844019 | U25: 7295058 | V25: 7529086 | W25: 7959725
A26: TOTAL EXPENDITURE | C26: =SUM(C21:C25) | D26: =SUM(D21:D25) | E26: =SUM(E21:E25) | F26: =SUM(F21:F25) | G26: =SUM(G21:G25) | H26: =SUM(H21:H25) | I26: =SUM(I21:I25) | J26: =SUM(J21:J25) | ... W26: =SUM(W21:W25)
A29: Existing (pre-2005) vs. New Property Cohort - live model
A30: Property that existed in FY2005 is followed separately from the new growth added each year after; both grow 2.5% a year plus their share of that year's override, debt exclusion and unused levy capacity. FY2005 is 100% existing property.
A31: Existing: allowed levy limit | C31: =C7+C8+C9+C10 | D31: =(C31*1.025)+D10*D39 | E31: =(D31*1.025)+E10*E39 | F31: =(E31*1.025)+F10*F39 | G31: =(F31*1.025)+G10*G39 | H31: =(G31*1.025)+H10*H39 | I31: =(H31*1.025)+I10*I39 | J31: =(I31*1.025)+J10*J39 | K31: =(J31*1.025)+K10*K39 | ... W31: =(V31*1.025)+W10*W39
A32: Existing: excess-capacity share | C32: =C12 | D32: =D12*D39 | E32: =E12*E39 | F32: =F12*F39 | G32: =G12*G39 | H32: =H12*H39 | I32: =I12*I39 | J32: =J12*J39 | K32: =K12*K39 | ... W32: =W12*W39
A33: Existing: debt-exclusion share | C33: =C11 | D33: =D11*D39 | E33: =E11*E39 | F33: =F11*F39 | G33: =G11*G39 | H33: =H11*H39 | I33: =I11*I39 | J33: =J11*J39 | K33: =K11*K39 | ... W33: =W11*W39
A34: Existing: TOTAL TAX | C34: =SUM(C31,C32,C33) | D34: =SUM(D31,D32,D33) | E34: =SUM(E31,E32,E33) | F34: =SUM(F31,F32,F33) | G34: =SUM(G31,G32,G33) | H34: =SUM(H31,H32,H33) | I34: =SUM(I31,I32,I33) | J34: =SUM(J31,J32,J33) | ... W34: =SUM(W31,W32,W33)
A35: New: allowed levy limit | C35: 0 | D35: =(C35*1.025+D9)+D10*(1-D39) | E35: =(D35*1.025+E9)+E10*(1-E39) | F35: =(E35*1.025+F9)+F10*(1-F39) | G35: =(F35*1.025+G9)+G10*(1-G39) | H35: =(G35*1.025+H9)+H10*(1-H39) | I35: =(H35*1.025+I9)+I10*(1-I39) | J35: =(I35*1.025+J9)+J10*(1-J39) | K35: =(J35*1.025+K9)+K10*(1-K39) | ... W35: =(V35*1.025+W9)+W10*(1-W39)
A36: New: excess-capacity share | C36: 0 | D36: =D12*(1-D39) | E36: =E12*(1-E39) | F36: =F12*(1-F39) | G36: =G12*(1-G39) | H36: =H12*(1-H39) | I36: =I12*(1-I39) | J36: =J12*(1-J39) | K36: =K12*(1-K39) | ... W36: =W12*(1-W39)
A37: New: debt-exclusion share | C37: 0 | D37: =D11*(1-D39) | E37: =E11*(1-E39) | F37: =F11*(1-F39) | G37: =G11*(1-G39) | H37: =H11*(1-H39) | I37: =I11*(1-I39) | J37: =J11*(1-J39) | K37: =K11*(1-K39) | ... W37: =W11*(1-W39)
A38: New: TOTAL TAX | C38: =SUM(C35,C36,C37) | D38: =SUM(D35,D36,D37) | E38: =SUM(E35,E36,E37) | F38: =SUM(F35,F36,F37) | G38: =SUM(G35,G36,G37) | H38: =SUM(H35,H36,H37) | I38: =SUM(I35,I36,I37) | J38: =SUM(J35,J36,J37) | ... W38: =SUM(W35,W36,W37)
A39: Existing share of pre-item total (helper) | C39: 1 | D39: =(C31*1.025)/((C31*1.025)+(C35*1.025+D9)) | E39: =(D31*1.025)/((D31*1.025)+(D35*1.025+E9)) | F39: =(E31*1.025)/((E31*1.025)+(E35*1.025+F9)) | G39: =(F31*1.025)/((F31*1.025)+(F35*1.025+G9)) | H39: =(G31*1.025)/((G31*1.025)+(G35*1.025+H9)) | I39: =(H31*1.025)/((H31*1.025)+(H35*1.025+I9)) | J39: =(I31*1.025)/((I31*1.025)+(I35*1.025+J9)) | K39: =(J31*1.025)/((J31*1.025)+(J35*1.025+K9)) | ... W39: =(V31*1.025)/((V31*1.025)+(V35*1.025+W9))
A40: Check: existing+new vs. total levy (should be $0) | C40: =C34+C38-C13 | D40: =D34+D38-D13 | E40: =E34+E38-E13 | F40: =F34+F38-F13 | G40: =G34+G38-G13 | H40: =H34+H38-H13 | I40: =I34+I38-I13 | J40: =J34+J38-J13 | ... W40: =W34+W38-W13

Sheet Appendix Schools FY09-25
A1: Appendix: schools spending by category, FY2009 to FY2025
A3: History, not forecast: Massachusetts Department of Elementary and Secondary Education spending per pupil by category times actual enrollment each year. This is the state's school spending measure, which counts school staff benefits, so it does not equal the Schedule A schools total.
A5: Line item | C5: FY2009 | D5: FY2010 | E5: FY2011 | F5: FY2012 | G5: FY2013 | H5: FY2014 | I5: FY2015 | J5: FY2016 | K5: FY2017 | L5: FY2018 | M5: FY2019 | N5: FY2020 | O5: FY2021 | P5: FY2022 | Q5: FY2023 | R5: FY2024 | S5: FY2025
A6: Administration | C6: 4860849 | D6: 4692200 | E6: 4970250 | F6: 5273125 | G6: 5504688 | H6: 5371256 | I6: 6404324 | J6: 6517800 | K6: 6748515 | L6: 4969237 | M6: 5082185 | N6: 5708318 | O6: 5836677 | P6: 5764096 | Q6: 9982840 | R6: 7947031 | S6: 7809576
A7: Guidance, Counseling and Testing | C7: 3413340 | D7: 3630792 | E7: 3611715 | F7: 3492500 | G7: 3876040 | H7: 4146872 | I7: 3911668 | J7: 5037876 | K7: 5140260 | L7: 4813217 | M7: 5160735 | N7: 5405015 | O7: 6008952 | P7: 6706304 | Q7: 6396360 | R7: 6581465 | S7: 7788507
A8: Instructional Leadership | C8: 6940458 | D8: 7002704 | E8: 7561407 | F8: 7122500 | G8: 8185912 | H8: 8556112 | I8: 9445064 | J8: 10988244 | K8: 9934245 | L8: 9603031 | M8: 11798210 | N8: 11541068 | O8: 12203961 | P8: 11742960 | Q8: 10801800 | R8: 11079386 | S8: 10583661
A9: Instructional Materials, Equipment and Technology | C9: 2136498 | D9: 2472304 | E9: 3154452 | F9: 2756875 | G9: 2887472 | H9: 2827744 | I9: 3829080 | J9: 4248072 | K9: 4947885 | L9: 5671327 | M9: 4029615 | N9: 3219678 | O9: 3982998 | P9: 4835744 | Q9: 3685320 | R9: 4659818 | S9: 4536858
A10: Insurance, Retirement Programs and Other | C10: 17224725 | D10: 18212208 | E10: 16355436 | F10: 17476250 | G10: 19038824 | H10: 20974864 | I10: 21990932 | J10: 24652620 | K10: 25308855 | L10: 26406385 | M10: 28199450 | N10: 29342621 | O10: 30458220 | P10: 32118208 | Q10: 33782100 | R10: 36025602 | S10: 38759937
A11: Operations and Maintenance | C11: 9734340 | D11: 9364984 | E11: 9576015 | F11: 9576875 | G11: 9658096 | H11: 10239640 | I11: 10413596 | J11: 10804212 | K11: 10965375 | L11: 12520605 | M11: 12497305 | N11: 12707618 | O11: 17317083 | P11: 17195296 | Q11: 13639920 | R11: 14971953 | S11: 16595349
A12: Other Teaching Services | C12: 10353798 | D12: 10821184 | E12: 11159868 | F12: 13818750 | G12: 12986512 | H12: 11413008 | I12: 11359604 | J12: 12659868 | K12: 10873035 | L12: 18519574 | M12: 16888250 | N12: 17817107 | O12: 17999292 | P12: 18677888 | Q12: 19344400 | R12: 21384482 | S12: 22571922
A13: Professional Development | C13: 1536003 | D13: 1598584 | E13: 1895322 | F13: 1980000 | G13: 1678432 | H13: 2047928 | I13: 1997128 | J13: 2377080 | K13: 2331585 | L13: 1170150 | M13: 1036860 | N13: 1088780 | O13: 971631 | P13: 1607296 | Q13: 1736760 | R13: 1274059 | S13: 1207956
A14: Pupil Services | C14: 4304601 | D14: 4743976 | E14: 5208822 | F14: 5706250 | G14: 5796280 | H14: 5385832 | I14: 6329244 | J14: 7345944 | K14: 8072055 | L14: 8440682 | M14: 7407265 | N14: 7668122 | O14: 7042602 | P14: 9505216 | Q14: 12030240 | R14: 12684278 | S14: 12023376
A15: Teachers | C15: 42104181 | D15: 41174864 | E15: 41697084 | F15: 42796875 | G15: 46114208 | H15: 50615160 | I15: 53186672 | J15: 56283120 | K15: 61744680 | L15: 59810267 | M15: 63570515 | N15: 66011176 | O15: 68923782 | P15: 64409616 | Q15: 70381140 | R15: 71213563 | S15: 71866359
A16: TOTAL (in-district spending) | C16: 102602472 | D16: 103707328 | E16: 105190371 | F16: 109993125 | G16: 115733576 | H16: 121571128 | I16: 128874820 | J16: 140907168 | K16: 146066490 | L16: 151924475 | M16: 155678245 | N16: 160509503 | O16: 170752089 | P16: 172562624 | Q16: 181787940 | R16: 187821637 | S16: 193757547
A18: Total enrollment (context; state data) | C18: 6321 | D18: 6472 | E18: 6627 | F18: 6875 | G18: 7112 | H18: 7288 | I18: 7508 | J18: 7668 | K18: 7695 | L18: 7801 | M18: 7855 | N18: 7777 | O18: 6891 | P18: 6928 | Q18: 7060 | R18: 7039 | S18: 7023
A19: Average teacher salary (context, FY2018 on) | L19: 95968 | M19: 98614 | N19: 100041 | O19: 101158 | P19: 104268 | Q19: 115926 | R19: 122329 | S19: 131997

Sheet Appendix Benefits FY23-25
A1: Appendix: benefits by category, FY2023 to FY2025
A3: History, not forecast: the Town's own benefits detail tables from three successive Financial Plans, FY2023 to FY2025.
A5: Line item | C5: FY2023 | D5: FY2024 | E5: FY2025
A6: Pensions (Contributory Retirement) | C6: 30553078 | D6: 33103579 | E6: 37517904
A7: Group Health Insurance (GIC) | C7: 33971831 | D7: 34756062 | E7: 38268676
A8: OPEB (Retiree Group Health Trust) | C8: 4431980 | D8: 4681980 | E8: 5415980
A9: Other (Group Life, Medicare, Workers' Comp, Disability, IOD, Unemployment)
A10: TOTAL BENEFITS | C10: 68956889 | D10: 72541621 | E10: 81202560
