Workbook

Sheet Read me
A1: Growth drivers by budget category, base case
A2: Built 2026-10-14 from the forecast as rebuilt on 2026-10-13 (room $12.4M in FY2031, $7.6M in FY2040). Read-only: nothing in the model was changed.
A4: Basis. Operating basis, the same as the forecast's room: excluded debt is left out of both sides because the debt-exclusion tax pays it dollar for dollar. FY2027 is the budget Town Meeting adopted in May 2026; drivers apply from FY2028.
A5: Sources. Spending: expense_driver_forecast.run(BASE), run in memory, which matches output/expense_driver_forecast_fy26_40.csv. Revenue: the trend_continues scenario of new_growth_scenario_forecast with the approved Chestnut Hill program, the frame the driver forecast uses. Non-departmental detail: output/town_own_forecast_fy26_31.csv and output/baseline_expense_forecast_fy26_40.csv.
A6: Growth columns are compound annual rates between the years shown. FY2027-31 rates include one-time moves (the pension catch-up ending, the OPEB shift, the override's phase-in), so read them with the driver text.
A7: Rows shaded orange are held flat in dollars after FY2031, which means they shrink about 2.5% a year after inflation.
A8: Blue numbers are values read from the model; black cells are formulas. Each sheet ends with a sum check against the model's total.
A10: Sheets
A11: Spending drivers: every spending line, its driver and the numbers behind it.
A12: Revenue drivers: every revenue line, plus memo lines splitting the levy's yearly increase into 2.5%, new growth and the override.
A13: History FY2011-25: what the same categories did in the record, next to the forecast's rate, and the FY2011-25 causes of spending growth.

Sheet Spending drivers
A1: Spending: what drives each line (base case, operating basis)
A2: FY2027 adopted budget; drivers from FY2028. Dollars are nominal.
A4: Group | B4: Category | C4: FY2027 ($) | D4: FY2031 ($) | E4: FY2040 ($) | F4: Share of FY2027 | G4: Growth FY2027-31 (%/yr) | H4: Growth FY2031-40 (%/yr) | I4: What drives it | J4: Numbers the model uses | K4: Held to the Town's plan? | L4: Flag | M4: Source (file:line)
A5: Schools | B5: School Department | C5: 149801900 | D5: 1.7032037e+08 | E5: 2.3021824e+08 | F5: =C5/C$21 | G5: =IF(AND(C5>0,D5>0),(D5/C5)^(1/4)-1,"n/a") | H5: =IF(D5>0,(E5/D5)^(1/9)-1,"n/a") | I5: Staff times pay, plus supplies. 83% of the budget is pay: school staff (held at the FY2027 level, about 1,214, because the base case keeps staff as enrollment falls) times school pay. The other 17% grows with prices and, for its enrollment-linked two-thirds, with enrollment. | J5: School pay 3.7%/yr (3.0% Town target + 0.7 pt for steps, lanes and turnover); CPI 2.5%/yr; staff held at FY2027 ratio (6,889 students / 1,214 staff); enrollment NESDEC rescaled for actual births: 6,889 (FY2027) to 6,313 (FY2031) to about 5,440 (FY2040); 67% of non-pay varies with enrollment. | K5: No. FY2027 is the adopted budget; drivers from FY2028. The Town's plan grows schools about 5%/yr to FY2031. | M5: expense_driver_forecast.py:463 (sch); BASE :245; SCHOOL_PERSONNEL_SHARE :257; SCHOOL_VARIABLE_SHARE :262
A6: Town departments | B6: Public safety personnel (police and fire) | C6: 45502245 | D6: 54262274 | E6: 80638901 | F6: =C6/C$21 | G6: =IF(AND(C6>0,D6>0),(D6/C6)^(1/4)-1,"n/a") | H6: =IF(D6>0,(E6/D6)^(1/9)-1,"n/a") | I6: Police and fire pay: positions held at the FY2027 budget (128 sworn police, 160 fire) times public safety pay. | J6: Public safety pay 4.5%/yr (3.0% target + 1.5 pt, its record above the national benchmark). Public safety is 57.5% of town personnel cost. | K6: No. Adopted FY2027, then drivers. | M6: expense_driver_forecast.py:444 (dep_base, pay_mix); BASE pay_ps_premium :245
A7: Town departments | B7: All other town department costs | C7: 57983879 | D7: 64731986 | E7: 82954729 | F7: =C7/C$21 | G7: =IF(AND(C7>0,D7>0),(D7/C7)^(1/4)-1,"n/a") | H7: =IF(D7>0,(E7/D7)^(1/9)-1,"n/a") | I7: Other town staff pay (headcount held at FY2027's 707 town FTE in total) plus non-personnel spending at inflation. | J7: Pay 3.0%/yr for non-public-safety staff; non-personnel (23.6% of town department spending, FY2019 salary shares) at CPI 2.5%/yr; town FTE flat at 707.5. | K7: No. Adopted FY2027, then drivers. | M7: expense_driver_forecast.py:444; pD/psD from FY2019 salary shares :420-428
A8: Town departments | B8: Costs of growth (new homes, commercial space, fire company, permitting) | C8: 0 | D8: 297021.42 | E8: 1757533.5 | F8: =C8/C$21 | G8: =IF(AND(C8>0,D8>0),(D8/C8)^(1/4)-1,"n/a") | H8: =IF(D8>0,(E8/D8)^(1/9)-1,"n/a") | I8: Service cost added by growth counted from FY2028: a per-home charge for new homes, a per-employee charge for new commercial space and Chestnut Hill, permitting staff above the trend, and a new fire company once homes pass a threshold. | J8: $660 per home (FY2025 $, less fire's share), $177 per commercial employee (1 per 200 sq ft), grown with pay; fire company at 31,200 homes ($3.04M FY2025 $, 20 firefighters), not reached in the base case. | K8: No. | M8: expense_driver_forecast.py:447-452; cost_assumptions.py:38-83
A9: Benefits | B9: Group health insurance (active and retired) | C9: 46364204 | D9: 68831841 | E9: 1.4243271e+08 | F9: =C9/C$21 | G9: =IF(AND(C9>0,D9>0),(D9/C9)^(1/4)-1,"n/a") | H9: =IF(D9>0,(E9/D9)^(1/9)-1,"n/a") | I9: Subscribers times premium. 51% of subscribers are active staff, who follow total town and school FTE (flat); 49% are retirees, growing 0.74%/yr. | J9: Premiums +12%/yr in FY2028 and FY2029 (the Town's figure), then 8%/yr (between the 6.5% 25-year average and the recent 10-12%). | K9: Partly. FY2028-29 premium rate is the Town's; level starts from the adopted FY2027 budget. | M9: expense_driver_forecast.py:341 (prem), :467-468
A10: Benefits | B10: Health and benefit loading for growth staff | C10: 0 | D10: 70170.975 | E10: 415215.31 | F10: =C10/C$21 | G10: =IF(AND(C10>0,D10>0),(D10/C10)^(1/4)-1,"n/a") | H10: =IF(D10>0,(E10/D10)^(1/9)-1,"n/a") | I10: Benefits on the growth-related town staff above. | J10: 23.6% of their pay (262/1,109). | K10: No. | M10: expense_driver_forecast.py:469; cost_assumptions.py:40
A11: Benefits | B11: Pensions | C11: 41167421 | D11: 7276167 | E11: 9493747.6 | F11: =C11/C$21 | G11: =IF(AND(C11>0,D11>0),(D11/C11)^(1/4)-1,"n/a") | H11: =IF(D11>0,(E11/D11)^(1/9)-1,"n/a") | I11: Through FY2031 the Town's actuarial schedule: catch-up payments on the unfunded liability end when the system reaches full funding in FY2030, so the line drops from $44M to the normal cost of about $7.3M in FY2031. After that, normal cost grows with town payroll. | J11: FY2028-31 Town schedule (2024 actuarial valuation); FY2032 on, town pay 3.0%/yr times town FTE (flat). | K11: Yes, FY2028-31 (appropriate: it is the actuarial schedule). Own rule after. | L11: Grows with town payroll at 3.0% only; school staff in the retirement system (non-teachers) and the 4.5% public safety pay are not reflected. Small. | M11: expense_driver_forecast.py:470-477
A12: Benefits | B12: Retiree health (OPEB) contributions | C12: 4931980 | D12: 42994233 | E12: 42994233 | F12: =C12/C$21 | G12: =IF(AND(C12>0,D12>0),(D12/C12)^(1/4)-1,"n/a") | H12: =IF(D12>0,(E12/D12)^(1/9)-1,"n/a") | I12: The Town's funding schedule for the retiree health trust. In FY2031 the money freed from pensions moves here, so the line jumps from $5.9M to $43.0M. | J12: FY2028-30 Town schedule (+$0.25M/yr); FY2031 $42.99M including the pension-to-OPEB shift; flat after. | K12: Yes, through FY2031 (a policy choice the base case makes on purpose). Held flat in dollars FY2032-40. | L12: Flat in dollars FY2032-40 (shrinks about 2.5%/yr after inflation). Deliberate, but worth knowing: the redirected pension money does not grow. | M12: expense_driver_forecast.py:479-488
A13: Benefits | B13: Other benefits (Medicare, workers' comp, injured-on-duty, unemployment, life, disability) | C13: 6659823 | D13: 8087057 | E13: 10573509 | F13: =C13/C$21 | G13: =IF(AND(C13>0,D13>0),(D13/C13)^(1/4)-1,"n/a") | H13: =IF(D13>0,(E13/D13)^(1/9)-1,"n/a") | I13: Mostly the 1.45% Medicare tax on pay and workers' compensation. | J13: FY2028-31 the Town's figures (Medicare grows 6.7%/yr there); FY2032 on, total payroll at 3.0% pay times total FTE. | K13: Yes, FY2028-31, so it follows the Town's payroll, not ours. Own rule after. | L13: FY2028-31 tied to the Town's faster school pay assumption; after FY2031 uses 3.0% pay for all staff, not the 3.7%/4.5% school and public safety rates. A few hundred thousand dollars. | M13: expense_driver_forecast.py:490-498
A14: Capital and debt | B14: Within-levy debt service | C14: 14045480 | D14: 17594808 | E14: 23063664 | F14: =C14/C$21 | G14: =IF(AND(C14>0,D14>0),(D14/C14)^(1/4)-1,"n/a") | H14: =IF(D14>0,(E14/D14)^(1/9)-1,"n/a") | I14: Debt on borrowing the Town pays inside the levy (not voter-approved exclusions). | J14: FY2028-32 the FY2027 Financial Plan's capital funding table (p.384); then +3.5%/yr. | K14: Yes, through FY2032 (the Town's capital table). Own rule after. | M14: expense_driver_forecast.py:500-502
A15: Capital and debt | B15: Cash capital (revenue-financed, free cash and overlay) | C15: 22409889 | D15: 21479166 | E15: 32337217 | F15: =C15/C$21 | G15: =IF(AND(C15>0,D15>0),(D15/C15)^(1/4)-1,"n/a") | H15: =IF(D15>0,(E15/D15)^(1/9)-1,"n/a") | I15: Pay-as-you-go capital projects, funded from revenue and from free cash. | J15: FY2028-32 the Town's capital table; FY2033 on, 2.30% (revenue-financed) plus 2.89% (free cash) of prior-year net revenue. | K15: Yes, through FY2032. Own rule after. | L15: FY2033-40 computed from the September 30 revenue forecast's net revenue, with non-appropriated items held flat, not from the current base case revenue. | M15: baseline_expense_forecast.py (special_appropriations_cip, :740); used at expense_driver_forecast.py:503
A16: Capital and debt | B16: Top-up to the 6.6% capital policy | C16: 0 | D16: 2393395.7 | E16: 3517832.5 | F16: =C16/C$21 | G16: =IF(AND(C16>0,D16>0),(D16/C16)^(1/4)-1,"n/a") | H16: =IF(D16>0,(E16/D16)^(1/9)-1,"n/a") | I16: Extra cash capital so debt plus revenue-financed capital reach 6.6% of prior-year net revenue (4.5% debt + 2.1% cash), the Select Board policy. | J16: 6.6% of prior-year net revenue, where net revenue = total revenue less debt exclusions, free cash and non-appropriated items ($10.79M in FY2027, +2.38%/yr). From FY2028. | K16: No. Base case choice (2026-10-13). | L16: Net revenue grows non-appropriated items 2.38%/yr while the spending line for them is flat after FY2031. | M16: expense_driver_forecast.py:504-510; CIP_POLICY_SHARE :265; NON_APPROP_FY27 :268
A17: Non-departmental | B17: General non-departmental (insurance, audit, stabilization, other) | C17: 7611957 | D17: 8845193 | E17: 8845193 | F17: =C17/C$21 | G17: =IF(AND(C17>0,D17>0),(D17/C17)^(1/4)-1,"n/a") | H17: =IF(D17>0,(E17/D17)^(1/9)-1,"n/a") | I17: Property and liability insurance, audit, stabilization deposits and other Town-wide costs. | J17: FY2028-31 the Town's plan (grows 3.8%/yr FY2027-31); FY2032-40 held at the FY2031 figure, $8.85M. | K17: Yes, FY2028-31. Flat in dollars after. | L17: FLAT IN DOLLARS FY2032-40. | M17: baseline_expense_forecast.py:772-780
A18: Non-departmental | B18: Reserve fund | C18: 3570679 | D18: 4056845 | E18: 4056845 | F18: =C18/C$21 | G18: =IF(AND(C18>0,D18>0),(D18/C18)^(1/4)-1,"n/a") | H18: =IF(D18>0,(E18/D18)^(1/9)-1,"n/a") | I18: The Advisory Committee's fund for unforeseen expenses during the year. | J18: FY2028-31 the Town's plan (3.2%/yr); FY2032-40 held at $4.06M. | K18: Yes, FY2028-31. Flat in dollars after. | L18: FLAT IN DOLLARS FY2032-40. | M18: baseline_expense_forecast.py:773, :780
A19: Non-departmental | B19: Non-appropriated (state and county assessments, MBTA, cherry-sheet offsets, overlay) | C19: 10792034 | D19: 11977091 | E19: 11977091 | F19: =C19/C$21 | G19: =IF(AND(C19>0,D19>0),(D19/C19)^(1/4)-1,"n/a") | H19: =IF(D19>0,(E19/D19)^(1/9)-1,"n/a") | I19: Charges taken off the top before appropriation: state assessments such as the MBTA, charter school tuition and county tax, plus the overlay reserve for abatements. | J19: FY2027 adopted $10.79M; FY2028-31 the Town's plan (2.4%/yr); FY2032-40 held at $11.98M. | K19: Yes, FY2028-31. Flat in dollars after. | L19: FLAT IN DOLLARS FY2032-40, while the capital policy's net revenue grows the same items 2.38%/yr. | M19: baseline_expense_forecast.py:740, :774, :781
A20: Non-departmental | B20: FY2027 one-time and grouping difference (Override Stabilization Fund deposit and other) | C20: 4447184 | D20: 0 | E20: 0 | F20: =C20/C$21 | G20: =IF(AND(C20>0,D20>0),(D20/C20)^(1/4)-1,"n/a") | H20: =IF(D20>0,(E20/D20)^(1/9)-1,"n/a") | I20: The adopted FY2027 budget's general line ($15.61M) includes a $3.57M one-time deposit to the new Override Stabilization Fund (drawn back as revenue FY2028-30) and $15,000 for vocational education; this row is that budget less the Town plan's general and reserve fund lines. | J20: FY2027 only. | K20: n/a | L20: One-time; explains part of the FY2027 to FY2028 drop in non-departmental spending. | M20: fy2027_adopted.py (SUBTOTAL_GENERAL, OVERRIDE_STABILIZATION_FUND)
B21: Total of the categories above | C21: =SUM(C5:C20) | D21: =SUM(D5:D20) | E21: =SUM(E5:E20) | F21: =C21/C21 | G21: =(D21/C21)^(1/4)-1 | H21: =(E21/D21)^(1/9)-1
B22: Model total: operating_expenditure | C22: 415288675 | D22: 4.8321762e+08 | E22: 6.8527667e+08
B23: Difference (sum check, should be $0) | C23: =ROUND(C21-C22,0) | D23: =ROUND(D21-D22,0) | E23: =ROUND(E21-E22,0)

Sheet Revenue drivers
A1: Revenue: what drives each line (base case, operating basis)
A2: Operating revenue excludes the debt-exclusion tax. Dollars are nominal.
A4: Group | B4: Category | C4: FY2027 ($) | D4: FY2031 ($) | E4: FY2040 ($) | F4: Share of FY2027 | G4: Growth FY2027-31 (%/yr) | H4: Growth FY2031-40 (%/yr) | I4: What drives it | J4: Numbers the model uses | K4: Held to the Town's plan? | L4: Flag | M4: Source (file:line)
A5: Property tax | B5: Levy within the limit, excluding the May 2026 override | C5: 316427408 | D5: 3.6736982e+08 | E5: 5.2045731e+08 | F5: =C5/C$11 | G5: =IF(AND(C5>0,D5>0),(D5/C5)^(1/4)-1,"n/a") | H5: =IF(D5>0,(E5/D5)^(1/9)-1,"n/a") | I5: Last year's levy plus 2.5% plus new growth. | J5: FY2026-31: the Town plan's levy (2.5% plus its flat $2.5M of new growth) plus a carried difference for our new growth, diff(t) = diff(t-1) x 1.025 + (new growth - $2.5M). FY2032 on: prior levy x 1.025 + new growth. | K5: Partly, FY2026-31 (delta method on the Town's levy; new growth now measured on our own levy). Own rule after. | M5: new_growth_scenario_forecast.py:790-858
A6: Property tax | B6: May 2026 operating override (cumulative, compounding) | C6: 9852330 | D6: 25102883 | E6: 31350060 | F6: =C6/C$11 | G6: =IF(AND(C6>0,D6>0),(D6/C6)^(1/4)-1,"n/a") | H6: =IF(D6>0,(E6/D6)^(1/9)-1,"n/a") | I6: The override's three tranches, each compounding at 2.5% once in the levy. | J6: $9.85M FY2027, $5.60M FY2028, $7.80M FY2029; then 2.5%/yr. | K6: Uses the override's adopted schedule. | L6: Straight compounding. The forecast's 'room without the override' uses a larger value ($27.3M FY2031, $38.2M FY2040, base_case_decomposition.py:223, written 2026-09-30) that also counts new growth and free cash earned on the larger levy. | M6: new_growth_scenario_forecast.py:210-220
A7: Other revenue | B7: State aid | C7: 26773287 | D7: 30771226 | E7: 42086400 | F7: =C7/C$11 | G7: =IF(AND(C7>0,D7>0),(D7/C7)^(1/4)-1,"n/a") | H7: =IF(D7>0,(E7/D7)^(1/9)-1,"n/a") | I7: Chapter 70 school aid and unrestricted local aid from the state budget. | J7: FY2025 actual x 3.54%/yr, the FY2015-25 growth rate. | K7: No. Own trend from FY2026 (the Town's plan grows it about 2.5%/yr). | L7: Faster than the Town's plan and than FY2011-25 overall (about 4.4%/yr there includes the FY2025 jump; FY2015-25 is 3.5%). | M7: new_growth_scenario_forecast.py:894
A8: Other revenue | B8: Local receipts (budgeted) | C8: 37633556 | D8: 42315554 | E8: 59057614 | F8: =C8/C$11 | G8: =IF(AND(C8>0,D8>0),(D8/C8)^(1/4)-1,"n/a") | H8: =IF(D8>0,(E8/D8)^(1/9)-1,"n/a") | I8: Excise taxes, fees, permits, meals and rooms tax, interest. Budgeted below expected collections; the excess comes back as free cash. | J8: Budget = 74.4% of forecast collections (FY2025 practice). Collections = FY2025 base (ex meals and permits) x 3.31%/yr (FY2019-25) + meals tax 5.96%/yr + building permits at 2.1% of new real estate value + Chestnut Hill rooms tax and excise. FY2027 adopted $37.63M. | K8: No. Own rule from FY2028. | M8: new_growth_scenario_forecast.py:976; revenue_cash_cycle.py:68
A9: Other revenue | B9: Free cash used in the budget | C9: 18280805 | D9: 25786290 | E9: 35629458 | F9: =C9/C$11 | G9: =IF(AND(C9>0,D9>0),(D9/C9)^(1/4)-1,"n/a") | H9: =IF(D9>0,(E9/D9)^(1/9)-1,"n/a") | I9: Last-but-one year's surplus, certified by the state and appropriated two years later. Funds capital and one-time items. | J9: FY2027 adopted $18.28M. Then 83.6% of the surplus two years earlier; surplus = excess receipts + 3.48% of that year's revenue (FY2022-25 average). | K9: No. Own rule from FY2028. | M9: revenue_cash_cycle.py:76-90
A10: Other revenue | B10: Other available funds | C10: 8755561 | D10: 4311795 | E10: 4311795 | F10: =C10/C$11 | G10: =IF(AND(C10>0,D10>0),(D10/C10)^(1/4)-1,"n/a") | H10: =IF(D10>0,(E10/D10)^(1/9)-1,"n/a") | I10: Transfers from other funds (parking, cemetery, stabilization draws). | J10: FY2027 adopted $8.76M; FY2028-31 Town plan plus $1.19M/yr draw of the Override Stabilization Fund FY2028-30; held at $4.31M after FY2031. | K10: Yes, FY2028-31. Flat in dollars after. | L10: FLAT IN DOLLARS FY2032-40 (revenue side; small and cautious). | M10: new_growth_scenario_forecast.py:897-902
B11: Total of the categories above | C11: =SUM(C5:C10) | D11: =SUM(D5:D10) | E11: =SUM(E5:E10) | F11: =C11/C11 | G11: =(D11/C11)^(1/4)-1 | H11: =(E11/D11)^(1/9)-1
B12: Model total: operating_revenue | C12: 417722947 | D12: 495657572 | E12: 692892636
B13: Difference (sum check, should be $0) | C13: =ROUND(C11-C12,0) | D13: =ROUND(D11-D12,0) | E13: =ROUND(E11-E12,0)
B15: Memo lines (not added above)
B16: New growth added in the year (included in the levy above) | C16: 3766984 | D16: 4672519 | E16: 6569452 | G16: =IF(AND(C16>0,D16>0),(D16/C16)^(1/4)-1,"n/a") | H16: =IF(D16>0,(E16/D16)^(1/9)-1,"n/a") | J16: 1.235% of prior levy: new homes 0.207%, home renovation 0.644%, new commercial 0.008%, commercial renovation 0.135%, business equipment 0.241% (FY2022-26 rates); FY2026 certified $3.56M; Chestnut Hill adds $4.54M phased in FY2032-34. | M16: new_growth_scenario_forecast.py:467-537, :756-788
B17: 2.5% increase in the year on the whole levy (derived: levy change less new growth and new override tranche) | C17: 7641476 | D17: 9458542 | E17: 13298485 | G17: =IF(AND(C17>0,D17>0),(D17/C17)^(1/4)-1,"n/a") | H17: =IF(D17>0,(E17/D17)^(1/9)-1,"n/a") | J17: 2.5% of prior levy; FY2027-31 reflects the Town plan's levy. | M17: derived
B18: Debt exclusions (outside the operating comparison, both sides) | C18: 35379833 | D18: 36720930 | E18: 36720930 | G18: =IF(AND(C18>0,D18>0),(D18/C18)^(1/4)-1,"n/a") | H18: =IF(D18>0,(E18/D18)^(1/9)-1,"n/a") | J18: Town plan through FY2031, flat after; matched by excluded debt service. | M18: new_growth_scenario_forecast.py:858

Sheet History FY2011-25
A1: The record: FY2011 to FY2025, next to the forecast
A2: Schedule A categories (state's actual-spending report) do not line up exactly with budget lines; the closest forecast line is named. Forecast rate is FY2027-40.
A4: Group | B4: Category | C4: FY2011 ($) | D4: FY2025 ($) | E4: Growth FY2011-25 (%/yr) | F4: Closest forecast line | G4: Forecast growth FY2027-40 (%/yr) | H4: Note
A5: Spending | B5: Education (Schedule A) | C5: 77435614 | D5: 146446110 | E5: =(D5/C5)^(1/14)-1 | F5: School Department | G5: =('Spending drivers'!E5/'Spending drivers'!C5)^(1/13)-1 | H5: Schedule A education; enrollment 6,627 to 7,023, students per staff 6.75 to 5.62.
A6: Spending | B6: Public safety (Schedule A) | C6: 28030700 | D6: 43497816 | E6: =(D6/C6)^(1/14)-1 | F6: Public safety personnel (police and fire) | G6: =('Spending drivers'!E6/'Spending drivers'!C6)^(1/13)-1
A7: Spending | B7: General government, public works, human services, culture (Schedule A) | C7: 29201951 | D7: 41124798 | E7: =(D7/C7)^(1/14)-1 | F7: All other town department costs | G7: =('Spending drivers'!E7/'Spending drivers'!C7)^(1/13)-1
A8: Spending | B8: Fixed costs, mostly benefits (Schedule A) | C8: 37512887 | D8: 89361296 | E8: =(D8/C8)^(1/14)-1 | H8: Benefits plus insurance; the forecast splits this into health, pensions, OPEB and other benefits (rows below).
A9: Spending | B9: State and county assessments (Schedule A) | C9: 5576032 | D9: 7959725 | E9: =(D9/C9)^(1/14)-1 | F9: Non-appropriated (state and county assessments, MBTA, cherry-sheet offsets, overlay) | G9: =('Spending drivers'!E19/'Spending drivers'!C19)^(1/13)-1
A10: Spending | B10: Debt service, all (Schedule A) | C10: 9491021 | D10: 36286410 | E10: =(D10/C10)^(1/14)-1 | H10: Includes excluded debt for school buildings, which the operating forecast leaves out.
A11: Spending | B11: Total expenditures (Schedule A) | C11: 187248205 | D11: 364676155 | E11: =(D11/C11)^(1/14)-1
A12: Revenue | B12: Prior-year levy limit | C12: 151047972 | D12: 282862062 | E12: =(D12/C12)^(1/14)-1
A13: Revenue | B13: Total levy incl. debt exclusions | C13: 157878286 | D13: 312568372 | E13: =(D13/C13)^(1/14)-1
A14: Revenue | B14: State aid (recap) | C14: 13796542 | D14: 24973542 | E14: =(D14/C14)^(1/14)-1 | F14: State aid | G14: =('Revenue drivers'!E7/'Revenue drivers'!C7)^(1/13)-1
A15: Revenue | B15: Local receipts (recap, budgeted) | C15: 19718475 | D15: 33050910 | E15: =(D15/C15)^(1/14)-1 | F15: Local receipts (budgeted) | G15: =('Revenue drivers'!E8/'Revenue drivers'!C8)^(1/13)-1
A16: Revenue | B16: General Fund surplus (becomes free cash two years later) | C16: 10153141 | D16: 25306322 | E16: =(D16/C16)^(1/14)-1 | F16: Free cash used in the budget | G16: =('Revenue drivers'!E9/'Revenue drivers'!C9)^(1/13)-1 | H16: Surplus, not the free cash appropriated two years later.
A17: Benefits | B17: Group health (reconstructed) | C17: 19390951 | D17: 38268676 | E17: =(D17/C17)^(1/14)-1 | F17: Group health insurance (active and retired) | G17: =('Spending drivers'!E9/'Spending drivers'!C9)^(1/13)-1 | H17: Premium inflation was most of it; staff +316 FTE added the rest.
A18: Benefits | B18: Pension contribution (audited, CY2014 to CY2022) | C18: 18432347 | D18: 31928207 | E18: =(D18/C18)^(1/8)-1 | H18: Growth here was the catch-up on the unfunded liability, which ends at full funding (FY2030); the forecast's FY2032-40 pension is normal cost only, +3.0%/yr.
A19: Revenue | B19: New growth as a share of prior levy limit, FY2011-25 average | E19: 0.012345977 | F19: New growth (memo) | G19: 0.01235 | H19: Range 1.06% to 1.43%. The forecast uses the FY2022-26 rate, 1.235%, before Chestnut Hill.
A22: Causes of the FY2011-25 rise in General Fund spending (output/expense_drivers_tree_fy11_25.csv)
A23: Block | B23: Cause | C23: Dollars ($) | D23: Share of total growth | E23: Note
A24: Town departments | B24: Wage & price inflation | C24: 26209238 | D24: 0.1477 | E24: personnel at national state/local ECI, non-personnel at Boston CPI
A25: Town departments | B25: Staff to serve new homes & commercial space | C25: 1696462 | D25: 0.0096 | E25: 1,251 homes x $1,371 + 1,745 commercial employees x $219 (RKG), department share 81%; benefits counted under Benefits
A26: Town departments | B26: Other staffing change | C26: 2669520 | D26: 0.015 | E26: town FTE +48.9 in total; +18.5 of it at the unvalidated FY2020/21 seam
A27: Town departments | B27: Cost per head above/below inflation | C27: -3185257 | D27: -0.018 | E27: residual: step/grade, turnover, role mix, local pay vs national
A28: Schools | B28: Wage & price inflation | C28: 35666129 | D28: 0.201 | E28: personnel (81%, derived) at the ECI, non-personnel at Boston CPI
A29: Schools | B29: Staff for students from new homes | C29: 4247515 | D29: 0.0239 | E29: 305 students at 0.2442/home, at the FY2011 staff ratio
A30: Schools | B30: Staff for other enrollment change | C30: 1258370 | D30: 0.0071 | E30: net enrollment 6,627 -> 7,023; peaked at 7,855 in FY2019
A31: Schools | B31: Lower students-per-staff ratio | C31: 19548206 | D31: 0.1102 | E31: students per staff FTE 6.75 -> 5.62
A32: Schools | B32: Cost per staff above/below inflation | C32: 8290276 | D32: 0.0467 | E32: residual
A33: Benefits | B33: Health: premium inflation | C33: 12073603 | D33: 0.068 | E33: national state/local ECI benefits index
A34: Benefits | B34: Health: more covered staff | C34: 1242202 | D34: 0.007 | E34: 20% of the +316 town+school FTE change
A35: Benefits | B35: Health: more covered staff | C35: 259238 | D35: 0.0015 | E35: 4% of the +316 town+school FTE change
... A43: Benefits | B43: OPEB trust contributions | C43: 3403449 | D43: 0.0192 | E43: funding-policy transfers into the retiree health trust
A44: Benefits | B44: Other benefits (Medicare tax, workers' comp, IOD, etc.) | C44: 2534593 | D44: 0.0143
A45: Benefits | B45: Other fixed costs & Schedule A reconciling difference | C45: 4006246 | D45: 0.0226 | E45: Schedule A fixed costs minus the Town's benefits detail
A46: Debt service | B46: Voter-approved excluded debt | C46: 20753548 | D46: 0.117 | E46: Devotion, BHS, Driscoll, Pierce, Newbury, fire stations
A47: Debt service | B47: Routine within-levy borrowing | C47: 6041841 | D47: 0.0341
A48: State & MBTA assessments | B48: State, county and MBTA assessments | C48: 2383693 | D48: 0.0134 | E48: outside local control
